Workbook
Name ABC: 'Drop DOwn'!$E$2:$E$23
Name ABC: 'Basic Bullets'!$E$1:$E$20
Name aggregatescore: [1]Sheet2!$N$12
Name auditstatus: 'Drop DOwn'!$I$14:$I$15
Name auditstatus: 'Basic Bullets'!$I$12:$I$13
Name BS: '3. Input-BS '!#REF!
Name BS: '3. Input-BS '!#REF!
Name BS: '3. Input-BS '!#REF!
Name BS: '3. Input-BS '!#REF!
Name BS: '3. Input-BS '!#REF!
Name BS: '3. Input-BS '!#REF!
Name BS: '3. Input-BS '!#REF!
Name BS: '3. Input-BS '!#REF!
Name BS: '3. Input-BS '!#REF!
Name BS: '3. Input-BS '!#REF!
Name BS: '3. Input-BS '!#REF!
Name BS: '3. Input-BS '!#REF!
Name BS: '3. Input-BS '!#REF!
Name BS: '3. Input-BS '!#REF!
Name BS: '3. Input-BS '!#REF!
Name BS: '3. Input-BS '!#REF!
Name BS: '3. Input-BS '!#REF!
Name BS: '3. Input-BS '!#REF!
Name BS: '3. Input-BS '!#REF!
Name BS: '3. Input-BS '!#REF!
Name BS: '3. Input-BS '!#REF!
Name BS: '3. Input-BS '!#REF!
Name BS: '3. Input-BS '!#REF!
Name BS: '3. Input-BS '!#REF!
Name BS: '3. Input-BS '!#REF!
Name BS: '3. Input-BS '!#REF!
Name BS: '3. Input-BS '!#REF!
Name BS: '3. Input-BS '!#REF!
Name cement: '7.Cement'!$K$45
Name ceramic: '8. Ceramic'!$H$44
Name chemical: '5. Chemical'!$E$8
Name cibstatus: 'Drop DOwn'!$K$2:$K$6
Name cibstatus: 'Basic Bullets'!$K$1:$K$4
Name fertilizer: '6. Fertilizer'!$N$38
Name food: '3. Food and Allied'!$I$44
Name InBS: '3. Input-BS '!#REF!
Name InBS: '3. Input-BS '!#REF!
Name InBS: '3. Input-BS '!#REF!
Name InBS: '3. Input-BS '!#REF!
Name InBS: '3. Input-BS '!#REF!
Name InBS: '3. Input-BS '!#REF!
Name InBS: '3. Input-BS '!#REF!
Name InBS: '3. Input-BS '!#REF!
Name InBS: '3. Input-BS '!#REF!
Name InBS: '3. Input-BS '!#REF!
Name InBS: '3. Input-BS '!#REF!
Name InBS: '3. Input-BS '!#REF!
Name InBS: '3. Input-BS '!#REF!
Name InBS: '3. Input-BS '!#REF!
Name InBS: '3. Input-BS '!#REF!
Name InBS: '3. Input-BS '!#REF!
Name InBS: '3. Input-BS '!#REF!
Name InBS: '3. Input-BS '!#REF!
Name InBS: '3. Input-BS '!#REF!
Name InBS: '3. Input-BS '!#REF!

Sheet Title
B2: Guidelines on Internal Credit Risk Rating System for Banks
D36: Bangladesh Bank

Sheet Author
B2: Guidelines on Internal Credit Risk Rating System for Banks

Sheet 1. Index
B2: Internal Credit Risk Rating System for Banks
C4: Index
C6: serial | D6: Contents
C7: 1 | D7: Index
C8: 2 | D8: Top Page
C9: 3 | D9: Input Balance Sheet
C10: 4 | D10: Input Profit & Loss Statement
C11: 5 | D11: Input Cashflow Statement
C12: 6 | D12: Output Balance Sheet
C13: 7 | D13: Output Profit and Loss Statement
C14: 8 | D14: Output Cashflow Statement
C15: 9 | D15: Quantitative Analysis
C16: 10 | D16: Qualitative Analysis
C17: 11 | D17: Detail Management Report
C18: 12 | D18: Executive Summary

Sheet 2. Instructions
B3: SL | C3: Particulars
B4: 1 | C4: This is a Microsoft Macro-enabled Excel Input Template and password protected; please do not try to unlock the sheets as such actions may distort data integrety and may make further processing of data/inputs difficult at the end of Bangladesh Bank.
B5: 2 | C5: At this stage, only 3 (three) input sheets have to filled in; Top Page, Input-BS, Input-IS, Input-CF.
B6: 3 | C6: Only Green marked cells are required to be filled, Blue market cells are Dropdown menue from where appropriate option need to be selected.
B7: 4 | C7: Input fields are subject to validation; therefore, appropriate data format have to be used in the in the relevant fields, for example, in the date fields only date data could be entered; in such fields entering other forms of data will result in error message.
B8: 5 | C8: All three input sheets contain comment boxes wherein relevant comments could be made; if the comments do not fit into the allocated space, please use MS word file and mention on which input sheet the comment will apply.
B9: 6 | C9: Filled in Template has to be sent to BRPD, Bangladesh Bank using email addresses: shah.naoaj@bb.org.bd
B10: 7 | C10: All figures will be in thousand.
B11: 8 | C11: Please use extra sheet for making yourself accustomed to populate data ihe template.
B12: 9 | C12: Enter data in the unlocked cells.
B13: 10 | C13: Please don’t use any sign in Input BS/IS. Use negative sign only in CF if necessay.

Sheet Basic Bullets
E1: 1. RMG | F1: 101 | I1: Partnership
E2: 2. Textile | F2: 102 | I2: Private Ltd
E3: 3. Food and Allied | F3: 103 | I3: Public Ltd
E4: 4. Pharmaceuticals | F4: 104
E5: 5. Chemical | F5: 105
E6: 6. Fertilizer | F6: 106 | K6: Standard
E7: 7. Cement | F7: 107 | K7: SMA
E8: 8. Ceramic | F8: 108 | K8: Doubtful
E9: 9. Ship Building | F9: 109 | K9: Substandard
E10: 10. Ship Breaking | F10: 110 | K10: Bad & Loss
E11: 11. Jute Mills | F11: 111 | I11: Audit Status
E12: 12. Steel Engineering | F12: 112 | I12: Audited
E13: 13. Power and Gas | F13: 113 | I13: Unaudited
E14: 14. Other Industries | F14: 114
E15: B. Trade and commerce | F15: 200
E16: C. Agro based and Agro Processing | F16: 300
E17: 1. Housing and Construction | F17: 401
E18: 2. Telecommunication | F18: 402
E19: 3. Hospitals and Clinics | F19: 403
E20: 4. Other Services | F20: 404

Sheet 2. Top Page
B1: Internal Credit Risk Rating System (Top Page)
B4: Internal Credit Risk Scoring System (ICRSS)
B5: Column1 | C5: Column2 | D5: Column3
B6: Bank Name | C6: : | D6: BRAC Bank PLC
B7: Branch Name | C7: : | D7: Corporate & Institutional Banking
B8: File/ Reference No | C8: : | D8: Outpace Spinning Mills Ltd
B9: Borrower Name | C9: : | D9: Outpace Spinning Mills Ltd | G9: A. Industry (please select sub category) | H9: Error: Please Select Sub Group
B10: Group Name, if any | C10: : | D10: Outright Group | G10: 1. RMG | H10: 101
B11: Type of Industry/ Sector | C11: : | D11: 2. Textile | G11: 2. Textile | H11: 102
B12: Industry Code | C12: : | D12: =INDEX('Basic Bullets'!F:F,MATCH('2. Top Page'!D11,'Basic Bullets'!E:E,0)) -> 102 | G12: 3. Food and Allied | H12: 103
B13: Ownership Type | C13: : | D13: Private Ltd Company | G13: 4. Pharmaceuticals | H13: 104
G14: 5. Chemical | H14: 105
B15: CIB Status | C15: : | D15: Standard | G15: 6. Fertilizer | H15: 106
B16: Financial Statement Audit Status: | C16: : | D16: Unaudited | G16: 7. Cement | H16: 107
B17: Name of Audit Farm | C17: : | D17: Dewan Nazrul Islam & Co. | G17: 8. Ceramic | H17: 108
B18: Credit Officer/Analyst Name, Designation | C18: : | D18: Md. Matiur Rahman, SRM | G18: 9. Ship Building | H18: 109
B19: Verifier Name, Designation | C19: : | D19: Farhana Afrin, SM | G19: 10. Ship Breaking | H19: 110
B20: Date of Financials | D20: 45473 | G20: 11. Jute Mills | H20: 111
B21: Date of Analysis (DD-MM-YYYY) | C21: : | D21: 45652 | G21: 12. Steel Engineering | H21: 112
B22: Date of Verification (DD-MM-YYYY) | C22: : | D22: 45736 | G22: 13. Power and Gas | H22: 113
G23: 14. Other Industries | H23: 114
B24: Legend: | G24: B. Trade and commerce | H24: 200
B25: Inputs to be given | G25: C. Agro based and Agro Processing | H25: 300
B26: Select from Drop down list | G26: D. Service (Please select sub category) | H26: Error: Please Select Sub Group
B27: Auto filled cell | G27: 1. Housing and Construction | H27: 401
G28: 2. Telecommunication | H28: 402
B29: Details of Analyst : | G29: 3. Hospitals and Clinics | H29: 403
B30: Name: | C30: Md. Matiur Rahman | G30: 4. Other Services | H30: 404
B31: Designation: | C31: SRM, Large Corporate
B32: Department/Unit/Cell: | C32: Unit- 04
B33: Phone Number:
B34: Email Address:
B35: Alternate Email Address
B36: Details of Verifier:
B37: Name: | C37: Farhana Afrin
B38: Designation: | C38: Senior Manager
B39: Department/Unit/Cell:
B40: Phone Number:
B41: Email Address:
B42: Alternate Email Address
B54: Sole Proprietorship | D54: Standard
B55: Partnership | D55: SMA
B56: Private Ltd Company | D56: Substandard
B57: Public Ltd Company | D57: Doubtful
B58: Others | D58: Bad&Loss

Sheet 3. Input-BS 
C4: ='2. Top Page'!D9 -> Outpace Spinning Mills Ltd
C5: Balance Sheet
C6: Analyst | E6: ='2. Top Page'!D18 -> Md. Matiur Rahman, SRM
C7: Verifier | E7: ='2. Top Page'!D19 -> Farhana Afrin, SM
C8: Name of Audit Farm | E8: Deawn Nazrul Islam & Co | F8: Deawn Nazrul Islam & Co | G8: Rahman Mustafiz Haw & Co.
C9: Period (months) | E9: 12 | F9: 12 | G9: 12
C10: Amount in thousand | E10: ('000) | F10: ('000) | G10: ('000)
C11: Statement Year | E11: 2025 | F11: 2024 | G11: 2023
C13: Current Assets: | H13: Commono Size
C14: 1 | D14: Inventories (raw materials+work in progress+Finished Goods) | E14: 2716117.7 | F14: 1547239.4 | G14: 1596103.7 | H14: =E14/$E$51 -> 0.68032647
C15: 2 | D15: Trade Debtors/Accounts Receivables | E15: 350127.01 | F15: 943794.93 | G15: 509309.24 | H15: =E15/$E$51 -> 0.08769895
C16: 3 | D16: Advances, Deposits and Prepayments | E16: 70922.706 | F16: =104353.967-F19-F23 -> 71989.994 | G16: =146578.191-G19-G23 -> 112099.51 | H16: =E16/$E$51 -> 0.017764545
C17: 4 | D17: Cash Subsidy Receivable | E17: 0 | F17: 0 | G17: 0 | H17: =E17/$E$51 -> 0
C18: 5 | D18: Other Receivables | E18: 0 | F18: 0 | G18: 0 | H18: =E18/$E$51 -> 0
C19: 6 | D19: Advance Income Tax | E19: 15902.348 | F19: 9694.682 | G19: 14013.878 | H19: =E19/$E$51 -> 0.003983181
F20: 0 | G20: 0 | H20: =E20/$E$51 -> 0
C21: 7 | D21: Interest Receivables | E21: 0 | F21: 0 | G21: 0 | H21: =E21/$E$51 -> 0
C22: 8 | D22: Loan to Associate/Subsidiary/Inter Company Loan | E22: 0 | F22: 0 | G22: 0 | H22: =E22/$E$51 -> 0
C23: 9 | D23: Short Term Loan/Investment | E23: 17389.659 | F23: 22669.291 | G23: 20464.8 | H23: =E23/$E$51 -> 0.004355719
C24: 10 | D24: Inter Company Receivables/Dues | E24: 0 | F24: 0 | G24: 0 | H24: =E24/$E$51 -> 0
C25: 11 | D25: Investments Held for Sale/Marketable Securities | E25: 0 | F25: 0 | G25: 0 | H25: =E25/$E$51 -> 0
C26: 12 | D26: Goods in Transit | E26: 0 | F26: 0 | G26: 0 | H26: =E26/$E$51 -> 0
C27: 13 | D27: Cash & Bank Balance | E27: 18841.322 | F27: 36951.324 | G27: 17409.703 | H27: =E27/$E$51 -> 0.0047193279
C28: 14 | D28: Other Current Assets | E28: 0 | F28: 0 | G28: 0 | H28: =E28/$E$51 -> 0
C29: 15 | D29: Total Current Assets | E29: =SUM(E14:E28) -> 3189300.7 | F29: =SUM(F14:F28) -> 2632339.6 | G29: =SUM(G14:G28) -> 2269400.9 | H29: =E29/$E$51 -> 0.79884819
C30: 16 | D30: Non-Current Assets: | H30: =E30/$E$51 -> 0
C31: 17 | D31: Net Property, Plant and Equipment | E31: 447186.03 | F31: 416976.52 | G31: 293638.33 | H31: =E31/$E$51 -> 0.11201006
C32: 18 | D32: Net Land and Buildings | E32: 0 | F32: 0 | G32: 0 | H32: =E32/$E$51 -> 0
C33: 19 | D33: Net Furniture & Fixture | E33: 0 | F33: 0 | G33: 0 | H33: =E33/$E$51 -> 0
C34: 20 | D34: Net Other Fixed Assets | E34: 0 | F34: 0 | G34: 0 | H34: =E34/$E$51 -> 0
C35: 21 | D35: Goodwill | E35: 0 | F35: 0 | G35: 0 | H35: =E35/$E$51 -> 0
C36: 22 | D36: Trademark/Patent/Software | E36: 0 | F36: 0 | G36: 0 | H36: =E36/$E$51 -> 0
C37: 23 | D37: other Intangible Assets | E37: 0 | F37: 0 | G37: 0 | H37: =E37/$E$51 -> 0
C38: 24 | D38: Investment in Subsidiary and Associates/ Joint Venture | E38: 300000 | F38: 300000 | G38: 300000 | H38: =E38/$E$51 -> 0.075143261
C39: 25 | D39: Investment in Shares/Bond | E39: 0 | F39: 0 | G39: 0 | H39: =E39/$E$51 -> 0
C40: 26 | D40: Other Investments | E40: 0 | F40: 0 | G40: 0 | H40: =E40/$E$51 -> 0
C41: 27 | D41: Deferred Tax Assets | E41: 0 | F41: 0 | G41: 0 | H41: =E41/$E$51 -> 0
C42: 28 | D42: Loan to Subsidiary/Associate | E42: 0 | F42: 0 | G42: 0 | H42: =E42/$E$51 -> 0
... C48: 34 | D48: Other Long Term Receivables | E48: 0 | F48: 0 | G48: 0 | H48: =E48/$E$51 -> 0
C49: 35 | D49: Other Non-Current Assets | E49: 55887.219 | F49: 50013.1 | G49: =327375.554-G38 -> 27375.554 | H49: =E49/$E$51 -> 0.013998493
C50: 36 | D50: Total Non- Current Assets | E50: =SUM(E31:E49) -> 803073.25 | F50: =SUM(F31:F49) -> 766989.62 | G50: =SUM(G31:G49) -> 621013.89 | H50: =E50/$E$51 -> 0.20115181
C51: 37 | D51: Total Assets | E51: =E29+E50 -> 3992374 | F51: =F29+F50 -> 3399329.3 | G51: =G29+G50 -> 2890414.8 | H51: =E51/$E$51 -> 1
D52: Current Liabilities:
C53: 1 | D53: Working Capital Loan | E53: 0 | F53: 0 | G53: 0 | H53: =E53/$E$51 -> 0
C54: 2 | D54: Short Term Loan | E54: =728407.044+2220960.371 -> 2949367.4 | F54: =573913.866+1768890.235 -> 2342804.1 | G54: 1836267.1 | H54: =E54/$E$51 -> 0.73875029
C55: 3 | D55: Bank Overdraft | E55: 0 | F55: 0 | H55: =E55/$E$51 -> 0
C56: 4 | D56: Current Portion of Long Term Borrowing/Loan | E56: 57150.696 | F56: 59269.116 | G56: 56081.808 | H56: =E56/$E$51 -> 0.014314966
C57: 5 | D57: Current Portion of Long Term Lease | E57: 0 | F57: 0 | G57: 0 | H57: =E57/$E$51 -> 0
C58: 6 | D58: Creditors/Liabilites for expenses/ Accrued Expenses | E58: 0 | F58: 0 | G58: 0 | H58: =E58/$E$51 -> 0
C59: 7 | D59: Creditors for goods and services/Accounts Payable/Accruals | E59: 42587.592 | F59: =722061.207-573913.866 -> 148147.34 | G59: 179606.09 | H59: =E59/$E$51 -> 0.010667235
C60: 8 | D60: Creditors for Services | E60: 0 | F60: 0 | G60: 0 | H60: =E60/$E$51 -> 0
C61: 9 | D61: Creditors for Other Finance | E61: 0 | F61: 0 | G61: 0 | H61: =E61/$E$51 -> 0
C62: 10 | D62: Income Taxes Payable | E62: 0 | F62: 0 | G62: 0 | H62: =E62/$E$51 -> 0
C63: 11 | D63: Provision for Tax | E63: 15902.348 | F63: 11393.965 | G63: 19760.428 | H63: =E63/$E$51 -> 0.003983181
C64: 12 | D64: Provision for Royalty and Technical Know-How | E64: 0 | F64: 0 | G64: 0 | H64: =E64/$E$51 -> 0
C65: 13 | D65: Other Provisions | E65: 0 | F65: 0 | G65: 0 | H65: =E65/$E$51 -> 0
C66: 14 | D66: Advance Against Sales | E66: 0 | F66: 0 | G66: 0 | H66: =E66/$E$51 -> 0
C67: 15 | D67: Deferred Liabilities | E67: 0 | F67: 0 | G67: 0 | H67: =E67/$E$51 -> 0
C68: 16 | D68: Accrued Expenses | E68: 0 | F68: 0 | G68: 0 | H68: =E68/$E$51 -> 0
C69: 17 | D69: Interest Payable | E69: 0 | F69: 0 | G69: 0 | H69: =E69/$E$51 -> 0
C70: 18 | D70: Unclaimed Dividend/Dividend Payable | E70: 0 | F70: 0 | G70: 0 | H70: =E70/$E$51 -> 0
C71: 19 | D71: Intercompany Payable/ Dues | E71: 0 | F71: 0 | G71: 0 | H71: =E71/$E$51 -> 0
... C73: 21 | D73: Other Current Liabilities | E73: 0 | F73: 0 | G73: 0 | H73: =E73/$E$51 -> 0
C74: 22 | D74: Total Current Liabilities | E74: =IF(E56=0,"please_insert_value_in_row_56_cur portion of long term loan",(SUM(E53:E73))) -> 3065008.1 | F74: =IF(F56=0,"please_insert_value_in_row_56: curr port of loan",(SUM(F53:F73))) -> 2561614.5 | G74: =IF(G56=0,"please_insert_value_in_row_56: curr port of loan",(SUM(G53:G73))) -> 2091715.4 | H74: =E74/$E$51 -> 0.76771567
D75: Non Current Liabilities: | H75: =E75/$E$51 -> 0
C76: 24 | D76: Long Term Loan | E76: 128649.68 | F76: 116554.8 | G76: 157875.2 | H76: =E76/$E$51 -> 0.032223855
C77: 25 | D77: Deferred Tax Liability | E77: 0 | F77: 0 | G77: 0 | H77: =E77/$E$51 -> 0
C78: 26 | D78: Provision for Employee Benefits (Gratuity) | E78: 0 | F78: 0 | G78: 0 | H78: =E78/$E$51 -> 0
C79: 27 | D79: Bond/ Preference Shares | E79: 0 | F79: 0 | G79: 0 | H79: =E79/$E$51 -> 0
C80: 28 | D80: Long Term Lease | E80: 0 | F80: 0 | G80: 0 | H80: =E80/$E$51 -> 0
C81: 29 | D81: Intercompany Loan | E81: 0 | F81: 0 | G81: 0 | H81: =E81/$E$51 -> 0
C82: 30 | D82: Product Warranties | E82: 0 | F82: 0 | G82: 0 | H82: =E82/$E$51 -> 0
C83: 31 | D83: Deferred Liability | E83: 0 | F83: 0 | G83: 0 | H83: =E83/$E$51 -> 0
C84: 32 | D84: Other Non-Current Liabilities | E84: 0 | F84: 0 | G84: 0 | H84: =E84/$E$51 -> 0
C85: 33 | D85: Total Non-Current Liabilities | E85: =IF(E76=0,"please_insert_value_in_row_76:long term loan",(SUM(E76:E84))) -> 128649.68 | F85: =IF(F76=0,"please_insert_value_in_row_76:long term loan",(SUM(F76:F84))) -> 116554.8 | G85: =IF(G76=0,"please_insert_value_in_row_76:long term loan",(SUM(G76:G84))) -> 157875.2 | H85: =E85/$E$51 -> 0.032223855
C86: 34 | D86: Total Liabilities | E86: =E74+E85 -> 3193657.7 | F86: =F74+F85 -> 2678169.3 | G86: =G74+G85 -> 2249590.6 | H86: =E86/$E$51 -> 0.79993952
D87: Equities | H87: =E87/$E$51 -> 0
C88: 36 | D88: Paid-Up Capital/ Share Capital | E88: 184000 | F88: 184000 | G88: 173200 | H88: =E88/$E$51 -> 0.046087867
C89: 37 | D89: Share Premium Account | E89: 0 | F89: 0 | G89: 0 | H89: =E89/$E$51 -> 0
C90: 38 | D90: Retained Earnings | E90: 614716.24 | F90: 537159.94 | G90: 467624.14 | H90: =E90/$E$51 -> 0.15397261
C91: 39 | D91: Fair Value Gain on Investment/ Unrealised gain from available for sale investments | E91: 0 | F91: 0 | G91: 0 | H91: =E91/$E$51 -> 0
C92: 40 | D92: Share Money Deposit | E92: 0 | F92: 0 | G92: 0 | H92: =E92/$E$51 -> 0
C93: 41 | D93: Tax Holiday Reserve | E93: 0 | F93: 0 | G93: 0 | H93: =E93/$E$51 -> 0
C94: 42 | D94: General Reserve | E94: 0 | F94: 0 | G94: 0 | H94: =E94/$E$51 -> 0
C95: 43 | D95: Revaluation Reserve | E95: 0 | F95: 0 | G95: 0 | H95: =E95/$E$51 -> 0
C96: 44 | D96: Dividend Equalization Reserve | E96: 0 | F96: 0 | G96: 0 | H96: =E96/$E$51 -> 0
C97: 45 | D97: Other Reserves | E97: 0 | F97: 0 | G97: 0 | H97: =E97/$E$51 -> 0
C98: 46 | D98: Other Equity Items | E98: 0 | F98: 0 | G98: 0 | H98: =E98/$E$51 -> 0
C99: 47 | D99: Total Equity | E99: =SUM(E88:E98) -> 798716.24 | F99: =SUM(F88:F98) -> 721159.94 | G99: =SUM(G88:G98) -> 640824.14 | H99: =E99/$E$51 -> 0.20006048
C100: 48 | D100: Minority Interest | E100: 0 | F100: 0 | G100: 0 | H100: =E100/$E$51 -> 0
C101: 49 | D101: Total Equity & Liabilities | E101: =E100+E99+E86 -> 3992374 | F101: =F100+F99+F86 -> 3399329.3 | G101: =G100+G99+G86 -> 2890414.8 | H101: =E101/$E$51 -> 1
E102: =IF(E101=E51,TRUE) -> TRUE | F102: =IF(F101=F51,TRUE) -> TRUE | G102: =IF(G101=G51,TRUE) -> TRUE
D103: Assets- Liabilities difference | E103: =E51-E101 -> 0 | F103: =F51-F101 -> 0 | G103: =G51-G101 -> 0

Sheet 4. Input P&L
C2: ='2. Top Page'!D9 -> Outpace Spinning Mills Ltd
C3: Profit & Loss Statement
C4: Analyst | E4: ='2. Top Page'!D18 -> Md. Matiur Rahman, SRM
C5: Verifier | E5: ='2. Top Page'!D19 -> Farhana Afrin, SM
C6: Name of Audit Farm | E6: ='3. Input-BS '!E8 -> Deawn Nazrul Islam & Co | F6: ='3. Input-BS '!F8 -> Deawn Nazrul Islam & Co | G6: ='3. Input-BS '!G8 -> Rahman Mustafiz Haw & Co.
C7: Period (months) | E7: ='3. Input-BS '!E9 -> 12 | F7: ='3. Input-BS '!F9 -> 12 | G7: ='3. Input-BS '!G9 -> 12
C8: Amount in thousand | E8: ('000) | F8: ('000) | G8: ('000)
C9: Statement Year | E9: ='3. Input-BS '!E11 -> 2025 | F9: ='3. Input-BS '!F11 -> 2024 | G9: ='3. Input-BS '!G11 -> 2023
H10: Common Size
C11: 1 | D11: Sales /Revenue/Turnover | E11: 1412760.6 | F11: 1736066.4 | G11: 1396131.3 | H11: =E11/$E$11 -> 1
C12: 2 | D12: VAT & Supplementary Duty | E12: 0 | F12: 0 | G12: 0 | H12: =E12/$E$11 -> 0
C13: 3 | D13: Net Sales/Revenue | E13: =E11-E12 -> 1412760.6 | F13: =IFERROR(F11-F12,"recheck") -> 1736066.4 | G13: =IFERROR(G11-G12,"recheck") -> 1396131.3 | H13: =E13/$E$11 -> 1
C14: 4 | D14: Cost of Goods/Service Sold | E14: =1207915.521-E19 -> 1187045.5 | F14: =1493014.199-F19 -> 1473623.9 | G14: =1157634.474-G19 -> 1144305.5 | H14: =E14/$E$11 -> 0.84023119
C15: 5 | D15: Gross Profit | E15: =E13-E14 -> 225715.08 | F15: =F13-F14 -> 262442.55 | G15: =G13-G14 -> 251825.83 | H15: =E15/$E$11 -> 0.15976881
C16: 6 | D16: Salaries | E16: 0 | F16: 0 | G16: 0 | H16: =E16/$E$11 -> 0
C17: 7 | D17: Marketing, Selling & Distribution Expenses | E17: 3381.175 | F17: 4765.77 | G17: 34597.824 | H17: =E17/$E$11 -> 0.0023933107
C18: 8 | D18: Administrative Expenses | E18: 29692.632 | F18: 41358.161 | G18: 4194.973 | H18: =E18/$E$11 -> 0.021017455
C19: 9 | D19: Depreciation/ Amortization | E19: 20870.038 | F19: 19390.317 | G19: 13328.984 | H19: =E19/$E$11 -> 0.014772523
C20: 10 | D20: Other Operating Expense | E20: 0 | F20: 0 | G20: 0 | H20: =E20/$E$11 -> 0
C21: 11 | D21: Total Operating Expenses | E21: =SUM(E16:E20) -> 53943.845 | F21: =SUM(F16:F20) -> 65514.248 | G21: =SUM(G16:G20) -> 52121.781 | H21: =E21/$E$11 -> 0.038183289
C22: 12 | D22: Other Operating Income | E22: 0 | F22: 0 | G22: 0 | H22: =E22/$E$11 -> 0
C23: 13 | D23: Operating Profit | E23: =E15+E22-E21 -> 171771.23 | F23: =F15-F21+F22 -> 196928.31 | G23: =G15-G21+G22 -> 199704.05 | H23: =E23/$E$11 -> 0.12158552
C24: 14 | D24: Exchange Gain | E24: 0 | F24: 0 | G24: 0 | H24: =E24/$E$11 -> 0
C25: 15 | D25: Exchang Loss | E25: 0 | F25: 0 | G25: 0 | H25: =E25/$E$11 -> 0
C26: 16 | D26: Investment/Interest Income | E26: 0 | F26: 0 | G26: 0 | H26: =E26/$E$11 -> 0
C27: 17 | D27: Rental Income | E27: 0 | F27: 0 | G27: 0 | H27: =E27/$E$11 -> 0
C28: 18 | D28: Gain on Disposals of Fixed Assets | E28: 0 | F28: 0 | G28: 0 | H28: =E28/$E$11 -> 0
C29: 19 | D29: Loss on Disposals of Fixed Assets | E29: 0 | F29: 0 | G29: 0 | H29: =E29/$E$11 -> 0
C30: 20 | D30: Surplus on Revaluation of Property | E30: 0 | F30: 0 | G30: 0 | H30: =E30/$E$11 -> 0
C31: 21 | D31: Deficit on Revaluation of Property | E31: 0 | F31: 0 | G31: 0 | H31: =E31/$E$11 -> 0
C32: 22 | D32: Other Income | E32: 1975.013 | F32: 2785.613 | G32: 738.384 | H32: =E32/$E$11 -> 0.0013979814
C33: 23 | D33: Other Expenses | E33: 0 | F33: 0 | G33: 0 | H33: =E33/$E$11 -> 0
C34: 24 | D34: Provision For Welfare and profit participation fund | E34: 0 | F34: 0 | G34: 0 | H34: =E34/$E$11 -> 0
C35: 25 | D35: Share of profit from associates | E35: 0 | F35: 0 | G35: 0 | H35: =E35/$E$11 -> 0
C36: 26 | D36: Share of loss from associates | E36: 0 | F36: 0 | G36: 0 | H36: =E36/$E$11 -> 0
C37: 27 | D37: Earnings Before Interest and Tax (EBIT) | E37: =E23+E24-E25+E26+E27+E28-E29+E30-E31+E32-E33-E34+E35-E36 -> 173746.24 | F37: =F23+F24-F25+F26+F27+F28-F29+F30-F31+F32-F33-F34+F35-F36 -> 199713.92 | G37: =G23+G24-G25+G26+G27+G28-G29+G30-G31+G32-G33-G34+G35-G36 -> 200442.43 | H37: =E37/$E$11 -> 0.1229835
C38: 28 | D38: Financial/Interest Expenses | E38: 80287.596 | F38: 118784.16 | G38: 68706.248 | H38: =E38/$E$11 -> 0.056830293
C39: 29 | D39: Earnings Before Tax (EBT) | E39: =IF(E38=0,"please_insert_value_in_row_38: Financial/Interest Expenses",E37-E38) -> 93458.648 | F39: =IF(F38=0,"please_insert_value_in_row_38: Financial/Interest Expenses",F37-F38) -> 80929.762 | G39: =IF(G38=0,"please_insert_value_in_row_38: Financial/Interest Expenses",G37-G38) -> 131736.19 | H39: =E39/$E$11 -> 0.066153211
C40: 30 | D40: Current Tax | E40: 15902.348 | F40: 11393.965 | G40: 19760.428 | H40: =E40/$E$11 -> 0.011256223
C41: 31 | D41: Deferred Tax/ Advance Tax Expense | E41: 0 | F41: 0 | H41: =E41/$E$11 -> 0
C42: 32 | D42: Deferred Tax/Advance Tax Income | E42: 0 | F42: 0 | G42: 0 | H42: =E42/$E$11 -> 0
C43: 33 | D43: Total Tax | E43: =E40+E41-E42 -> 15902.348 | F43: =F40+F41-F42 -> 11393.965 | G43: =G40+G41-G42 -> 19760.428 | H43: =E43/$E$11 -> 0.011256223
C44: 34 | D44: Net Profit After Tax (NPAT) | E44: =IF(E38=0,"please_insert_value_in_row_38: Financial/Interest Expenses",(E39-E43)) -> 77556.3 | F44: =IF(F38=0,"please_insert_value_in_row_38: Financial/Interest Expenses",(F39-F43)) -> 69535.797 | G44: =IF(G38=0,"please_insert_value_in_row_38: Financial/Interest Expenses",(G39-G43)) -> 111975.76 | H44: =E44/$E$11 -> 0.054896988
C45: 35 | D45: Extraordinary Income/ Other Comprehensive Income | E45: 0 | F45: 0 | G45: 0 | H45: =E45/$E$11 -> 0
C46: 36 | D46: Extraordinary Expenses/ Other Comprehensive Expense | E46: 0 | F46: 0 | G46: 0 | H46: =E46/$E$11 -> 0
C47: 37 | D47: Total Comprehensive Income | E47: =E44+E45-E46 -> 77556.3 | F47: =F44+F45-F46 -> 69535.797 | G47: =G44+G45-G46 -> 111975.76 | H47: =E47/$E$11 -> 0.054896988
D49: Note:
D50: 1. don’t use any sign with figures.
D51: Example: Cost of Good sold is 900; here just input 900 instead of -900 or (900)

Sheet 5. Input-CF
C2: ='2. Top Page'!D9 -> Outpace Spinning Mills Ltd
C3: Cash Flow Statement
C4: Analyst | E4: ='2. Top Page'!D18 -> Md. Matiur Rahman, SRM
C5: Verifier | E5: ='2. Top Page'!D19 -> Farhana Afrin, SM
C6: Name of the Audit Farm | E6: ='3. Input-BS '!E8 -> Deawn Nazrul Islam & Co | F6: ='3. Input-BS '!F8 -> Deawn Nazrul Islam & Co | G6: ='3. Input-BS '!G8 -> Rahman Mustafiz Haw & Co.
C7: Period (months) | E7: ='3. Input-BS '!E9 -> 12 | F7: ='3. Input-BS '!F9 -> 12 | G7: ='3. Input-BS '!G9 -> 12
C8: Amount in thousand | E8: ('000) | F8: ('000) | G8: ('000)
C10: Year | E10: ='3. Input-BS '!E11 -> 2025 | F10: ='3. Input-BS '!F11 -> 2024 | G10: ='3. Input-BS '!G11 -> 2023
C11: A. | D11: Net cash flows from operating activities | E11: 105171.03 | F11: 398401.77 | G11: -723188.92
C12: B. | D12: Net cash flows from investing activities | E12: -56953.665 | F12: -165366.05 | G12: -20827.202
C13: C. | D13: Net cash flows from financing activities | E13: -66327.363 | F13: -213494.1 | G13: 748507.59
C14: D. | D14: Net inflow of cash and cash equivalents | E14: =SUM(E11:E13) -> -18110.002 | F14: =SUM(F11:F13) -> 19541.621 | G14: =SUM(G11:G13) -> 4491.471
C15: E. | D15: Cash and cash equivalent at opening | E15: 36951.324 | F15: 17409.703 | G15: 12918.232
C16: F | D16: Cash and cash equivalent at closing | E16: =E14+E15 -> 18841.322 | F16: =F14+F15 -> 36951.324 | G16: =G14+G15 -> 17409.703
C18: Note: Please use sign (+/-) with the figures if needed.
D19: Example: if cash flow from operation is negative 100 provide input -100.

Sheet 6. Output-BS
C2: ='2. Top Page'!D9 -> Outpace Spinning Mills Ltd
C3: ='3. Input-BS '!C5:G5 -> Balance Sheet
C4: ='3. Input-BS '!C6:D6 -> Analyst | E4: ='2. Top Page'!D18 -> Md. Matiur Rahman, SRM
C5: Verifier | E5: ='2. Top Page'!D19 -> Farhana Afrin, SM
C6: ='3. Input-BS '!C8:D8 -> Name of Audit Farm | E6: ='3. Input-BS '!E8 -> Deawn Nazrul Islam & Co | F6: ='3. Input-BS '!F8 -> Deawn Nazrul Islam & Co | G6: ='3. Input-BS '!G8 -> Rahman Mustafiz Haw & Co.
C7: ='3. Input-BS '!C9:D9 -> Period (months) | E7: ='3. Input-BS '!E9 -> 12 | F7: ='3. Input-BS '!F9 -> 12 | G7: ='3. Input-BS '!G9 -> 12
C8: ='3. Input-BS '!C10:D10 -> Amount in thousand | E8: ='3. Input-BS '!E10 -> ('000) | F8: ='3. Input-BS '!F10 -> ('000) | G8: ='3. Input-BS '!G10 -> ('000)
C9: ='3. Input-BS '!C11:D11 -> Statement Year | E9: ='3. Input-BS '!E11 -> 2025 | F9: ='3. Input-BS '!F11 -> 2024 | G9: ='3. Input-BS '!G11 -> 2023
C11: ='3. Input-BS '!C13:D13 -> Current Assets:
C12: ='3. Input-BS '!C14 -> 1 | D12: ='3. Input-BS '!D14 -> Inventories (raw materials+work in progress+Finished Goods) | E12: ='3. Input-BS '!E14 -> 2716117.7 | F12: ='3. Input-BS '!F14 -> 1547239.4 | G12: ='3. Input-BS '!G14 -> 1596103.7
C13: ='3. Input-BS '!C15 -> 2 | D13: ='3. Input-BS '!D15 -> Trade Debtors/Accounts Receivables | E13: ='3. Input-BS '!E15 -> 350127.01 | F13: ='3. Input-BS '!F15 -> 943794.93 | G13: ='3. Input-BS '!G15 -> 509309.24
C14: ='3. Input-BS '!C16 -> 3 | D14: ='3. Input-BS '!D16 -> Advances, Deposits and Prepayments | E14: ='3. Input-BS '!E16 -> 70922.706 | F14: ='3. Input-BS '!F16 -> 71989.994 | G14: ='3. Input-BS '!G16 -> 112099.51
C15: ='3. Input-BS '!C17 -> 4 | D15: ='3. Input-BS '!D17 -> Cash Subsidy Receivable | E15: ='3. Input-BS '!E17 -> 0 | F15: ='3. Input-BS '!F17 -> 0 | G15: ='3. Input-BS '!G17 -> 0
C16: ='3. Input-BS '!C18 -> 5 | D16: ='3. Input-BS '!D18 -> Other Receivables | E16: ='3. Input-BS '!E18 -> 0 | F16: ='3. Input-BS '!F18 -> 0 | G16: ='3. Input-BS '!G18 -> 0
C17: ='3. Input-BS '!C19 -> 6 | D17: ='3. Input-BS '!D19 -> Advance Income Tax | E17: ='3. Input-BS '!E19 -> 15902.348 | F17: ='3. Input-BS '!F19 -> 9694.682 | G17: ='3. Input-BS '!G19 -> 14013.878
C18: ='3. Input-BS '!C20 -> 0 | D18: ='3. Input-BS '!D20 -> 0 | E18: ='3. Input-BS '!E20 -> 0 | F18: ='3. Input-BS '!F20 -> 0 | G18: ='3. Input-BS '!G20 -> 0
C19: ='3. Input-BS '!C21 -> 7 | D19: ='3. Input-BS '!D21 -> Interest Receivables | E19: ='3. Input-BS '!E21 -> 0 | F19: ='3. Input-BS '!F21 -> 0 | G19: ='3. Input-BS '!G21 -> 0
C20: ='3. Input-BS '!C22 -> 8 | D20: ='3. Input-BS '!D22 -> Loan to Associate/Subsidiary/Inter Company Loan | E20: ='3. Input-BS '!E22 -> 0 | F20: ='3. Input-BS '!F22 -> 0 | G20: ='3. Input-BS '!G22 -> 0
C21: ='3. Input-BS '!C23 -> 9 | D21: ='3. Input-BS '!D23 -> Short Term Loan/Investment | E21: ='3. Input-BS '!E23 -> 17389.659 | F21: ='3. Input-BS '!F23 -> 22669.291 | G21: ='3. Input-BS '!G23 -> 20464.8
C22: ='3. Input-BS '!C24 -> 10 | D22: ='3. Input-BS '!D24 -> Inter Company Receivables/Dues | E22: ='3. Input-BS '!E24 -> 0 | F22: ='3. Input-BS '!F24 -> 0 | G22: ='3. Input-BS '!G24 -> 0
C23: ='3. Input-BS '!C25 -> 11 | D23: ='3. Input-BS '!D25 -> Investments Held for Sale/Marketable Securities | E23: ='3. Input-BS '!E25 -> 0 | F23: ='3. Input-BS '!F25 -> 0 | G23: ='3. Input-BS '!G25 -> 0
... C26: ='3. Input-BS '!C28 -> 14 | D26: ='3. Input-BS '!D28 -> Other Current Assets | E26: ='3. Input-BS '!E28 -> 0 | F26: ='3. Input-BS '!F28 -> 0 | G26: ='3. Input-BS '!G28 -> 0
D27: ='3. Input-BS '!D29 -> Total Current Assets | E27: ='3. Input-BS '!E29 -> 3189300.7 | F27: ='3. Input-BS '!F29 -> 2632339.6 | G27: ='3. Input-BS '!G29 -> 2269400.9
D28: ='3. Input-BS '!D30 -> Non-Current Assets: | E28: ='3. Input-BS '!E30 -> 0 | F28: ='3. Input-BS '!F30 -> 0 | G28: ='3. Input-BS '!G30 -> 0
C29: ='3. Input-BS '!C31 -> 17 | D29: ='3. Input-BS '!D31 -> Net Property, Plant and Equipment | E29: ='3. Input-BS '!E31 -> 447186.03 | F29: ='3. Input-BS '!F31 -> 416976.52 | G29: ='3. Input-BS '!G31 -> 293638.33
C30: ='3. Input-BS '!C32 -> 18 | D30: ='3. Input-BS '!D32 -> Net Land and Buildings | E30: ='3. Input-BS '!E32 -> 0 | F30: ='3. Input-BS '!F32 -> 0 | G30: ='3. Input-BS '!G32 -> 0
C31: ='3. Input-BS '!C33 -> 19 | D31: ='3. Input-BS '!D33 -> Net Furniture & Fixture | E31: ='3. Input-BS '!E33 -> 0 | F31: ='3. Input-BS '!F33 -> 0 | G31: ='3. Input-BS '!G33 -> 0
C32: ='3. Input-BS '!C30 -> 16 | D32: ='3. Input-BS '!D34 -> Net Other Fixed Assets | E32: ='3. Input-BS '!E34 -> 0 | F32: ='3. Input-BS '!F34 -> 0 | G32: ='3. Input-BS '!G34 -> 0
C33: ='3. Input-BS '!C35 -> 21 | D33: ='3. Input-BS '!D35 -> Goodwill | E33: ='3. Input-BS '!E35 -> 0 | F33: ='3. Input-BS '!F35 -> 0 | G33: ='3. Input-BS '!G35 -> 0
C34: ='3. Input-BS '!C36 -> 22 | D34: ='3. Input-BS '!D36 -> Trademark/Patent/Software | E34: ='3. Input-BS '!E36 -> 0 | F34: ='3. Input-BS '!F36 -> 0 | G34: ='3. Input-BS '!G36 -> 0
C35: ='3. Input-BS '!C37 -> 23 | D35: ='3. Input-BS '!D37 -> other Intangible Assets | E35: ='3. Input-BS '!E37 -> 0 | F35: ='3. Input-BS '!F37 -> 0 | G35: ='3. Input-BS '!G37 -> 0
C36: ='3. Input-BS '!C38 -> 24 | D36: ='3. Input-BS '!D38 -> Investment in Subsidiary and Associates/ Joint Venture | E36: ='3. Input-BS '!E38 -> 300000 | F36: ='3. Input-BS '!F38 -> 300000 | G36: ='3. Input-BS '!G38 -> 300000
C37: ='3. Input-BS '!C39 -> 25 | D37: ='3. Input-BS '!D39 -> Investment in Shares/Bond | E37: ='3. Input-BS '!E39 -> 0 | F37: ='3. Input-BS '!F39 -> 0 | G37: ='3. Input-BS '!G39 -> 0
C38: ='3. Input-BS '!C40 -> 26 | D38: ='3. Input-BS '!D40 -> Other Investments | E38: ='3. Input-BS '!E40 -> 0 | F38: ='3. Input-BS '!F40 -> 0 | G38: ='3. Input-BS '!G40 -> 0
C39: ='3. Input-BS '!C41 -> 27 | D39: ='3. Input-BS '!D41 -> Deferred Tax Assets | E39: ='3. Input-BS '!E41 -> 0 | F39: ='3. Input-BS '!F41 -> 0 | G39: ='3. Input-BS '!G41 -> 0
C40: ='3. Input-BS '!C42 -> 28 | D40: ='3. Input-BS '!D42 -> Loan to Subsidiary/Associate | E40: ='3. Input-BS '!E42 -> 0 | F40: ='3. Input-BS '!F42 -> 0 | G40: ='3. Input-BS '!G42 -> 0
C41: ='3. Input-BS '!C43 -> 29 | D41: ='3. Input-BS '!D43 -> Preliminary Expenses | E41: ='3. Input-BS '!E43 -> 0 | F41: ='3. Input-BS '!F43 -> 0 | G41: ='3. Input-BS '!G43 -> 0
C42: ='3. Input-BS '!C44 -> 30 | D42: ='3. Input-BS '!D44 -> Product Development Cost | E42: ='3. Input-BS '!E44 -> 0 | F42: ='3. Input-BS '!F44 -> 0 | G42: ='3. Input-BS '!G44 -> 0
C43: ='3. Input-BS '!C45 -> 31 | D43: ='3. Input-BS '!D45 -> Capital Work In Progress | E43: ='3. Input-BS '!E45 -> 0 | F43: ='3. Input-BS '!F45 -> 0 | G43: ='3. Input-BS '!G45 -> 0
C44: ='3. Input-BS '!C46 -> 32 | D44: ='3. Input-BS '!D46 -> Prepayment of Rent | E44: ='3. Input-BS '!E46 -> 0 | F44: ='3. Input-BS '!F46 -> 0 | G44: ='3. Input-BS '!G46 -> 0
... C47: ='3. Input-BS '!C49 -> 35 | D47: ='3. Input-BS '!D49 -> Other Non-Current Assets | E47: ='3. Input-BS '!E49 -> 55887.219 | F47: ='3. Input-BS '!F49 -> 50013.1 | G47: ='3. Input-BS '!G49 -> 27375.554
D48: ='3. Input-BS '!D50 -> Total Non- Current Assets | E48: ='3. Input-BS '!E50 -> 803073.25 | F48: ='3. Input-BS '!F50 -> 766989.62 | G48: ='3. Input-BS '!G50 -> 621013.89
D49: ='3. Input-BS '!D51 -> Total Assets | E49: ='3. Input-BS '!E51 -> 3992374 | F49: ='3. Input-BS '!F51 -> 3399329.3 | G49: ='3. Input-BS '!G51 -> 2890414.8
C50: ='3. Input-BS '!D52 -> Current Liabilities:
C51: ='3. Input-BS '!C53 -> 1 | D51: ='3. Input-BS '!D53 -> Working Capital Loan | E51: ='3. Input-BS '!E53 -> 0 | F51: ='3. Input-BS '!F53 -> 0 | G51: ='3. Input-BS '!G53 -> 0
C52: ='3. Input-BS '!C54 -> 2 | D52: ='3. Input-BS '!D54 -> Short Term Loan | E52: ='3. Input-BS '!E54 -> 2949367.4 | F52: ='3. Input-BS '!F54 -> 2342804.1 | G52: ='3. Input-BS '!G54 -> 1836267.1
C53: ='3. Input-BS '!C55 -> 3 | D53: ='3. Input-BS '!D55 -> Bank Overdraft | E53: ='3. Input-BS '!E55 -> 0 | F53: ='3. Input-BS '!F55 -> 0 | G53: ='3. Input-BS '!G55 -> 0
C54: ='3. Input-BS '!C56 -> 4 | D54: ='3. Input-BS '!D56 -> Current Portion of Long Term Borrowing/Loan | E54: ='3. Input-BS '!E56 -> 57150.696 | F54: ='3. Input-BS '!F56 -> 59269.116 | G54: ='3. Input-BS '!G56 -> 56081.808
C55: ='3. Input-BS '!C57 -> 5 | D55: ='3. Input-BS '!D57 -> Current Portion of Long Term Lease | E55: ='3. Input-BS '!E57 -> 0 | F55: ='3. Input-BS '!F57 -> 0 | G55: ='3. Input-BS '!G57 -> 0
C56: ='3. Input-BS '!C58 -> 6 | D56: ='3. Input-BS '!D58 -> Creditors/Liabilites for expenses/ Accrued Expenses | E56: ='3. Input-BS '!E58 -> 0 | F56: ='3. Input-BS '!F58 -> 0 | G56: ='3. Input-BS '!G58 -> 0
C57: ='3. Input-BS '!C59 -> 7 | D57: ='3. Input-BS '!D59 -> Creditors for goods and services/Accounts Payable/Accruals | E57: ='3. Input-BS '!E59 -> 42587.592 | F57: ='3. Input-BS '!F59 -> 148147.34 | G57: ='3. Input-BS '!G59 -> 179606.09
C58: ='3. Input-BS '!C60 -> 8 | D58: ='3. Input-BS '!D60 -> Creditors for Services | E58: ='3. Input-BS '!E60 -> 0 | F58: ='3. Input-BS '!F60 -> 0 | G58: ='3. Input-BS '!G60 -> 0
C59: ='3. Input-BS '!C61 -> 9 | D59: ='3. Input-BS '!D61 -> Creditors for Other Finance | E59: ='3. Input-BS '!E61 -> 0 | F59: ='3. Input-BS '!F61 -> 0 | G59: ='3. Input-BS '!G61 -> 0
C60: ='3. Input-BS '!C62 -> 10 | D60: ='3. Input-BS '!D62 -> Income Taxes Payable | E60: ='3. Input-BS '!E62 -> 0 | F60: ='3. Input-BS '!F62 -> 0 | G60: ='3. Input-BS '!G62 -> 0
C61: ='3. Input-BS '!C63 -> 11 | D61: ='3. Input-BS '!D63 -> Provision for Tax | E61: ='3. Input-BS '!E63 -> 15902.348 | F61: ='3. Input-BS '!F63 -> 11393.965 | G61: ='3. Input-BS '!G63 -> 19760.428
C62: ='3. Input-BS '!C64 -> 12 | D62: ='3. Input-BS '!D64 -> Provision for Royalty and Technical Know-How | E62: ='3. Input-BS '!E64 -> 0 | F62: ='3. Input-BS '!F64 -> 0 | G62: ='3. Input-BS '!G64 -> 0
... C71: ='3. Input-BS '!C73 -> 21 | D71: ='3. Input-BS '!D73 -> Other Current Liabilities | E71: ='3. Input-BS '!E73 -> 0 | F71: ='3. Input-BS '!F73 -> 0 | G71: ='3. Input-BS '!G73 -> 0
D72: ='3. Input-BS '!D74 -> Total Current Liabilities | E72: ='3. Input-BS '!E74 -> 3065008.1 | F72: ='3. Input-BS '!F74 -> 2561614.5 | G72: ='3. Input-BS '!G74 -> 2091715.4
D73: ='3. Input-BS '!D75 -> Non Current Liabilities:
C74: ='3. Input-BS '!C76 -> 24 | D74: ='3. Input-BS '!D76 -> Long Term Loan | E74: ='3. Input-BS '!E76 -> 128649.68 | F74: ='3. Input-BS '!F76 -> 116554.8 | G74: ='3. Input-BS '!G76 -> 157875.2
C75: ='3. Input-BS '!C77 -> 25 | D75: ='3. Input-BS '!D77 -> Deferred Tax Liability | E75: ='3. Input-BS '!E77 -> 0 | F75: ='3. Input-BS '!F77 -> 0 | G75: ='3. Input-BS '!G77 -> 0
C76: ='3. Input-BS '!C78 -> 26 | D76: ='3. Input-BS '!D78 -> Provision for Employee Benefits (Gratuity) | E76: ='3. Input-BS '!E78 -> 0 | F76: ='3. Input-BS '!F78 -> 0 | G76: ='3. Input-BS '!G78 -> 0
C77: ='3. Input-BS '!C79 -> 27 | D77: ='3. Input-BS '!D79 -> Bond/ Preference Shares | E77: ='3. Input-BS '!E79 -> 0 | F77: ='3. Input-BS '!F79 -> 0 | G77: ='3. Input-BS '!G79 -> 0
C78: ='3. Input-BS '!C80 -> 28 | D78: ='3. Input-BS '!D80 -> Long Term Lease | E78: ='3. Input-BS '!E80 -> 0 | F78: ='3. Input-BS '!F80 -> 0 | G78: ='3. Input-BS '!G80 -> 0
C79: ='3. Input-BS '!C81 -> 29 | D79: ='3. Input-BS '!D81 -> Intercompany Loan | E79: ='3. Input-BS '!E81 -> 0 | F79: ='3. Input-BS '!F81 -> 0 | G79: ='3. Input-BS '!G81 -> 0
C80: ='3. Input-BS '!C82 -> 30 | D80: ='3. Input-BS '!D82 -> Product Warranties | E80: ='3. Input-BS '!E82 -> 0 | F80: ='3. Input-BS '!F82 -> 0 | G80: ='3. Input-BS '!G82 -> 0
C81: ='3. Input-BS '!C83 -> 31 | D81: ='3. Input-BS '!D83 -> Deferred Liability | E81: ='3. Input-BS '!E83 -> 0 | F81: ='3. Input-BS '!F83 -> 0 | G81: ='3. Input-BS '!G83 -> 0
C82: ='3. Input-BS '!C84 -> 32 | D82: ='3. Input-BS '!D84 -> Other Non-Current Liabilities | E82: ='3. Input-BS '!E84 -> 0 | F82: ='3. Input-BS '!F84 -> 0 | G82: ='3. Input-BS '!G84 -> 0
D83: ='3. Input-BS '!D85 -> Total Non-Current Liabilities | E83: ='3. Input-BS '!E85 -> 128649.68 | F83: ='3. Input-BS '!F85 -> 116554.8 | G83: ='3. Input-BS '!G85 -> 157875.2
D84: ='3. Input-BS '!D86 -> Total Liabilities | E84: ='3. Input-BS '!E86 -> 3193657.7 | F84: ='3. Input-BS '!F86 -> 2678169.3 | G84: ='3. Input-BS '!G86 -> 2249590.6
D85: ='3. Input-BS '!D87 -> Equities
C86: ='3. Input-BS '!C88 -> 36 | D86: ='3. Input-BS '!D88 -> Paid-Up Capital/ Share Capital | E86: ='3. Input-BS '!E88 -> 184000 | F86: ='3. Input-BS '!F88 -> 184000 | G86: ='3. Input-BS '!G88 -> 173200
C87: ='3. Input-BS '!C89 -> 37 | D87: ='3. Input-BS '!D89 -> Share Premium Account | E87: ='3. Input-BS '!E89 -> 0 | F87: ='3. Input-BS '!F89 -> 0 | G87: ='3. Input-BS '!G89 -> 0
C88: ='3. Input-BS '!C90 -> 38 | D88: ='3. Input-BS '!D90 -> Retained Earnings | E88: ='3. Input-BS '!E96 -> 0 | F88: ='3. Input-BS '!F90 -> 537159.94 | G88: ='3. Input-BS '!G90 -> 467624.14
C89: ='3. Input-BS '!C91 -> 39 | D89: ='3. Input-BS '!D91 -> Fair Value Gain on Investment/ Unrealised gain from available for sale investments | E89: ='3. Input-BS '!E95 -> 0 | F89: ='3. Input-BS '!F91 -> 0 | G89: ='3. Input-BS '!G91 -> 0
C90: ='3. Input-BS '!C92 -> 40 | D90: ='3. Input-BS '!D92 -> Share Money Deposit | E90: ='3. Input-BS '!E92 -> 0 | F90: ='3. Input-BS '!F92 -> 0 | G90: ='3. Input-BS '!G92 -> 0
C91: ='3. Input-BS '!C93 -> 41 | D91: ='3. Input-BS '!D93 -> Tax Holiday Reserve | E91: ='3. Input-BS '!E93 -> 0 | F91: ='3. Input-BS '!F93 -> 0 | G91: ='3. Input-BS '!G93 -> 0
C92: ='3. Input-BS '!C94 -> 42 | D92: ='3. Input-BS '!D94 -> General Reserve | E92: ='3. Input-BS '!E94 -> 0 | F92: ='3. Input-BS '!F94 -> 0 | G92: ='3. Input-BS '!G94 -> 0
C93: ='3. Input-BS '!C95 -> 43 | D93: ='3. Input-BS '!D95 -> Revaluation Reserve | E93: ='3. Input-BS '!E95 -> 0 | F93: ='3. Input-BS '!F95 -> 0 | G93: ='3. Input-BS '!G95 -> 0
C94: ='3. Input-BS '!C96 -> 44 | D94: ='3. Input-BS '!D96 -> Dividend Equalization Reserve | E94: ='3. Input-BS '!E96 -> 0 | F94: ='3. Input-BS '!F96 -> 0 | G94: ='3. Input-BS '!G96 -> 0
C95: ='3. Input-BS '!C97 -> 45 | D95: ='3. Input-BS '!D97 -> Other Reserves | E95: ='3. Input-BS '!E97 -> 0 | F95: ='3. Input-BS '!F97 -> 0 | G95: ='3. Input-BS '!G97 -> 0
C96: ='3. Input-BS '!C98 -> 46 | D96: ='3. Input-BS '!D98 -> Other Equity Items | E96: ='3. Input-BS '!E98 -> 0 | F96: ='3. Input-BS '!F98 -> 0 | G96: ='3. Input-BS '!G98 -> 0
D97: ='3. Input-BS '!D99 -> Total Equity | E97: ='3. Input-BS '!E99 -> 798716.24 | F97: ='3. Input-BS '!F99 -> 721159.94 | G97: ='3. Input-BS '!G99 -> 640824.14
C98: ='3. Input-BS '!C100 -> 48 | D98: ='3. Input-BS '!D100 -> Minority Interest | E98: ='3. Input-BS '!E100 -> 0 | F98: ='3. Input-BS '!F100 -> 0 | G98: ='3. Input-BS '!G100 -> 0
D99: ='3. Input-BS '!D101 -> Total Equity & Liabilities | E99: ='3. Input-BS '!E101 -> 3992374 | F99: ='3. Input-BS '!F101 -> 3399329.3 | G99: ='3. Input-BS '!G101 -> 2890414.8
D100: Validation | E100: ='3. Input-BS '!E102 -> TRUE | F100: ='3. Input-BS '!F102 -> TRUE | G100: ='3. Input-BS '!G102 -> TRUE

Sheet 7. Output IS
C2: ='4. Input P&L'!C2:G2 -> Outpace Spinning Mills Ltd
C3: ='4. Input P&L'!C3:G3 -> Profit & Loss Statement
C4: ='4. Input P&L'!C4:D4 -> Analyst | E4: ='4. Input P&L'!E4:G4 -> Md. Matiur Rahman, SRM
C5: ='4. Input P&L'!C5:D5 -> Verifier | E5: ='4. Input P&L'!E5:G5 -> Farhana Afrin, SM
C6: ='4. Input P&L'!C6:D6 -> Name of Audit Farm | E6: ='4. Input P&L'!E6 -> Deawn Nazrul Islam & Co | F6: ='4. Input P&L'!F6 -> Deawn Nazrul Islam & Co | G6: ='4. Input P&L'!G6 -> Rahman Mustafiz Haw & Co.
C7: ='4. Input P&L'!C7:D7 -> Period (months) | E7: ='4. Input P&L'!E7 -> 12 | F7: ='4. Input P&L'!F7 -> 12 | G7: ='4. Input P&L'!G7 -> 12
C8: ='4. Input P&L'!C8:D8 -> Amount in thousand | E8: ('000) | F8: ('000) | G8: ('000)
C9: ='4. Input P&L'!C9:D9 -> Statement Year | E9: ='4. Input P&L'!E9 -> 2025 | F9: ='4. Input P&L'!F9 -> 2024 | G9: ='4. Input P&L'!G9 -> 2023
C11: ='4. Input P&L'!C11 -> 1 | D11: ='4. Input P&L'!D11 -> Sales /Revenue/Turnover | E11: ='4. Input P&L'!E11 -> 1412760.6 | F11: ='4. Input P&L'!F11 -> 1736066.4 | G11: ='4. Input P&L'!G11 -> 1396131.3
C12: ='4. Input P&L'!C12 -> 2 | D12: ='4. Input P&L'!D12 -> VAT & Supplementary Duty | E12: ='4. Input P&L'!E12 -> 0 | F12: ='4. Input P&L'!F12 -> 0 | G12: ='4. Input P&L'!G12 -> 0
C13: ='4. Input P&L'!C13 -> 3 | D13: ='4. Input P&L'!D13 -> Net Sales/Revenue | E13: ='4. Input P&L'!E13 -> 1412760.6 | F13: ='4. Input P&L'!F13 -> 1736066.4 | G13: ='4. Input P&L'!G13 -> 1396131.3
C14: ='4. Input P&L'!C14 -> 4 | D14: ='4. Input P&L'!D14 -> Cost of Goods/Service Sold | E14: ='4. Input P&L'!E14 -> 1187045.5 | F14: ='4. Input P&L'!F14 -> 1473623.9 | G14: ='4. Input P&L'!G14 -> 1144305.5
C15: ='4. Input P&L'!C15 -> 5 | D15: ='4. Input P&L'!D15 -> Gross Profit | E15: ='4. Input P&L'!E15 -> 225715.08 | F15: ='4. Input P&L'!F15 -> 262442.55 | G15: ='4. Input P&L'!G15 -> 251825.83
C16: ='4. Input P&L'!C16 -> 6 | D16: ='4. Input P&L'!D16 -> Salaries | E16: ='4. Input P&L'!E16 -> 0 | F16: ='4. Input P&L'!F16 -> 0 | G16: ='4. Input P&L'!G16 -> 0
C17: ='4. Input P&L'!C17 -> 7 | D17: ='4. Input P&L'!D17 -> Marketing, Selling & Distribution Expenses | E17: ='4. Input P&L'!E17 -> 3381.175 | F17: ='4. Input P&L'!F17 -> 4765.77 | G17: ='4. Input P&L'!G17 -> 34597.824
C18: ='4. Input P&L'!C18 -> 8 | D18: ='4. Input P&L'!D18 -> Administrative Expenses | E18: ='4. Input P&L'!E18 -> 29692.632 | F18: ='4. Input P&L'!F18 -> 41358.161 | G18: ='4. Input P&L'!G18 -> 4194.973
C19: ='4. Input P&L'!C19 -> 9 | D19: ='4. Input P&L'!D19 -> Depreciation/ Amortization | E19: ='4. Input P&L'!E19 -> 20870.038 | F19: ='4. Input P&L'!F19 -> 19390.317 | G19: ='4. Input P&L'!G19 -> 13328.984
C20: ='4. Input P&L'!C20 -> 10 | D20: ='4. Input P&L'!D20 -> Other Operating Expense | E20: ='4. Input P&L'!E20 -> 0 | F20: ='4. Input P&L'!F20 -> 0 | G20: ='4. Input P&L'!G20 -> 0
C21: ='4. Input P&L'!C21 -> 11 | D21: ='4. Input P&L'!D21 -> Total Operating Expenses | E21: ='4. Input P&L'!E21 -> 53943.845 | F21: ='4. Input P&L'!F21 -> 65514.248 | G21: ='4. Input P&L'!G21 -> 52121.781
C22: ='4. Input P&L'!C22 -> 12 | D22: ='4. Input P&L'!D22 -> Other Operating Income | E22: ='4. Input P&L'!E22 -> 0 | F22: ='4. Input P&L'!F22 -> 0 | G22: ='4. Input P&L'!G22 -> 0
... C35: ='4. Input P&L'!C35 -> 25 | D35: ='4. Input P&L'!D35 -> Share of profit from associates | E35: ='4. Input P&L'!E35 -> 0 | F35: ='4. Input P&L'!F35 -> 0 | G35: ='4. Input P&L'!G35 -> 0
C36: ='4. Input P&L'!C37 -> 27 | D36: ='4. Input P&L'!D37 -> Earnings Before Interest and Tax (EBIT) | E36: ='4. Input P&L'!E37 -> 173746.24 | F36: ='4. Input P&L'!F37 -> 199713.92 | G36: ='4. Input P&L'!G37 -> 200442.43
C37: ='4. Input P&L'!C38 -> 28 | D37: ='4. Input P&L'!D38 -> Financial/Interest Expenses | E37: ='4. Input P&L'!E38 -> 80287.596 | F37: ='4. Input P&L'!F38 -> 118784.16 | G37: ='4. Input P&L'!G38 -> 68706.248
C38: ='4. Input P&L'!C39 -> 29 | D38: ='4. Input P&L'!D39 -> Earnings Before Tax (EBT) | E38: ='4. Input P&L'!E39 -> 93458.648 | F38: ='4. Input P&L'!F39 -> 80929.762 | G38: ='4. Input P&L'!G39 -> 131736.19
C39: ='4. Input P&L'!C40 -> 30 | D39: ='4. Input P&L'!D40 -> Current Tax | E39: ='4. Input P&L'!E40 -> 15902.348 | F39: ='4. Input P&L'!F40 -> 11393.965 | G39: ='4. Input P&L'!G40 -> 19760.428
C40: ='4. Input P&L'!C41 -> 31 | D40: ='4. Input P&L'!D41 -> Deferred Tax/ Advance Tax Expense | E40: ='4. Input P&L'!E41 -> 0 | F40: ='4. Input P&L'!F41 -> 0 | G40: ='4. Input P&L'!G41 -> 0
C41: ='4. Input P&L'!C42 -> 32 | D41: ='4. Input P&L'!D42 -> Deferred Tax/Advance Tax Income | E41: ='4. Input P&L'!E42 -> 0 | F41: ='4. Input P&L'!F42 -> 0 | G41: ='4. Input P&L'!G42 -> 0
C42: ='4. Input P&L'!C43 -> 33 | D42: ='4. Input P&L'!D43 -> Total Tax | E42: ='4. Input P&L'!E43 -> 15902.348 | F42: ='4. Input P&L'!F43 -> 11393.965 | G42: ='4. Input P&L'!G43 -> 19760.428
C43: ='4. Input P&L'!C44 -> 34 | D43: ='4. Input P&L'!D44 -> Net Profit After Tax (NPAT) | E43: ='4. Input P&L'!E44 -> 77556.3 | F43: ='4. Input P&L'!F44 -> 69535.797 | G43: ='4. Input P&L'!G44 -> 111975.76
C44: ='4. Input P&L'!C45 -> 35 | D44: ='4. Input P&L'!D45 -> Extraordinary Income/ Other Comprehensive Income | E44: ='4. Input P&L'!E45 -> 0 | F44: ='4. Input P&L'!F45 -> 0 | G44: ='4. Input P&L'!G45 -> 0
C45: ='4. Input P&L'!C46 -> 36 | D45: ='4. Input P&L'!D46 -> Extraordinary Expenses/ Other Comprehensive Expense | E45: ='4. Input P&L'!E46 -> 0 | F45: ='4. Input P&L'!F46 -> 0 | G45: ='4. Input P&L'!G46 -> 0
C46: ='4. Input P&L'!C47 -> 37 | D46: ='4. Input P&L'!D47 -> Total Comprehensive Income | E46: ='4. Input P&L'!E47 -> 77556.3 | F46: ='4. Input P&L'!F47 -> 69535.797 | G46: ='4. Input P&L'!G47 -> 111975.76

Sheet 8. Output CF
C2: ='2. Top Page'!D9 -> Outpace Spinning Mills Ltd
C3: Cash Flow Statement
C4: ='5. Input-CF'!C4:D4 -> Analyst | E4: ='2. Top Page'!D18 -> Md. Matiur Rahman, SRM
C5: ='5. Input-CF'!C5:D5 -> Verifier | E5: ='2. Top Page'!D19 -> Farhana Afrin, SM
C6: ='5. Input-CF'!C6:D6 -> Name of the Audit Farm | E6: ='5. Input-CF'!E6 -> Deawn Nazrul Islam & Co | F6: ='5. Input-CF'!F6 -> Deawn Nazrul Islam & Co | G6: ='5. Input-CF'!G6 -> Rahman Mustafiz Haw & Co.
C7: ='5. Input-CF'!C7:D7 -> Period (months) | E7: ='4. Input P&L'!E7 -> 12 | F7: ='4. Input P&L'!F7 -> 12 | G7: ='4. Input P&L'!G7 -> 12
C8: ='5. Input-CF'!C8:D8 -> Amount in thousand | E8: ('000) | F8: ('000) | G8: ('000)
C10: Year | E10: ='5. Input-CF'!E10 -> 2025 | F10: ='5. Input-CF'!F10 -> 2024 | G10: ='5. Input-CF'!G10 -> 2023
C11: ='5. Input-CF'!C11 -> A. | D11: ='5. Input-CF'!D11 -> Net cash flows from operating activities | E11: ='5. Input-CF'!E11 -> 105171.03 | F11: ='5. Input-CF'!F11 -> 398401.77 | G11: ='5. Input-CF'!G11 -> -723188.92
C12: ='5. Input-CF'!C12 -> B. | D12: ='5. Input-CF'!D12 -> Net cash flows from investing activities | E12: ='5. Input-CF'!E12 -> -56953.665 | F12: ='5. Input-CF'!F12 -> -165366.05 | G12: ='5. Input-CF'!G12 -> -20827.202
C13: ='5. Input-CF'!C13 -> C. | D13: ='5. Input-CF'!D13 -> Net cash flows from financing activities | E13: ='5. Input-CF'!E13 -> -66327.363 | F13: ='5. Input-CF'!F13 -> -213494.1 | G13: ='5. Input-CF'!G13 -> 748507.59
C14: ='5. Input-CF'!C14 -> D. | D14: ='5. Input-CF'!D14 -> Net inflow of cash and cash equivalents | E14: ='5. Input-CF'!E14 -> -18110.002 | F14: ='5. Input-CF'!F14 -> 19541.621 | G14: ='5. Input-CF'!G14 -> 4491.471
C15: ='5. Input-CF'!C15 -> E. | D15: ='5. Input-CF'!D15 -> Cash and cash equivalent at opening | E15: ='5. Input-CF'!E15 -> 36951.324 | F15: ='5. Input-CF'!F15 -> 17409.703 | G15: ='5. Input-CF'!G15 -> 12918.232
C16: E. | D16: Cash and cash equivalent at closing | E16: =SUM(E14:E15) -> 18841.322 | F16: =SUM(F14:F15) -> 36951.324 | G16: =SUM(G14:G15) -> 17409.703

Sheet Final Graph
B2: Components for Analysis
D3: ='6. Output-BS'!E9 -> 2025 | E3: ='6. Output-BS'!F9 -> 2024 | F3: ='6. Output-BS'!G9 -> 2023 | G3: =E3 -> 2024 | H3: =D3 -> 2025
B4: 1 | C4: Debt Equity | D4: =D5/D6 -> 3.9252586 | E4: =E5/E6 -> 3.492468 | F4: =F5/F6 -> 3.1993553 | G4: =E4 -> 3.492468 | H4: =D4 -> 3.9252586
C5: Total Financial Debt | D5: ='6. Output-BS'!E51+'6. Output-BS'!E52+'6. Output-BS'!E53+'6. Output-BS'!E54+'6. Output-BS'!E55+'6. Output-BS'!E74+'6. Output-BS'!E78+'6. Output-BS'!E79+'6. Output-BS'!E77 -> 3135167.8 | E5: ='6. Output-BS'!F51+'6. Output-BS'!F52+'6. Output-BS'!F53+'6. Output-BS'!F54+'6. Output-BS'!F55+'6. Output-BS'!F74+'6. Output-BS'!F78+'6. Output-BS'!F79+'6. Output-BS'!F77 -> 2518628 | F5: ='6. Output-BS'!G51+'6. Output-BS'!G52+'6. Output-BS'!G53+'6. Output-BS'!G54+'6. Output-BS'!G55+'6. Output-BS'!G74+'6. Output-BS'!G78+'6. Output-BS'!G79+'6. Output-BS'!G77 -> 2050224.1 | G5: =E5 -> 2518628 | H5: =D5 -> 3135167.8
C6: Total Tangible Net Worth | D6: ='6. Output-BS'!E97-'6. Output-BS'!E33-'6. Output-BS'!E34-'6. Output-BS'!E35-('6. Output-BS'!E93*0.25) -> 798716.24 | E6: ='6. Output-BS'!F97-'6. Output-BS'!F33-'6. Output-BS'!F34-'6. Output-BS'!F35-('6. Output-BS'!F93*0.25) -> 721159.94 | F6: ='6. Output-BS'!G97-'6. Output-BS'!G33-'6. Output-BS'!G34-'6. Output-BS'!G35-('6. Output-BS'!G93*0.25) -> 640824.14 | G6: =E6 -> 721159.94 | H6: =D6 -> 798716.24
B7: 2 | C7: Debt to Assets | D7: =D8/D9 -> 0.78528911 | E7: =E8/E9 -> 0.74091911 | F7: =F8/F9 -> 0.7093183 | G7: =E7 -> 0.74091911 | H7: =D7 -> 0.78528911
C8: Total Financial Debt | D8: =D5 -> 3135167.8 | E8: =E5 -> 2518628 | F8: =F5 -> 2050224.1 | G8: =E8 -> 2518628 | H8: =D8 -> 3135167.8
C9: Total Assets | D9: ='6. Output-BS'!E49 -> 3992374 | E9: ='6. Output-BS'!F49 -> 3399329.3 | F9: ='6. Output-BS'!G49 -> 2890414.8 | G9: =E9 -> 3399329.3 | H9: =D9 -> 3992374
B10: 3 | C10: Cash Ratio | D10: =D12/D14 -> 0.0061472341 | E10: =E12/E14 -> 0.014425013 | F10: =F12/F14 -> 0.00832317 | G10: =E10 -> 0.014425013 | H10: =D10 -> 0.0061472341
B11: 4 | C11: Current Ratio | D11: =D13/D14 -> 1.0405522 | E11: =E13/E14 -> 1.0276096 | F11: =F13/F14 -> 1.0849472 | G11: =E11 -> 1.0276096 | H11: =D11 -> 1.0405522
C12: Cash and easily marketable securities | D12: ='6. Output-BS'!E25+'6. Output-BS'!E23 -> 18841.322 | E12: ='6. Output-BS'!F25+'6. Output-BS'!F23 -> 36951.324 | F12: ='6. Output-BS'!G25+'6. Output-BS'!G23 -> 17409.703 | G12: =E12 -> 36951.324 | H12: =D12 -> 18841.322
C13: Current Assets | D13: ='6. Output-BS'!E27 -> 3189300.7 | E13: ='6. Output-BS'!F27 -> 2632339.6 | F13: ='6. Output-BS'!G27 -> 2269400.9 | G13: =E13 -> 2632339.6 | H13: =D13 -> 3189300.7
C14: Current Liabilites | D14: ='6. Output-BS'!E72 -> 3065008.1 | E14: ='6. Output-BS'!F72 -> 2561614.5 | F14: ='6. Output-BS'!G72 -> 2091715.4 | G14: =E14 -> 2561614.5 | H14: =D14 -> 3065008.1
B15: 5 | C15: Net Profit Margin | D15: =D16/D17 -> 0.054896988 | E15: =E16/E17 -> 0.04005365 | F15: =F16/F17 -> 0.080204317 | G15: =E15 -> 0.04005365 | H15: =D15 -> 0.054896988
C16: Net profit after tax | D16: ='7. Output IS'!E43 -> 77556.3 | E16: ='7. Output IS'!F43 -> 69535.797 | F16: ='7. Output IS'!G43 -> 111975.76 | G16: =E16 -> 69535.797 | H16: =D16 -> 77556.3
C17: Net Sales | D17: ='7. Output IS'!E13 -> 1412760.6 | E17: ='7. Output IS'!F13 -> 1736066.4 | F17: ='7. Output IS'!G13 -> 1396131.3 | G17: =E17 -> 1736066.4 | H17: =D17 -> 1412760.6
B18: 6 | C18: Return on Asset | D18: =D19/D20 -> 0.019426111 | E18: =E19/E20 -> 0.02045574 | F18: =F19/F20 -> 0.038740378 | G18: =E18 -> 0.02045574 | H18: =D18 -> 0.019426111
C19: Net profit after tax | D19: =D16 -> 77556.3 | E19: =E16 -> 69535.797 | F19: =F16 -> 111975.76 | G19: =E19 -> 69535.797 | H19: =D19 -> 77556.3
C20: Average Total Assets | D20: ='6. Output-BS'!E49 -> 3992374 | E20: ='6. Output-BS'!F49 -> 3399329.3 | F20: ='6. Output-BS'!G49 -> 2890414.8 | G20: =E20 -> 3399329.3 | H20: =D20 -> 3992374
B21: 7 | C21: Operating Profit to Operating Assets | D21: =D22/D23 -> 0.04652054 | E21: =E22/E23 -> 0.063539008 | F21: =F22/F23 -> 0.077093466 | G21: =E21 -> 0.063539008 | H21: =D21 -> 0.04652054
C22: Operating Profit | D22: ='7. Output IS'!E23 -> 171771.23 | E22: ='7. Output IS'!F23 -> 196928.31 | F22: ='7. Output IS'!G23 -> 199704.05 | G22: =E22 -> 196928.31 | H22: =D22 -> 171771.23
C23: Operating Assets | D23: ='6. Output-BS'!E49-'6. Output-BS'!E37-'6. Output-BS'!E38-'6. Output-BS'!E40-'6. Output-BS'!E36 -> 3692374 | E23: ='6. Output-BS'!F49-'6. Output-BS'!F37-'6. Output-BS'!F38-'6. Output-BS'!F40-'6. Output-BS'!F36 -> 3099329.3 | F23: ='6. Output-BS'!G49-'6. Output-BS'!G37-'6. Output-BS'!G38-'6. Output-BS'!G40-'6. Output-BS'!G36 -> 2590414.8 | G23: =E23 -> 3099329.3 | H23: =D23 -> 3692374
B24: 8 | C24: Interest Coverage | D24: =D25/D26 -> 2.1640484 | E24: =E25/E26 -> 1.6813178 | F24: =F25/F26 -> 2.9173829 | G24: =E24 -> 1.6813178 | H24: =D24 -> 2.1640484
C25: Earning Before Interest and Tax | D25: ='7. Output IS'!E36 -> 173746.24 | E25: ='7. Output IS'!F36 -> 199713.92 | F25: ='7. Output IS'!G36 -> 200442.43 | G25: =E25 -> 199713.92 | H25: =D25 -> 173746.24
C26: Interest Expense | D26: ='7. Output IS'!E37 -> 80287.596 | E26: ='7. Output IS'!F37 -> 118784.16 | F26: ='7. Output IS'!G37 -> 68706.248 | G26: =E26 -> 118784.16 | H26: =D26 -> 80287.596
B27: 9 | C27: DSCR | D27: =D28/D29 -> 1.4160266 | E27: =E28/E29 -> 1.2305544 | F27: =F28/F29 -> 1.713076 | G27: =E27 -> 1.2305544 | H27: =D27 -> 1.4160266
C28: Earning Before Interest Tax Depreciation Amortization | D28: ='7. Output IS'!E36+'7. Output IS'!E19 -> 194616.28 | E28: ='7. Output IS'!F36+'7. Output IS'!F19 -> 219104.24 | F28: ='7. Output IS'!G36+'7. Output IS'!G19 -> 213771.42 | G28: =E28 -> 219104.24 | H28: =D28 -> 194616.28
C29: Debts to be Serviced | D29: ='6. Output-BS'!E54+'6. Output-BS'!E55+'7. Output IS'!E37+'6. Output-BS'!E67 -> 137438.29 | E29: ='6. Output-BS'!F54+'6. Output-BS'!F55+'7. Output IS'!F37+'6. Output-BS'!F67 -> 178053.27 | F29: ='6. Output-BS'!G54+'6. Output-BS'!G55+'7. Output IS'!G37+'6. Output-BS'!G67 -> 124788.06 | G29: =E29 -> 178053.27 | H29: =D29 -> 137438.29
B30: 10 | C30: 3. Financial Debt to Operating Cash Flow (FDCF) | D30: =D31/D32 -> 29.810185 | E30: =E31/E32 -> 6.3218293 | F30: =F31/F32 -> -2.8349772 | G30: =E30 -> 6.3218293 | H30: =D30 -> 29.810185
C31: Total Financial Debt | D31: =D5 -> 3135167.8 | E31: =E5 -> 2518628 | F31: =F5 -> 2050224.1 | G31: =E31 -> 2518628 | H31: =D31 -> 3135167.8
C32: Operating Cash flow | D32: ='8. Output CF'!E11 -> 105171.03 | E32: ='8. Output CF'!F11 -> 398401.77 | F32: ='8. Output CF'!G11 -> -723188.92 | G32: =E32 -> 398401.77 | H32: =D32 -> 105171.03
B33: 11 | C33: Cashflow Coverage | D33: =D34/D35 -> 0.76522361 | E33: =E34/E35 -> 2.2375425 | F33: =F34/F35 -> -5.7953376 | G33: =E33 -> 2.2375425 | H33: =D33 -> 0.76522361
C34: Operating Cash flow | D34: ='8. Output CF'!E11 -> 105171.03 | E34: ='8. Output CF'!F11 -> 398401.77 | F34: ='8. Output CF'!G11 -> -723188.92 | G34: =E34 -> 398401.77 | H34: =D34 -> 105171.03
C35: Debt to be serviced | D35: =D29 -> 137438.29 | E35: =E29 -> 178053.27 | F35: =F29 -> 124788.06 | G35: =E35 -> 178053.27 | H35: =D35 -> 137438.29
B36: 12 | C36: 1. Stock Turnover Days (STD) | D36: =D37/D38*360 -> 0 | E36: =E37/E38*360 -> 0 | F36: =F37/F38*360 -> 0 | G36: =E36 -> 0 | H36: =D36 -> 0
C37: Total Inventory | D37: ='6. Output-BS'!E33 -> 0 | E37: ='6. Output-BS'!F33 -> 0 | F37: ='6. Output-BS'!G33 -> 0 | G37: =E37 -> 0 | H37: =D37 -> 0
C38: COGS | D38: ='7. Output IS'!E14 -> 1187045.5 | E38: ='7. Output IS'!F14 -> 1473623.9 | F38: ='7. Output IS'!G14 -> 1144305.5 | G38: =E38 -> 1473623.9 | H38: =D38 -> 1187045.5
B39: 13 | C39: 2. Trade Debtor Collection Days (TDCD) | D39: =(D40/D41)*360 -> 89.219452 | E39: =(E40/E41)*360 -> 195.71035 | F39: =(F40/F41)*360 -> 131.32814 | G39: =E39 -> 195.71035 | H39: =D39 -> 89.219452
C40: Total Accoutns Receivable | D40: ='6. Output-BS'!E13 -> 350127.01 | E40: ='6. Output-BS'!F13 -> 943794.93 | F40: ='6. Output-BS'!G13 -> 509309.24 | G40: =E40 -> 943794.93 | H40: =D40 -> 350127.01
C41: Sales | D41: ='7. Output IS'!E13 -> 1412760.6 | E41: ='7. Output IS'!F13 -> 1736066.4 | F41: ='7. Output IS'!G13 -> 1396131.3 | G41: =E41 -> 1736066.4 | H41: =D41 -> 1412760.6
B42: 14 | C42: 3. Asset Turnover (AT) | D42: =D43/D44 -> 0.35386479 | E42: =E43/E44 -> 0.51070853 | F42: =F43/F44 -> 0.4830211 | G42: =E42 -> 0.51070853 | H42: =D42 -> 0.35386479
C43: Sales | D43: =D41 -> 1412760.6 | E43: =E41 -> 1736066.4 | F43: =F41 -> 1396131.3 | G43: =E43 -> 1736066.4 | H43: =D43 -> 1412760.6
C44: Average Total Assets | D44: =D20 -> 3992374 | E44: =E20 -> 3399329.3 | F44: =F20 -> 2890414.8 | G44: =E44 -> 3399329.3 | H44: =D44 -> 3992374
B45: 15 | C45: 1. Operating Cash Flow to Sales (CFS) | D45: =D46/D47 -> 0.074443631 | E45: =E46/E47 -> 0.22948533 | F45: =F46/F47 -> -0.51799491 | G45: =E45 -> 0.22948533 | H45: =D45 -> 0.074443631
C46: Operating Cashflow | D46: =D34 -> 105171.03 | E46: =E34 -> 398401.77 | F46: =F34 -> -723188.92 | G46: =E46 -> 398401.77 | H46: =D46 -> 105171.03
C47: Sales | D47: =D41 -> 1412760.6 | E47: =E41 -> 1736066.4 | F47: =F41 -> 1396131.3 | G47: =E47 -> 1736066.4 | H47: =D47 -> 1412760.6
B48: 16 | C48: 2. Cashflow based accrual ratio (CAR) | D48: =D52/D53 -> -0.022279384 | E48: =E52/E53 -> -0.15918539 | F48: =F52/F53 -> 0.32257783 | G48: =E48 -> -0.15918539 | H48: =D48 -> -0.022279384
C49: Operating Assets Y1 | D49: ='6. Output-BS'!E49-'Final Graph'!D12 -> 3973532.6 | E49: ='6. Output-BS'!F49-'Final Graph'!E12 -> 3362377.9 | F49: ='6. Output-BS'!G49-'Final Graph'!F12 -> 2873005 | G49: =E49 -> 3362377.9 | H49: =D49 -> 3973532.6
C50: Operating Liabilities Y1 | D50: ='6. Output-BS'!E84-'6. Output-BS'!E78-'6. Output-BS'!E52-'6. Output-BS'!E53-'6. Output-BS'!E54-'6. Output-BS'!E55 -> 187139.62 | E50: ='6. Output-BS'!F84-'6. Output-BS'!F78-'6. Output-BS'!F52-'6. Output-BS'!F53-'6. Output-BS'!F54-'6. Output-BS'!F55 -> 276096.1 | F50: ='6. Output-BS'!G84-'6. Output-BS'!G78-'6. Output-BS'!G52-'6. Output-BS'!G53-'6. Output-BS'!G54-'6. Output-BS'!G55 -> 357241.73 | G50: =E50 -> 276096.1 | H50: =D50 -> 187139.62
C51: Net Operating Assets Y1 | D51: =D49-D50 -> 3786393 | E51: =E49-E50 -> 3086281.8 | F51: =F49-F50 -> 2515763.3 | G51: =E51 -> 3086281.8 | H51: =D51 -> 3786393
C52: NI-CFO+CFI | D52: ='7. Output IS'!E43-'8. Output CF'!E11+'8. Output CF'!E12 -> -84568.391 | E52: ='7. Output IS'!F43-'8. Output CF'!F11+'8. Output CF'!F12 -> -494232.03 | F52: ='7. Output IS'!G43-'8. Output CF'!G11+'8. Output CF'!G12 -> 814337.48 | G52: =E52 -> -494232.03 | H52: =D52 -> -84568.391
C53: Average Net Operating Assets | D53: =AVERAGE(D54:D55) -> 3795813.7 | E53: =AVERAGE(E54:E55) -> 3104757.5 | F53: =AVERAGE(F54:F55) -> 2524468.2 | G53: =E53 -> 3104757.5 | H53: =D53 -> 3795813.7
C54: Net Operating Assets Y1 | D54: =D49-D50 -> 3786393 | E54: =E49-E50 -> 3086281.8 | F54: =F49-F50 -> 2515763.3 | G54: =E54 -> 3086281.8 | H54: =D54 -> 3786393
C55: Net Operating Assets Y0 | D55: =D56-D57 -> 3805234.4 | E55: =E56-E57 -> 3123233.2 | F55: =F56-F57 -> 2533173 | G55: =E55 -> 3123233.2 | H55: =D55 -> 3805234.4
C56: Operating Assets Y0 | D56: ='6. Output-BS'!E49-'6. Output-BS'!E44-'6. Output-BS'!E46 -> 3992374 | E56: ='6. Output-BS'!F49-'6. Output-BS'!F44-'6. Output-BS'!F46 -> 3399329.3 | F56: ='6. Output-BS'!G49-'6. Output-BS'!G44-'6. Output-BS'!G46 -> 2890414.8 | G56: =E56 -> 3399329.3 | H56: =D56 -> 3992374
C57: Operating Liabilities Y0 | D57: ='6. Output-BS'!E84-'6. Output-BS'!E78-'6. Output-BS'!E52-'6. Output-BS'!E53-'6. Output-BS'!E54-'6. Output-BS'!E55 -> 187139.62 | E57: ='6. Output-BS'!F84-'6. Output-BS'!F78-'6. Output-BS'!F52-'6. Output-BS'!F53-'6. Output-BS'!F54-'6. Output-BS'!F55 -> 276096.1 | F57: ='6. Output-BS'!G84-'6. Output-BS'!G78-'6. Output-BS'!G52-'6. Output-BS'!G53-'6. Output-BS'!G54-'6. Output-BS'!G55 -> 357241.73 | G57: =E57 -> 276096.1 | H57: =D57 -> 187139.62
G58: =E58 -> 0

Sheet Graph
B2: Components for Analysis
D3: ='6. Output-BS'!E9 -> 2025 | E3: ='6. Output-BS'!F9 -> 2024 | F3: ='6. Output-BS'!G9 -> 2023 | G3: =E3 -> 2024 | H3: =D3 -> 2025
B4: 1 | C4: Debt to Equity | D4: =D5/D6 -> 3.9984885 | E4: =E5/E6 -> 3.7136967 | F4: =F5/F6 -> 3.5104648 | G4: =E4 -> 3.7136967 | H4: =D4 -> 3.9984885
C5: Total Liabilites | D5: ='6. Output-BS'!E84 -> 3193657.7 | E5: ='6. Output-BS'!F84 -> 2678169.3 | F5: ='6. Output-BS'!G84 -> 2249590.6 | G5: =E5 -> 2678169.3 | H5: =D5 -> 3193657.7
C6: Total Tangible Net Worth | D6: ='6. Output-BS'!E97-'6. Output-BS'!E33-'6. Output-BS'!E34-'6. Output-BS'!E35-('6. Output-BS'!E93*0.25) -> 798716.24 | E6: ='6. Output-BS'!F97-'6. Output-BS'!F33-'6. Output-BS'!F34-'6. Output-BS'!F35-('6. Output-BS'!F93*0.25) -> 721159.94 | F6: ='6. Output-BS'!G97-'6. Output-BS'!G33-'6. Output-BS'!G34-'6. Output-BS'!G35-('6. Output-BS'!G93*0.25) -> 640824.14 | G6: =E6 -> 721159.94 | H6: =D6 -> 798716.24
B7: 2 | C7: Debt to Total Assets | D7: =D8/D9 -> 0.16107057 | E7: =E8/E9 -> 0.16162128 | F7: =F8/F9 -> 0.24636276 | G7: =E7 -> 0.16162128 | H7: =D7 -> 0.16107057
C8: Total Long Term Debt | D8: ='6. Output-BS'!E74+'6. Output-BS'!E78+'6. Output-BS'!E79 -> 128649.68 | E8: ='6. Output-BS'!F74+'6. Output-BS'!F78+'6. Output-BS'!F79 -> 116554.8 | F8: ='6. Output-BS'!G74+'6. Output-BS'!G78+'6. Output-BS'!G79 -> 157875.2 | G8: =E8 -> 116554.8 | H8: =D8 -> 128649.68
C9: Total Equity | D9: ='6. Output-BS'!E97 -> 798716.24 | E9: ='6. Output-BS'!F97 -> 721159.94 | F9: ='6. Output-BS'!G97 -> 640824.14 | G9: =E9 -> 721159.94 | H9: =D9 -> 798716.24
B10: 3 | C10: Cash Ratio | D10: =D12/D14 -> 0.0061472341 | E10: =E12/E14 -> 0.014425013 | F10: =F12/F14 -> 0.00832317 | G10: =E10 -> 0.014425013 | H10: =D10 -> 0.0061472341
B11: 4 | C11: Current Ratio | D11: =D13/D14 -> 1.0405522 | E11: =E13/E14 -> 1.0276096 | F11: =F13/F14 -> 1.0849472 | G11: =E11 -> 1.0276096 | H11: =D11 -> 1.0405522
C12: Cash and easily marketable securities | D12: ='6. Output-BS'!E25+'6. Output-BS'!E23 -> 18841.322 | E12: ='6. Output-BS'!F25+'6. Output-BS'!F23 -> 36951.324 | F12: ='6. Output-BS'!G25+'6. Output-BS'!G23 -> 17409.703 | G12: =E12 -> 36951.324 | H12: =D12 -> 18841.322
C13: Current Assets | D13: ='6. Output-BS'!E27 -> 3189300.7 | E13: ='6. Output-BS'!F27 -> 2632339.6 | F13: ='6. Output-BS'!G27 -> 2269400.9 | G13: =E13 -> 2632339.6 | H13: =D13 -> 3189300.7
C14: Current Liabilites | D14: ='6. Output-BS'!E72 -> 3065008.1 | E14: ='6. Output-BS'!F72 -> 2561614.5 | F14: ='6. Output-BS'!G72 -> 2091715.4 | G14: =E14 -> 2561614.5 | H14: =D14 -> 3065008.1
B15: 5 | C15: NPM | D15: =D16/D17 -> 0.054896988 | E15: =E16/E17 -> 0.04005365 | F15: =F16/F17 -> 0.080204317 | G15: =E15 -> 0.04005365 | H15: =D15 -> 0.054896988
C16: Net profit after tax | D16: ='7. Output IS'!E43 -> 77556.3 | E16: ='7. Output IS'!F43 -> 69535.797 | F16: ='7. Output IS'!G43 -> 111975.76 | G16: =E16 -> 69535.797 | H16: =D16 -> 77556.3
C17: Net Sales | D17: ='7. Output IS'!E13 -> 1412760.6 | E17: ='7. Output IS'!F13 -> 1736066.4 | F17: ='7. Output IS'!G13 -> 1396131.3 | G17: =E17 -> 1736066.4 | H17: =D17 -> 1412760.6
B18: 6 | C18: ROA | D18: =D19/D20 -> 0.019426111 | E18: =E19/E20 -> 0.02045574 | F18: =F19/F20 -> 0.038740378 | G18: =E18 -> 0.02045574 | H18: =D18 -> 0.019426111
C19: Net profit after tax | D19: =D16 -> 77556.3 | E19: =E16 -> 69535.797 | F19: =F16 -> 111975.76 | G19: =E19 -> 69535.797 | H19: =D19 -> 77556.3
C20: Average Total Assets | D20: ='6. Output-BS'!E49 -> 3992374 | E20: ='6. Output-BS'!F49 -> 3399329.3 | F20: ='6. Output-BS'!G49 -> 2890414.8 | G20: =E20 -> 3399329.3 | H20: =D20 -> 3992374
B21: 7 | C21: Operating Profit to Operating Assets | D21: =D22/D23 -> 0.043024835 | E21: =E22/E23 -> 0.057931519 | F21: =F22/F23 -> 0.069091832 | G21: =E21 -> 0.057931519 | H21: =D21 -> 0.043024835
C22: Operating Profit | D22: ='7. Output IS'!E23 -> 171771.23 | E22: ='7. Output IS'!F23 -> 196928.31 | F22: ='7. Output IS'!G23 -> 199704.05 | G22: =E22 -> 196928.31 | H22: =D22 -> 171771.23
C23: Average Total Assets | D23: ='6. Output-BS'!E49 -> 3992374 | E23: ='6. Output-BS'!F49 -> 3399329.3 | F23: ='6. Output-BS'!G49 -> 2890414.8 | G23: =E23 -> 3399329.3 | H23: =D23 -> 3992374
B24: 8 | C24: Int Cov | D24: =D25/D26 -> 2.1640484 | E24: =E25/E26 -> 1.6813178 | F24: =F25/F26 -> 2.9173829 | G24: =E24 -> 1.6813178 | H24: =D24 -> 2.1640484
C25: Earning Before Interest and Tax | D25: ='7. Output IS'!E36 -> 173746.24 | E25: ='7. Output IS'!F36 -> 199713.92 | F25: ='7. Output IS'!G36 -> 200442.43 | G25: =E25 -> 199713.92 | H25: =D25 -> 173746.24
C26: Interest Expense | D26: ='7. Output IS'!E37 -> 80287.596 | E26: ='7. Output IS'!F37 -> 118784.16 | F26: ='7. Output IS'!G37 -> 68706.248 | G26: =E26 -> 118784.16 | H26: =D26 -> 80287.596
B27: 9 | C27: DSCR | D27: =D28/D29 -> 1.4160266 | E27: =E28/E29 -> 1.2305544 | F27: =F28/F29 -> 1.713076 | G27: =E27 -> 1.2305544 | H27: =D27 -> 1.4160266
C28: Earning Before Interest Tax Depreciation Amortization | D28: ='7. Output IS'!E36+'7. Output IS'!E19 -> 194616.28 | E28: ='7. Output IS'!F36+'7. Output IS'!F19 -> 219104.24 | F28: ='7. Output IS'!G36+'7. Output IS'!G19 -> 213771.42 | G28: =E28 -> 219104.24 | H28: =D28 -> 194616.28
C29: Debts to be Serviced | D29: ='6. Output-BS'!E54+'6. Output-BS'!E55+'7. Output IS'!E37+'6. Output-BS'!E67 -> 137438.29 | E29: ='6. Output-BS'!F54+'6. Output-BS'!F55+'7. Output IS'!F37+'6. Output-BS'!F67 -> 178053.27 | F29: ='6. Output-BS'!G54+'6. Output-BS'!G55+'7. Output IS'!G37+'6. Output-BS'!G67 -> 124788.06 | G29: =E29 -> 178053.27 | H29: =D29 -> 137438.29
B30: 10 | C30: Financial Debt to Operating Cash Flow | D30: =D31/D32 -> 29.266778 | E30: =E31/E32 -> 6.1730621 | F30: =F31/F32 -> -2.7574293 | G30: =E30 -> 6.1730621 | H30: =D30 -> 29.266778
C31: Total Debt | D31: ='6. Output-BS'!E74+'6. Output-BS'!E77+'6. Output-BS'!E78+'6. Output-BS'!E79+'6. Output-BS'!E51+'6. Output-BS'!E52+'6. Output-BS'!E53+'6. Output-BS'!E55+'6. Output-BS'!E55 -> 3078017.1 | E31: ='6. Output-BS'!F74+'6. Output-BS'!F77+'6. Output-BS'!F78+'6. Output-BS'!F79+'6. Output-BS'!F51+'6. Output-BS'!F52+'6. Output-BS'!F53+'6. Output-BS'!F55+'6. Output-BS'!F55 -> 2459358.9 | F31: ='6. Output-BS'!G74+'6. Output-BS'!G77+'6. Output-BS'!G78+'6. Output-BS'!G79+'6. Output-BS'!G51+'6. Output-BS'!G52+'6. Output-BS'!G53+'6. Output-BS'!G55+'6. Output-BS'!G55 -> 1994142.3 | G31: =E31 -> 2459358.9 | H31: =D31 -> 3078017.1
C32: Operating Cash flow | D32: ='8. Output CF'!E11 -> 105171.03 | E32: ='8. Output CF'!F11 -> 398401.77 | F32: ='8. Output CF'!G11 -> -723188.92 | G32: =E32 -> 398401.77 | H32: =D32 -> 105171.03
B33: 11 | C33: Cash Cov | D33: =D34/D35 -> 0.76522361 | E33: =E34/E35 -> 2.2375425 | F33: =F34/F35 -> -5.7953376 | G33: =E33 -> 2.2375425 | H33: =D33 -> 0.76522361
C34: Operating Cash flow | D34: ='8. Output CF'!E11 -> 105171.03 | E34: ='8. Output CF'!F11 -> 398401.77 | F34: ='8. Output CF'!G11 -> -723188.92 | G34: =E34 -> 398401.77 | H34: =D34 -> 105171.03
C35: Debt to be serviced | D35: =D29 -> 137438.29 | E35: =E29 -> 178053.27 | F35: =F29 -> 124788.06 | G35: =E35 -> 178053.27 | H35: =D35 -> 137438.29
B36: 12 | C36: Stock Turnover Days | D36: =D37/D38*360 -> 0 | E36: =E37/E38*360 -> 0 | F36: =F37/F38*360 -> 0 | G36: =E36 -> 0 | H36: =D36 -> 0
C37: Total Inventory | D37: ='6. Output-BS'!E33 -> 0 | E37: ='6. Output-BS'!F33 -> 0 | F37: ='6. Output-BS'!G33 -> 0 | G37: =E37 -> 0 | H37: =D37 -> 0
C38: COGS | D38: ='7. Output IS'!E14 -> 1187045.5 | E38: ='7. Output IS'!F14 -> 1473623.9 | F38: ='7. Output IS'!G14 -> 1144305.5 | G38: =E38 -> 1473623.9 | H38: =D38 -> 1187045.5
B39: 13 | C39: Trade Debtor Collection Days | D39: =(D40/D41)*360 -> 89.219452 | E39: =(E40/E41)*360 -> 195.71035 | F39: =(F40/F41)*360 -> 131.32814 | G39: =E39 -> 195.71035 | H39: =D39 -> 89.219452
C40: Total Accoutns Receivable | D40: ='6. Output-BS'!E13 -> 350127.01 | E40: ='6. Output-BS'!F13 -> 943794.93 | F40: ='6. Output-BS'!G13 -> 509309.24 | G40: =E40 -> 943794.93 | H40: =D40 -> 350127.01
C41: Sales | D41: ='7. Output IS'!E13 -> 1412760.6 | E41: ='7. Output IS'!F13 -> 1736066.4 | F41: ='7. Output IS'!G13 -> 1396131.3 | G41: =E41 -> 1736066.4 | H41: =D41 -> 1412760.6
B42: 14 | C42: Asset Turnover | D42: =D43/D44 -> 0.35386479 | E42: =E43/E44 -> 0.51070853 | F42: =F43/F44 -> 0.4830211 | G42: =E42 -> 0.51070853 | H42: =D42 -> 0.35386479
C43: Sales | D43: =D41 -> 1412760.6 | E43: =E41 -> 1736066.4 | F43: =F41 -> 1396131.3 | G43: =E43 -> 1736066.4 | H43: =D43 -> 1412760.6
C44: Average Total Assets | D44: =D20 -> 3992374 | E44: =E20 -> 3399329.3 | F44: =F20 -> 2890414.8 | G44: =E44 -> 3399329.3 | H44: =D44 -> 3992374
B45: 15 | C45: Operating Cash Flow to Sales | D45: =D46/D47 -> 0.074443631 | E45: =E46/E47 -> 0.22948533 | F45: =F46/F47 -> -0.51799491 | G45: =E45 -> 0.22948533 | H45: =D45 -> 0.074443631
C46: Operating Cashflow | D46: =D34 -> 105171.03 | E46: =E34 -> 398401.77 | F46: =F34 -> -723188.92 | G46: =E46 -> 398401.77 | H46: =D46 -> 105171.03
C47: Sales | D47: =D41 -> 1412760.6 | E47: =E41 -> 1736066.4 | F47: =F41 -> 1396131.3 | G47: =E47 -> 1736066.4 | H47: =D47 -> 1412760.6
B48: 16 | C48: Cashflow based accrual ratio | D48: =D52/D53 -> -0.022279384 | E48: =E52/E53 -> -0.15918539 | F48: =F52/F53 -> 0.32257783 | G48: =E48 -> -0.15918539 | H48: =D48 -> -0.022279384
C49: Operating Assets Y1 | D49: ='6. Output-BS'!E49-Graph!D12 -> 3973532.6 | E49: ='6. Output-BS'!F49-Graph!E12 -> 3362377.9 | F49: ='6. Output-BS'!G49-Graph!F12 -> 2873005 | G49: =E49 -> 3362377.9 | H49: =D49 -> 3973532.6
C50: Operating Liabilities Y1 | D50: ='6. Output-BS'!E84-'6. Output-BS'!E78-'6. Output-BS'!E52-'6. Output-BS'!E53-'6. Output-BS'!E54-'6. Output-BS'!E55 -> 187139.62 | E50: ='6. Output-BS'!F84-'6. Output-BS'!F78-'6. Output-BS'!F52-'6. Output-BS'!F53-'6. Output-BS'!F54-'6. Output-BS'!F55 -> 276096.1 | F50: ='6. Output-BS'!G84-'6. Output-BS'!G78-'6. Output-BS'!G52-'6. Output-BS'!G53-'6. Output-BS'!G54-'6. Output-BS'!G55 -> 357241.73 | G50: =E50 -> 276096.1 | H50: =D50 -> 187139.62
C51: Net Operating Assets Y1 | D51: =D49-D50 -> 3786393 | E51: =E49-E50 -> 3086281.8 | F51: =F49-F50 -> 2515763.3 | G51: =E51 -> 3086281.8 | H51: =D51 -> 3786393
C52: NI-CFO+CFI | D52: ='7. Output IS'!E43-'8. Output CF'!E11+'8. Output CF'!E12 -> -84568.391 | E52: ='7. Output IS'!F43-'8. Output CF'!F11+'8. Output CF'!F12 -> -494232.03 | F52: ='7. Output IS'!G43-'8. Output CF'!G11+'8. Output CF'!G12 -> 814337.48 | G52: =E52 -> -494232.03 | H52: =D52 -> -84568.391
C53: Average Net Operating Assets | D53: =AVERAGE(D54:D55) -> 3795813.7 | E53: =AVERAGE(E54:E55) -> 3104757.5 | F53: =AVERAGE(F54:F55) -> 2524468.2 | G53: =E53 -> 3104757.5 | H53: =D53 -> 3795813.7
C54: Net Operating Assets Y1 | D54: =D49-D50 -> 3786393 | E54: =E49-E50 -> 3086281.8 | F54: =F49-F50 -> 2515763.3 | G54: =E54 -> 3086281.8 | H54: =D54 -> 3786393
C55: Net Operating Assets Y0 | D55: =D56-D57 -> 3805234.4 | E55: =E56-E57 -> 3123233.2 | F55: =F56-F57 -> 2533173 | G55: =E55 -> 3123233.2 | H55: =D55 -> 3805234.4
C56: Operating Assets Y0 | D56: ='6. Output-BS'!E49-'6. Output-BS'!E44-'6. Output-BS'!E46 -> 3992374 | E56: ='6. Output-BS'!F49-'6. Output-BS'!F44-'6. Output-BS'!F46 -> 3399329.3 | F56: ='6. Output-BS'!G49-'6. Output-BS'!G44-'6. Output-BS'!G46 -> 2890414.8 | G56: =E56 -> 3399329.3 | H56: =D56 -> 3992374
C57: Operating Liabilities Y0 | D57: ='6. Output-BS'!E84-'6. Output-BS'!E78-'6. Output-BS'!E52-'6. Output-BS'!E53-'6. Output-BS'!E54-'6. Output-BS'!E55 -> 187139.62 | E57: ='6. Output-BS'!F84-'6. Output-BS'!F78-'6. Output-BS'!F52-'6. Output-BS'!F53-'6. Output-BS'!F54-'6. Output-BS'!F55 -> 276096.1 | F57: ='6. Output-BS'!G84-'6. Output-BS'!G78-'6. Output-BS'!G52-'6. Output-BS'!G53-'6. Output-BS'!G54-'6. Output-BS'!G55 -> 357241.73 | G57: =E57 -> 276096.1 | H57: =D57 -> 187139.62

Sheet 9. Inputs-Analysis
B2: Components for Analysis
C3: Year | D3: ='6. Output-BS'!E9 -> 2025 | E3: ='6. Output-BS'!F9 -> 2024 | F3: ='6. Output-BS'!G9 -> 2023
B4: 1 | C4: 1. Financial Debt to Tangible Net Worth (DTN) | D4: =D5/D6 -> 3.9252586 | E4: =E5/E6 -> 3.492468 | F4: =F5/F6 -> 3.1993553
C5: Total Financial Debt | D5: ='6. Output-BS'!E51+'6. Output-BS'!E52+'6. Output-BS'!E53+'6. Output-BS'!E54+'6. Output-BS'!E55+'6. Output-BS'!E74+'6. Output-BS'!E78+'6. Output-BS'!E79+'6. Output-BS'!E77 -> 3135167.8 | E5: ='6. Output-BS'!F51+'6. Output-BS'!F52+'6. Output-BS'!F53+'6. Output-BS'!F54+'6. Output-BS'!F55+'6. Output-BS'!F74+'6. Output-BS'!F78+'6. Output-BS'!F79+'6. Output-BS'!F77 -> 2518628 | F5: ='6. Output-BS'!G51+'6. Output-BS'!G52+'6. Output-BS'!G53+'6. Output-BS'!G54+'6. Output-BS'!G55+'6. Output-BS'!G74+'6. Output-BS'!G78+'6. Output-BS'!G79+'6. Output-BS'!G77 -> 2050224.1 | G5: TCL+TNCL
C6: Total Tangible Net Worth | D6: ='6. Output-BS'!E97-'6. Output-BS'!E33-'6. Output-BS'!E34-'6. Output-BS'!E35 -> 798716.24 | E6: ='6. Output-BS'!F97-'6. Output-BS'!F33-'6. Output-BS'!F34-'6. Output-BS'!F35-('6. Output-BS'!F93*0.25) -> 721159.94 | F6: ='6. Output-BS'!G97-'6. Output-BS'!G33-'6. Output-BS'!G34-'6. Output-BS'!G35-('6. Output-BS'!G93*0.25) -> 640824.14 | G6: Equity-goodwil-patent-software-other intangibles-50% of revaluation reserve
B7: 2 | C7: 2. Financial Debt to Total Assets (DTA) | D7: =D8/D9 -> 0.78528911 | E7: =E8/E9 -> 0.74091911 | F7: =F8/F9 -> 0.7093183
C8: Total Financial Debt | D8: =D5 -> 3135167.8 | E8: =E5 -> 2518628 | F8: =F5 -> 2050224.1 | G8: Long term loan+ Long term Lease+ intercompany lease
C9: Total Assets | D9: ='6. Output-BS'!E49 -> 3992374 | E9: ='6. Output-BS'!F49 -> 3399329.3 | F9: ='6. Output-BS'!G49 -> 2890414.8
B10: 3 | C10: 2. Cash Ratio (Cash) | D10: =D12/D14 -> 0.0061472341 | E10: =E12/E14 -> 0.014425013 | F10: =F12/F14 -> 0.00832317
B11: 4 | C11: 1. Current Ratio (CR) | D11: =D13/D14 -> 1.0405522 | E11: =E13/E14 -> 1.0276096 | F11: =F13/F14 -> 1.0849472
C12: Cash and easily marketable securities | D12: ='6. Output-BS'!E25+'6. Output-BS'!E23 -> 18841.322 | E12: ='6. Output-BS'!F25+'6. Output-BS'!F23 -> 36951.324 | F12: ='6. Output-BS'!G25+'6. Output-BS'!G23 -> 17409.703 | G12: cash+bank balance+investment held for sale
C13: Current Assets | D13: ='6. Output-BS'!E27 -> 3189300.7 | E13: ='6. Output-BS'!F27 -> 2632339.6 | F13: ='6. Output-BS'!G27 -> 2269400.9 | G13: TCA
C14: Current Liabilites | D14: ='6. Output-BS'!E72 -> 3065008.1 | E14: ='6. Output-BS'!F72 -> 2561614.5 | F14: ='6. Output-BS'!G72 -> 2091715.4
B15: 5 | C15: 1. Net Profit Margin (NPM) | D15: =D16/D17 -> 0.054896988 | E15: =E16/E17 -> 0.04005365 | F15: =F16/F17 -> 0.080204317
C16: Net profit after tax | D16: ='7. Output IS'!E43 -> 77556.3 | E16: ='7. Output IS'!F43 -> 69535.797 | F16: ='7. Output IS'!G43 -> 111975.76
C17: Net Sales | D17: ='7. Output IS'!E13 -> 1412760.6 | E17: ='7. Output IS'!F13 -> 1736066.4 | F17: ='7. Output IS'!G13 -> 1396131.3
B18: 6 | C18: 2. Return on Assets (ROA) | D18: =D19/D20 -> 0.019426111 | E18: =E19/E20 -> 0.02045574 | F18: =F19/F20 -> 0.038740378
C19: Net profit after tax | D19: =D16 -> 77556.3 | E19: =E16 -> 69535.797 | F19: =F16 -> 111975.76
C20: Average Total Assets | D20: ='6. Output-BS'!E49 -> 3992374 | E20: ='6. Output-BS'!F49 -> 3399329.3 | F20: ='6. Output-BS'!G49 -> 2890414.8
B21: 7 | C21: 3. Operating Profit to Operating Assets (OPOA) | D21: =D22/D23 -> 0.04652054 | E21: =E22/E23 -> 0.063539008 | F21: =F22/F23 -> 0.077093466
C22: Operating Profit | D22: ='7. Output IS'!E23 -> 171771.23 | E22: ='7. Output IS'!F23 -> 196928.31 | F22: ='7. Output IS'!G23 -> 199704.05
C23: Operating Assets | D23: ='6. Output-BS'!E49-'6. Output-BS'!E37-'6. Output-BS'!E38-'6. Output-BS'!E40-'6. Output-BS'!E36 -> 3692374 | E23: ='6. Output-BS'!F49-'6. Output-BS'!F37-'6. Output-BS'!F38-'6. Output-BS'!F40-'6. Output-BS'!F36 -> 3099329.3 | F23: ='6. Output-BS'!G49-'6. Output-BS'!G37-'6. Output-BS'!G38-'6. Output-BS'!G40-'6. Output-BS'!G36 -> 2590414.8
B24: 8 | C24: 1. Interest Coverage (IC) | D24: =D25/D26 -> 2.1640484 | E24: =E25/E26 -> 1.6813178 | F24: =F25/F26 -> 2.9173829
C25: Earning Before Interest and Tax | D25: ='7. Output IS'!E36 -> 173746.24 | E25: ='7. Output IS'!F36 -> 199713.92 | F25: ='7. Output IS'!G36 -> 200442.43
C26: Interest Expense | D26: ='7. Output IS'!E37 -> 80287.596 | E26: ='7. Output IS'!F37 -> 118784.16 | F26: ='7. Output IS'!G37 -> 68706.248
B27: 9 | C27: 2. Debt Service Coverage Ratio (DSCR) | D27: =D28/D29 -> 1.4160266 | E27: =E28/E29 -> 1.2305544 | F27: =F28/F29 -> 1.713076
C28: Earning Before Interest Tax Depreciation Amortization | D28: ='7. Output IS'!E36+'7. Output IS'!E19 -> 194616.28 | E28: ='7. Output IS'!F36+'7. Output IS'!F19 -> 219104.24 | F28: ='7. Output IS'!G36+'7. Output IS'!G19 -> 213771.42
C29: Debts to be Serviced | D29: ='6. Output-BS'!E54+'6. Output-BS'!E55+'7. Output IS'!E37+'6. Output-BS'!E67 -> 137438.29 | E29: ='6. Output-BS'!F54+'6. Output-BS'!F55+'7. Output IS'!F37+'6. Output-BS'!F67 -> 178053.27 | F29: ='6. Output-BS'!G54+'6. Output-BS'!G55+'7. Output IS'!G37+'6. Output-BS'!G67 -> 124788.06
B30: 10 | C30: 3. Operating Cashflow to Debt Ratio (CDR) | D30: =D32/D31 -> 0.033545581 | E30: =E32/E31 -> 0.15818206 | F30: =F32/F31 -> -0.35273652
C31: Total Financial Debt | D31: =D5 -> 3135167.8 | E31: =E5 -> 2518628 | F31: =F5 -> 2050224.1
C32: Operating Cash flow | D32: ='8. Output CF'!E11 -> 105171.03 | E32: ='8. Output CF'!F11 -> 398401.77 | F32: ='8. Output CF'!G11 -> -723188.92
B33: 11 | C33: 4. Cashflow Coverage Ratio (CCR) | D33: =D34/D35 -> 0.76522361 | E33: =E34/E35 -> 2.2375425 | F33: =F34/F35 -> -5.7953376
C34: Operating Cash flow | D34: ='8. Output CF'!E11 -> 105171.03 | E34: ='8. Output CF'!F11 -> 398401.77 | F34: ='8. Output CF'!G11 -> -723188.92
C35: Debt to be serviced | D35: =D29 -> 137438.29 | E35: =E29 -> 178053.27 | F35: =F29 -> 124788.06
B36: 12 | C36: 1. Stock Turnover Days (STD) | D36: =D37/D38*360 -> 823.7278 | E36: =E37/E38*360 -> 377.98396 | F36: =F37/F38*360 -> 502.13632
C37: Total Inventory | D37: ='6. Output-BS'!E12 -> 2716117.7 | E37: ='6. Output-BS'!F12 -> 1547239.4 | F37: ='6. Output-BS'!G12 -> 1596103.7
C38: COGS | D38: ='7. Output IS'!E14 -> 1187045.5 | E38: ='7. Output IS'!F14 -> 1473623.9 | F38: ='7. Output IS'!G14 -> 1144305.5
B39: 13 | C39: 2. Trade Debtor Collection Days (TDCD) | D39: =(D40/D41)*360 -> 89.219452 | E39: =(E40/E41)*360 -> 195.71035 | F39: =(F40/F41)*360 -> 131.32814
C40: Total Accoutns Receivable | D40: ='6. Output-BS'!E13 -> 350127.01 | E40: ='6. Output-BS'!F13 -> 943794.93 | F40: ='6. Output-BS'!G13 -> 509309.24
C41: Sales | D41: ='7. Output IS'!E13 -> 1412760.6 | E41: ='7. Output IS'!F13 -> 1736066.4 | F41: ='7. Output IS'!G13 -> 1396131.3
B42: 14 | C42: 3. Asset Turnover (AT) | D42: =D43/D44 -> 0.35386479 | E42: =E43/E44 -> 0.51070853 | F42: =F43/F44 -> 0.4830211
C43: Sales | D43: =D41 -> 1412760.6 | E43: =E41 -> 1736066.4 | F43: =F41 -> 1396131.3
C44: Average Total Assets | D44: =D20 -> 3992374 | E44: =E20 -> 3399329.3 | F44: =F20 -> 2890414.8
B45: 15 | C45: 1. Operating Cash Flow to Sales (CFS) | D45: =D46/D47 -> 0.074443631 | E45: =E46/E47 -> 0.22948533 | F45: =F46/F47 -> -0.51799491
C46: Operating Cashflow | D46: =D34 -> 105171.03 | E46: =E34 -> 398401.77 | F46: =F34 -> -723188.92
C47: Sales | D47: =D41 -> 1412760.6 | E47: =E41 -> 1736066.4 | F47: =F41 -> 1396131.3
B48: 16 | C48: 2. Cashflow based accrual ratio (CAR) | D48: =D52/D53 -> 0.0077292885 | E48: =E52/E53 -> -0.052661093 | F48: =F52/F53 -> 0.3390781
C49: Operating Assets Y1 | D49: ='6. Output-BS'!E49-'9. Inputs-Analysis'!D12 -> 3973532.6 | E49: ='6. Output-BS'!F49-'9. Inputs-Analysis'!E12 -> 3362377.9 | F49: ='6. Output-BS'!G49-'9. Inputs-Analysis'!F12 -> 2873005
C50: Operating Liabilities Y1 | D50: ='6. Output-BS'!E84-'6. Output-BS'!E78-'6. Output-BS'!E52-'6. Output-BS'!E53-'6. Output-BS'!E54-'6. Output-BS'!E55 -> 187139.62 | E50: ='6. Output-BS'!F84-'6. Output-BS'!F78-'6. Output-BS'!F52-'6. Output-BS'!F53-'6. Output-BS'!F54-'6. Output-BS'!F55 -> 276096.1 | F50: ='6. Output-BS'!G84-'6. Output-BS'!G78-'6. Output-BS'!G52-'6. Output-BS'!G53-'6. Output-BS'!G54-'6. Output-BS'!G55 -> 357241.73
C51: Net Operating Assets Y1 | D51: =D49-D50 -> 3786393 | E51: =E49-E50 -> 3086281.8 | F51: =F49-F50 -> 2515763.3
C52: NI-CFO-CFI | D52: ='7. Output IS'!E43-'8. Output CF'!E11-'8. Output CF'!E12 -> 29338.939 | E52: ='7. Output IS'!F43-'8. Output CF'!F11-'8. Output CF'!F12 -> -163499.92 | F52: ='7. Output IS'!G43-'8. Output CF'!G11-'8. Output CF'!G12 -> 855991.88
C53: Average Net Operating Assets | D53: =AVERAGE(D54:D55) -> 3795813.7 | E53: =AVERAGE(E54:E55) -> 3104757.5 | F53: =AVERAGE(F54:F55) -> 2524468.2
C54: Net Operating Assets Y1 | D54: =D49-D50 -> 3786393 | E54: =E49-E50 -> 3086281.8 | F54: =F49-F50 -> 2515763.3
C55: Net Operating Assets Y0 | D55: =D56-D57 -> 3805234.4 | E55: =E56-E57 -> 3123233.2 | F55: =F56-F57 -> 2533173
C56: Operating Assets Y0 | D56: ='6. Output-BS'!E49-'6. Output-BS'!E44-'6. Output-BS'!E46 -> 3992374 | E56: ='6. Output-BS'!F49-'6. Output-BS'!F44-'6. Output-BS'!F46 -> 3399329.3 | F56: ='6. Output-BS'!G49-'6. Output-BS'!G44-'6. Output-BS'!G46 -> 2890414.8
C57: Operating Liabilities Y0 | D57: ='6. Output-BS'!E84-'6. Output-BS'!E78-'6. Output-BS'!E52-'6. Output-BS'!E53-'6. Output-BS'!E54-'6. Output-BS'!E55 -> 187139.62 | E57: ='6. Output-BS'!F84-'6. Output-BS'!F78-'6. Output-BS'!F52-'6. Output-BS'!F53-'6. Output-BS'!F54-'6. Output-BS'!F55 -> 276096.1 | F57: ='6. Output-BS'!G84-'6. Output-BS'!G78-'6. Output-BS'!G52-'6. Output-BS'!G53-'6. Output-BS'!G54-'6. Output-BS'!G55 -> 357241.73

Sheet 9. Quantitative Analysis
A1: Internal Credit Risk Score Sheet
A2: Quantitative Analysis
A3: File / Reference No: | B3: ='11. Detail Managment Report'!D2 -> Outpace Spinning Mills Ltd
A4: Borrowe Name | B4: ='11. Detail Managment Report'!D3 -> Outpace Spinning Mills Ltd
A5: Group Name (if any) | B5: ='11. Detail Managment Report'!D4 -> Outright Group
A6: Industry Name | B6: ='11. Detail Managment Report'!D5 -> 2. Textile | S6: Score | T6: =C55 -> 0.36666667 | U6: =1-T6 -> 0.63333333
A7: Latest CIB Status | B7: ='11. Detail Managment Report'!D6 -> Standard
A8: Audit Status | B8: ='11. Detail Managment Report'!D7 -> Unaudited
A9: Auditor Name | B9: ='11. Detail Managment Report'!D8 -> Dewan Nazrul Islam & Co.
A10: Analyst Name, Designations | B10: ='11. Detail Managment Report'!D9 -> Md. Matiur Rahman, SRM
A11: Verifier Name, Designation | B11: ='11. Detail Managment Report'!D10 -> Farhana Afrin, SM
A13: Date of Analysis | B13: ='11. Detail Managment Report'!D12 -> 45652
A14: Date of Financials | B14: ='11. Detail Managment Report'!D13 -> 45473
A16: Quantitative Indicators (60)
A17: Criteria | B17: Parameter | C17: Scale | D17: Actual Parameter | E17: Score Obtained
A18: A. Leverage | C18: 10 | E18: =E19+E21 -> 1
A19: ='11. Detail Managment Report'!C18 -> 1. Financial Debt to Tangible Net Worth (DTN) | C19: 7 | D19: ='9. Inputs-Analysis'!D4 -> 3.9252586 | E19: ='11. Detail Managment Report'!E18 -> 0
A21: ='11. Detail Managment Report'!C19 -> 2. Financial Debt to Total Assets (DTA) | C21: 3 | D21: ='9. Inputs-Analysis'!D7 -> 0.78528911 | E21: ='11. Detail Managment Report'!E19 -> 1
A23: B. Liquidity | C23: 10 | E23: =E24+E26 -> 5
A24: ='11. Detail Managment Report'!C21 -> 1. Current Ratio (CR) | C24: 7 | D24: ='9. Inputs-Analysis'!D11 -> 1.0405522 | E24: ='11. Detail Managment Report'!E21 -> 5
A26: ='11. Detail Managment Report'!C22 -> 2. Cash Ratio (Cash) | C26: 3 | D26: ='9. Inputs-Analysis'!D10 -> 0.0061472341 | E26: ='11. Detail Managment Report'!E22 -> 0
A28: C. Profitability | C28: 10 | E28: =E29+E31+E33 -> 5
A29: ='11. Detail Managment Report'!C24 -> 1. Net Profit Margin (NPM) | C29: 5 | D29: ='9. Inputs-Analysis'!D15 -> 0.054896988 | E29: ='11. Detail Managment Report'!E24 -> 3
A31: ='11. Detail Managment Report'!C25 -> 2. Return on Assets (ROA) | C31: 3 | D31: ='9. Inputs-Analysis'!D18 -> 0.019426111 | E31: ='11. Detail Managment Report'!E25 -> 1
A33: ='11. Detail Managment Report'!C26 -> 3. Operating Profit to Operating Assets (OPOA) | C33: 2 | D33: ='9. Inputs-Analysis'!D21 -> 0.04652054 | E33: ='11. Detail Managment Report'!E26 -> 1
A35: D. Coverage | C35: 15 | E35: =E36+E38+E40+E42 -> 6
A36: ='11. Detail Managment Report'!C28 -> 1. Interest Coverage (IC) | C36: 3 | D36: ='9. Inputs-Analysis'!D24 -> 2.1640484 | E36: ='11. Detail Managment Report'!E28 -> 1
A38: ='11. Detail Managment Report'!C29 -> 2. Debt Service Coverage Ratio (DSCR) | C38: 5 | D38: ='9. Inputs-Analysis'!D27 -> 1.4160266 | E38: ='11. Detail Managment Report'!E29 -> 2
A40: ='11. Detail Managment Report'!C30 -> 3. Operating Cashflow to Debt Ratio (CDR) | C40: 4 | D40: ='9. Inputs-Analysis'!D30 -> 0.033545581 | E40: ='11. Detail Managment Report'!E30 -> 1
A42: ='11. Detail Managment Report'!C31 -> 4. Cashflow Coverage Ratio (CCR) | C42: 3 | D42: ='9. Inputs-Analysis'!D33 -> 0.76522361 | E42: ='11. Detail Managment Report'!E31 -> 2
A44: E. Operational Efficiency | C44: 10 | E44: =E45+E47+E49 -> 3
A45: ='11. Detail Managment Report'!C33 -> 1. Stock Turnover Days (STD) | D45: ='9. Inputs-Analysis'!D36 -> 823.7278 | E45: ='11. Detail Managment Report'!E33 -> 0
A47: ='11. Detail Managment Report'!C34 -> 2. Trade Debtor Collection Days (TDCD) | D47: ='9. Inputs-Analysis'!D39 -> 89.219452 | E47: ='11. Detail Managment Report'!E34 -> 2
A49: ='11. Detail Managment Report'!C35 -> 3. Asset Turnover (AT) | D49: ='9. Inputs-Analysis'!D42 -> 0.35386479 | E49: ='11. Detail Managment Report'!E35 -> 1
A50: F. Earning Quality | C50: 5 | E50: =E51+E53 -> 2
A51: ='11. Detail Managment Report'!C37 -> 1. Operating Cash Flow to Sales (CFS) | C51: 3 | D51: ='9. Inputs-Analysis'!D45 -> 0.074443631 | E51: ='11. Detail Managment Report'!E37 -> 2
A53: ='11. Detail Managment Report'!C38 -> 2. Cashflow based accrual ratio (CAR) | C53: 2 | D53: ='9. Inputs-Analysis'!D48 -> 0.0077292885 | E53: ='11. Detail Managment Report'!E38 -> 0
A54: Total | C54: =C50+C44+C35+C28+C23+C18 -> 60 | E54: =E50+E44+E35+E28+E23+E18 -> 22
A55: Percentage | C55: =E54/C54 -> 0.36666667

Sheet 10. Qualitative Analysis
B1: Qualitative Analysis
B2: ='11. Detail Managment Report'!B2:C2 -> File / Reference No: | D2: ='11. Detail Managment Report'!D2 -> Outpace Spinning Mills Ltd
B3: ='11. Detail Managment Report'!B3:C3 -> Borrower Name | D3: ='11. Detail Managment Report'!D3 -> Outpace Spinning Mills Ltd
B4: ='11. Detail Managment Report'!B4:C4 -> Group Name (if any) | D4: ='11. Detail Managment Report'!D4 -> Outright Group
B5: ='11. Detail Managment Report'!B5:C5 -> Industry Name | D5: ='11. Detail Managment Report'!D5 -> 2. Textile
B6: ='11. Detail Managment Report'!B6:C6 -> Latest CIB Status | D6: ='11. Detail Managment Report'!D6 -> Standard
B7: ='11. Detail Managment Report'!B7:C7 -> Audit Status | D7: ='11. Detail Managment Report'!D7 -> Unaudited
B8: ='11. Detail Managment Report'!B8:C8 -> Auditor Name | D8: ='11. Detail Managment Report'!D8 -> Dewan Nazrul Islam & Co. | I8: Score Percentage | J8: =G111/40 -> 0.7125 | K8: =1-J8 -> 0.2875
B9: ='11. Detail Managment Report'!B9:C9 -> Analyst Name, Designations | D9: ='11. Detail Managment Report'!D9 -> Md. Matiur Rahman, SRM
B10: ='11. Detail Managment Report'!B10:C10 -> Verifier Name, Designation | D10: ='11. Detail Managment Report'!D10 -> Farhana Afrin, SM
B11: ='11. Detail Managment Report'!B11:C11 -> 0 | D11: ='11. Detail Managment Report'!D11 -> 0
B12: ='11. Detail Managment Report'!B12:C12 -> Date of Analysis | D12: ='11. Detail Managment Report'!D12 -> 45652
B13: ='11. Detail Managment Report'!B13:C13 -> Date of Financials | D13: ='11. Detail Managment Report'!D13 -> 45473
B15: Qualitative Indicators (40)
C16: Criteria | D16: Paraeter | E16: Score | F16: Actual Paramenter | G16: Score Obtained
B17: G | C17: Performance Behavior | E17: =E20+E26+E32 -> 10 | G17: =G19+G25+G31 -> 10
B18: G.1 | C18: Performance behavior with lending banks
B19: G.1.1 | C19: How many times the borrower was adversely classified in last 3 years | F19: O time | G19: =IF(F19=D20,E20,IF(F19=D21,E21,IF(F19=D22,E22,IF(F19=D23,E23,IF(F19=D24,E24))))) -> 5
C20: [ Aversely classified means the borrower's loans classified as per BB loan classifications policy i.e SS, DF, BL] | D20: O time | E20: 5 | H20: =1/5 -> 0.2
D21: 1 time | E21: 4
D22: 2 times | E22: 3
D23: 3 times | E23: 1
D24: >3 times | E24: 0
B25: G1.2 | C25: How many times the borrower's loans was rescheduled/ restructured in last 3 years | F25: 0 time | G25: =IF(F25=D26,E26,IF(F25=D27,E27,IF(F25=D28,E28,IF(F25=D29,E29,IF(F25=D30,E30))))) -> 4
D26: 0 time | E26: 4
D27: 1 time | E27: 3
D28: 2 times | E28: 2
D29: 3 times | E29: 1
D30: >3 times | E30: 0
B31: G.2 | C31: Performance behavior with suppliers/ Creditors | F31: Yes | G31: =IF(F31=D32,E32,IF(F31=D33,E33)) -> 1
C32: Did The Borrower Pay Its Suppliers/ Creditors Regularly In Last 1 Year | D32: Yes | E32: 1
D33: No | E33: 0
B34: H | C34: Business and Industry Risk | E34: =E36+E42+E48+E53 -> 7 | G34: =G35+G41+G47+G52 -> 6
B35: H.1 | C35: Sales Growth | F35: >10% | G35: =IF(F35=D36,E36,IF(F35=D37,E37,IF(F35=D38,E38))) -> 2
C36: * Sales growth means annual sales growth | D36: >10% | E36: 2
C37: The formula for calculating sales growth is [(current year sales - previous year sales)/ previous year sales]*100 | D37: 5%-10% | E37: 1
D38: Less than 5% | E38: 0
B41: H.2 | C41: Age of Business | F41: >10 years | G41: =IF(F41=D42,E42,IF(F41=D43,E43,IF(F41=D44,E44,IF(F41=D45,E45,IF(F41=D46,E46))))) -> 2
C42: The number of years the borrower | D42: >10 years | E42: 2
C43: engaged in this line of business | D43: 7 to 10 years | E43: 1.5
D44: 5 to 7 years | E44: 1
D45: 4 to 5 years | E45: 0.5
D46: <4 years | E46: 0
B47: H.3 | C47: Industry Prospects | F47: Growing but High Volatility | G47: =IF(F47=D48,E48,IF(F47=D49,E49,IF(F47=D50,E50,IF(F47=D51,E51)))) -> 0.5
C48: Critical assessment of 5 (five) years prospect of industry and borrower's sales volatility | D48: Growing and Low Volatility | E48: 1
C49: * Volatility denotes sales volatility | D49: Stable | E49: 0.75
D50: Growing but High Volatility | E50: 0.5
D51: Declining | E51: 0
B52: H.4 | C52: Long-Term External Credit Rating of the Borrower | F52: 2&3 | G52: =IF(F52=D53,E53,IF(F52=D54,E54,IF(F52=D55,E55,IF(F52=D56,E56)))) -> 1.5
D53: 1 | E53: 2
C54: Rating Grade should be assigned in line with BB Rating Mapping as per BRPD circular 18/2014 on Risk-Based Capital Adequacy in line with Basel III (see annex: Rating Mapping) | D54: 2&3 | E54: 1.5
D55: >3 | E55: 0.5
D56: Unrated | E56: 0
B57: I | C57: Management Risk | E57: =E59+E64+E69+E73 -> 7 | G57: =G58+G63+G68+G72 -> 5
B58: I.1 | C58: Experience of the Management | F58: More than 10 years in the related line of business | G58: =IF(F58=D59,E59,IF(F58=D60,E60,IF(F58=D61,E61))) -> 2
C59: Quality of the management based on total number of years of experience of the senior management in the Industry. | D59: More than 10 years in the related line of business | E59: 2
C60: * Senior Management means MD and next two tiers | D60: 5–10 years in the related line of business | E60: 1
D61: Less than 5 years | E61: 0
E62: 0
B63: I.2 | C63: Existence of Succession Plan | F63: Yes, with good capability of successor | G63: =IF(F63=D64,E64,IF(F63=D65,E65,IF(F63=D66,E66))) -> 2
D64: Yes, with good capability of successor | E64: 2
D65: Yes, but questionable capacity of successor | E65: 1
D66: No successor | E66: 0
B68: I.3 | C68: Auditing Firms | F68: Other Auditors | G68: =IF(F68=D69,E69,IF(F68=D70,E70,IF(F68=D71,E71))) -> 1
C69: BSEC listed auditors are considered as recognized | D69: Recognized Auditors | E69: 2
D70: Other Auditors | E70: 1
D71: Un audited | E71: 0
B72: I.4 | C72: Change In External Auditors In Last 4 Years | F72: No | G72: =IF(F72=D73,E73,IF(F72=D74,E74)) -> 0
D73: Yes | E73: 1
D74: No | E74: 0
B75: J | C75: Security Risk | E75: =E77+E82+E87+E93 -> 11 | G75: =G76+G81+G86+G92 -> 2.5
B76: J.1 | C76: Primary Security | F76: Registered Hypothecation (1st Charge/1st Pari Passu Charge) | G76: =IF(F76=D77,E77,IF(F76=D78,E78,IF(F76=D79,E79,IF(F76=D80,E80)))) -> 1.5
D77: Fully Pledged Facilities | E77: 2
D78: Registered Hypothecation (1st Charge/1st Pari Passu Charge) | E78: 1.5
D79: 2nd Charge/Inferior Charge | E79: 1
D80: No Security | E80: 0
B81: J.2 | C81: Collateral | F81: No Collateral | G81: =IF(F81=D82,E82,IF(F81=D83,E83,IF(F81=D84,E84,IF(F81=D85,E85)))) -> 0
D82: Registered Mortgage On Municipal Corporation/Prime Area Property | E82: 2
D83: Registered Mortgage On Pourashava/Semi-Urban/ Union Parishad Area Property | E83: 1.5
D84: Equitable Mortgage Or No Property But Plant And Machinery As Collateral | E84: 1
D85: No Collateral | E85: 0
B86: J.3 | C86: Eligible Collateral Coverage | F86: <50% | G86: =IF(F86=D87,E87,IF(F86=D88,E88,IF(F86=D89,E89,IF(F86=D90,E90,IF(F86=D91,E91))))) -> 0
C87: The formula of eligible collateral coverage is [eligible collateral / total loans] | D87: >100% | E87: 5
D88: 80% to 100% | E88: 4
C89: * Eligible collateral should be determined as per BRPD circular no 14 issued on September 23, 2012 (Para 07, Page 10). (see annex: Eligible Collateral) | D89: 70% to 80% | E89: 3
D90: 50% to 70% | E90: 2
D91: <50% | E91: 0
B92: J.4 | C92: Type of Guarantee | F92: Personal Guarantees or Corporate Guarantee without Strong Financial Strength | G92: =IF(F92=D93,E93,IF(F92=D94,E94,IF(F92=D95,E95,IF(F92=D96,E96)))) -> 1
D93: Government Guarantee and/or Bank Guarantee | E93: 2
C94: Strong Corporate Guarantee means the credit rating of the guarantor should be at least 1 or 2 as per BB rating mapping mentioned in BRPD circular 18/2014 on Risk Based Capital Adequacy in line with Basel III. | D94: Strong Corporate Guarantee | E94: 1.5
D95: Personal Guarantees or Corporate Guarantee without Strong Financial Strength | E95: 1
D96: No support/guarantee | E96: 0
B98: K | C98: Relationship Risk | E98: =E99 -> 3 | G98: =G99 -> 3
B99: K.1 | C99: Account Conduct | D99: More than 3 years Accounts with Faultless Record | E99: 3 | F99: More than 3 years Accounts with Faultless Record | G99: =IF(F99=D99,E99,IF(F99=D100,E100,IF(F99=D101,E101,IF(F99=D102,E102)))) -> 3
D100: Less than 3 years Accounts with faultless record | E100: 2
D101: Accounts having satisfactory dealings with some late payments. | E101: 1
D102: Frequent Past dues & Irregular dealings in account | E102: 0
B104: L | C104: Compliance Risk | E104: =E106+E109 -> 2 | G104: =G105+G108 -> 2
B105: L.1 | C105: Compliance with environmental rules, regulations and covenants | F105: Yes | G105: =IF(F105=D106,E106,IF(F105=D107,E107)) -> 1
D106: Yes | E106: 1
...

Sheet 11. Detail Managment Report
B2: File / Reference No: | D2: ='2. Top Page'!D8 -> Outpace Spinning Mills Ltd | E2: Assessment Criteria: Greater than or equal to 80%= Excellent; 70%-80% = Good; 60% to 70% = Marginal; Less than 60% = Unacceptable
B3: Borrower Name | D3: ='2. Top Page'!D9 -> Outpace Spinning Mills Ltd
B4: Group Name (if any) | D4: ='2. Top Page'!D10 -> Outright Group
B5: Industry Name | D5: ='2. Top Page'!D11 -> 2. Textile
B6: Latest CIB Status | D6: ='2. Top Page'!D15 -> Standard | E6: Indicators | G6: Score Obtained | H6: Risk Rating
B7: Audit Status | D7: ='2. Top Page'!D16 -> Unaudited | E7: Quantitative | G7: =E16 -> 22 | H7: =IF(G8>=80%,"Excellent",IF(G8>=70%,"Good",IF(G8>=50%,"Marginal",IF(G8<50%,"Unacceptable",0)))) -> Unacceptable | J7: Greater than or equal to 85% | K7: Excellent
B8: Auditor Name | D8: =top -> Dewan Nazrul Islam & Co. | G8: =G7/60 -> 0.36666667 | J8: 70%-84% | K8: Good
B9: Analyst Name, Designations | D9: ='2. Top Page'!D18 -> Md. Matiur Rahman, SRM | E9: Qualitative | G9: =E39 -> 28.5 | H9: =IF(G10>=80%,"Excellent",IF(G10>=70%,"Good",IF(G10>=60%,"Marginal",IF(G10<60%,"Unacceptable",0)))) -> Good | J9: 60%-69% | K9: Marginal
B10: Verifier Name, Designation | D10: ='2. Top Page'!D19 -> Farhana Afrin, SM | G10: =G9/40 -> 0.7125 | J10: Less than 50% | K10: Unacceptable
E11: Aggregate | G11: =G7+G9 -> 50.5 | H11: =IF(G8<50%,"Unacceptable",IF(G12>=80%,"Excellent",IF(G12>=70%,"Good",IF(G12>=60%,"Marginal",IF(G12<60%,"Unacceptable",0))))) -> Unacceptable
B12: Date of Analysis | D12: ='2. Top Page'!D21 -> 45652 | G12: =G11/100 -> 0.505
B13: Date of Financials | D13: ='2. Top Page'!D20 -> 45473
D15: Outcome | E15: Score Obtained | F15: Scale | G15: Percentage | H15: Risk Rating
B16: Quantitative Assessments | E16: =E17+E20+E23+E27+E32+E36 -> 22 | F16: =F17+F20+F23+F27+F32+F36 -> 60 | G16: =E16/F16 -> 0.36666667 | H16: =IF(G16>=80%,"Excellent",IF(G16>=70%,"Good",IF(G16>=60%,"Marginal",IF(G16<60%,"Unacceptable",0)))) -> Unacceptable
B17: A | C17: Leverage | E17: =E18+E19 -> 1 | F17: =F18+F19 -> 10 | G17: =E17/F17 -> 0.1 | H17: =IF(G17>=80%,"Excellent",IF(G17>=70%,"Good",IF(G17>=60%,"Marginal",IF(G17<60%,"Unacceptable",0)))) -> Unacceptable
B18: A.1 | C18: ='9. Inputs-Analysis'!C4 -> 1. Financial Debt to Tangible Net Worth (DTN) | D18: =IF(D5='Basic Bullets'!E1,'1. RMG'!D19,IF(D5='Basic Bullets'!E2,'2. Textile '!D19,IF(D5='Basic Bullets'!E3,'3. Food and Allied'!D19,IF(D5='Basic Bullets'!E4,'4. Pharmaceutical'!D19,IF(D5='Basic Bullets'!E5,'5. Chemical'!D19,IF(D5='Basic Bullets'!E6,'6. Fertilizer'!D19,IF(D5='Basic Bullets'!E7,'7.Cement'!D19,IF(D5='Basic Bullets'!E8,'8. Ceramic'!D19,IF(D5='Basic Bullets'!E9,'9. Ship Building'!D19,IF(D5='Basic Bullets'!E10,'10. Ship Breaking'!D19,IF(D5='Basic Bullets'!E11,'11. Jute Mills'!D19,IF(D5='Basic Bullets'!E12,'12. Steel Engineering '!D19,IF(D5='Basic Bullets'!E13,'13.Power and gas'!D19,IF(D5='Basic Bullets'!E14,'14. Industry_Others'!D19,IF(D5='Basic Bullets'!E15,'B. Trade and commerce'!D19,IF(D5='Basic Bullets'!E16,'C. Agro'!D19,IF(D5='Basic Bullets'!E17,'1. Service_Housing&Cnst'!D19,IF(D5='Basic Bullets'!E18,'2. Service_Telecom'!D19,IF(D5='Basic Bullets'!E19,'3. Servic_Hospitals&Clinics'!D19,IF(D5='Basic Bullets'!E20,'3. Service_ Others '!D19,0)))))))))))))))))))) -> 3.9252586 | E18: =IF(D5='Basic Bullets'!E1,'1. RMG'!E19,IF(D5='Basic Bullets'!E2,'2. Textile '!E19,IF(D5='Basic Bullets'!E3,'3. Food and Allied'!E19,IF(D5='Basic Bullets'!E4,'4. Pharmaceutical'!E19,IF(D5='Basic Bullets'!E5,'5. Chemical'!E19,IF(D5='Basic Bullets'!E6,'6. Fertilizer'!E19,IF(D5='Basic Bullets'!E7,'7.Cement'!E19,IF(D5='Basic Bullets'!E8,'8. Ceramic'!E19,IF(D5='Basic Bullets'!E9,'9. Ship Building'!E19,IF(D5='Basic Bullets'!E10,'10. Ship Breaking'!E19,IF(D5='Basic Bullets'!E11,'11. Jute Mills'!E19,IF(D5='Basic Bullets'!E12,'12. Steel Engineering '!E19,IF(D5='Basic Bullets'!E13,'13.Power and gas'!E19,IF(D5='Basic Bullets'!E14,'14. Industry_Others'!E19,IF(D5='Basic Bullets'!E15,'B. Trade and commerce'!E19,IF(D5='Basic Bullets'!E16,'C. Agro'!E19,IF(D5='Basic Bullets'!E17,'1. Service_Housing&Cnst'!E19,IF(D5='Basic Bullets'!E18,'2. Service_Telecom'!E19,IF(D5='Basic Bullets'!E19,'3. Servic_Hospitals&Clinics'!E19,IF(D5='Basic Bullets'!E20,'3. Service_ Others '!E19,0)))))))))))))))))))) -> 0 | F18: 7 | G18: =E18/F18 -> 0 | H18: =IF(G18>=80%,"Excellent",IF(G18>=70%,"Good",IF(G18>=60%,"Marginal",IF(G18<60%,"Unacceptable",0)))) -> Unacceptable | J18: IF(D5='Basic Bullets'!E1,1,IF(D5='Basic Bullets'!E2,2,IF(D5='Basic Bullets'!E3,3,IF(D5='Basic Bullets'!E4,4,IF(D5='Basic Bullets'!E5,5,IF(D5='Basic Bullets'!E6,6,IF(D5='Basic Bullets'!E7,7,IF(D5='Basic Bullets'!E8,8,IF(D5='Basic Bullets'!E9,9,IF(D5='Basic Bullets'!E10,10,IF(D5='Basic Bullets'!E11,11,IF(D5='Basic Bullets'!E12,12,IF(D5='Basic Bullets'!E13,13,IF(D5='Basic Bullets'!E14,14,IF(D5='Basic Bullets'!E15,15,IF(D5='Basic Bullets'!E16,16, IF(D5='Basic Bullets'!E17,17,IF(D5='Basic Bullets'!E18,18,IF(D5='Basic Bullets'!E19,19,IF(D5='Basic Bullets'!E20,20,
B19: B.2 | C19: ='9. Inputs-Analysis'!C7 -> 2. Financial Debt to Total Assets (DTA) | D19: =IF(D5='Basic Bullets'!E1,'1. RMG'!D29,IF(D5='Basic Bullets'!E2,'2. Textile '!D29,IF(D5='Basic Bullets'!E3,'3. Food and Allied'!D29,IF(D5='Basic Bullets'!E4,'4. Pharmaceutical'!D29,IF(D5='Basic Bullets'!E5,'5. Chemical'!D29,IF(D5='Basic Bullets'!E6,'6. Fertilizer'!D29,IF(D5='Basic Bullets'!E7,'7.Cement'!D29,IF(D5='Basic Bullets'!E8,'8. Ceramic'!D29,IF(D5='Basic Bullets'!E9,'9. Ship Building'!D29,IF(D5='Basic Bullets'!E10,'10. Ship Breaking'!D29,IF(D5='Basic Bullets'!E11,'11. Jute Mills'!D29,IF(D5='Basic Bullets'!E12,'12. Steel Engineering '!D29,IF(D5='Basic Bullets'!E13,'13.Power and gas'!D29,IF(D5='Basic Bullets'!E14,'14. Industry_Others'!D29,IF(D5='Basic Bullets'!E15,'B. Trade and commerce'!D29,IF(D5='Basic Bullets'!E16,'C. Agro'!D29,IF(D5='Basic Bullets'!E17,'1. Service_Housing&Cnst'!D29,IF(D5='Basic Bullets'!E18,'2. Service_Telecom'!D29,IF(D5='Basic Bullets'!E19,'3. Servic_Hospitals&Clinics'!D29,IF(D5='Basic Bullets'!E20,'3. Service_ Others '!D29,0)))))))))))))))))))) -> 0.78528911 | E19: =IF(D5='Basic Bullets'!E1,'1. RMG'!E29,IF(D5='Basic Bullets'!E2,'2. Textile '!E29,IF(D5='Basic Bullets'!E3,'3. Food and Allied'!E29,IF(D5='Basic Bullets'!E4,'4. Pharmaceutical'!E29,IF(D5='Basic Bullets'!E5,'5. Chemical'!E29,IF(D5='Basic Bullets'!E6,'6. Fertilizer'!E29,IF(D5='Basic Bullets'!E7,'7.Cement'!E29,IF(D5='Basic Bullets'!E8,'8. Ceramic'!E29,IF(D5='Basic Bullets'!E9,'9. Ship Building'!E29,IF(D5='Basic Bullets'!E10,'10. Ship Breaking'!E29,IF(D5='Basic Bullets'!E11,'11. Jute Mills'!E29,IF(D5='Basic Bullets'!E12,'12. Steel Engineering '!E29,IF(D5='Basic Bullets'!E13,'13.Power and gas'!E29,IF(D5='Basic Bullets'!E14,'14. Industry_Others'!E29,IF(D5='Basic Bullets'!E15,'B. Trade and commerce'!E29,IF(D5='Basic Bullets'!E16,'C. Agro'!E29,IF(D5='Basic Bullets'!E17,'1. Service_Housing&Cnst'!E29,IF(D5='Basic Bullets'!E18,'2. Service_Telecom'!E29,IF(D5='Basic Bullets'!E19,'3. Servic_Hospitals&Clinics'!E29,IF(D5='Basic Bullets'!E20,'3. Service_ Others '!E29,0)))))))))))))))))))) -> 1 | F19: 3 | G19: =E19/F19 -> 0.33333333 | H19: =IF(G19>=80%,"Excellent",IF(G19>=70%,"Good",IF(G19>=60%,"Marginal",IF(G19<60%,"Unacceptable",0)))) -> Unacceptable
B20: B | C20: Liquidity | E20: =SUM(E21:E22) -> 5 | F20: =SUM(F21:F22) -> 10 | G20: =E20/F20 -> 0.5 | H20: =IF(G20>=80%,"Excellent",IF(G20>=70%,"Good",IF(G20>=60%,"Marginal",IF(G20<60%,"Unacceptable",0)))) -> Unacceptable
B21: B.1 | C21: ='9. Inputs-Analysis'!C11 -> 1. Current Ratio (CR) | D21: =IF(D5='Basic Bullets'!E1,'1. RMG'!D37,IF(D5='Basic Bullets'!E2,'2. Textile '!D37,IF(D5='Basic Bullets'!E3,'3. Food and Allied'!D37,IF(D5='Basic Bullets'!E4,'4. Pharmaceutical'!D37,IF(D5='Basic Bullets'!E5,'5. Chemical'!D37,IF(D5='Basic Bullets'!E6,'6. Fertilizer'!D37,IF(D5='Basic Bullets'!E7,'7.Cement'!D37,IF(D5='Basic Bullets'!E8,'8. Ceramic'!D37,IF(D5='Basic Bullets'!E9,'9. Ship Building'!D37,IF(D5='Basic Bullets'!E10,'10. Ship Breaking'!D37,IF(D5='Basic Bullets'!E11,'11. Jute Mills'!D37,IF(D5='Basic Bullets'!E12,'12. Steel Engineering '!D37,IF(D5='Basic Bullets'!E13,'13.Power and gas'!D37,IF(D5='Basic Bullets'!E14,'14. Industry_Others'!D37,IF(D5='Basic Bullets'!E15,'B. Trade and commerce'!D37,IF(D5='Basic Bullets'!E16,'C. Agro'!D37,IF(D5='Basic Bullets'!E17,'1. Service_Housing&Cnst'!D37,IF(D5='Basic Bullets'!E18,'2. Service_Telecom'!D37,IF(D5='Basic Bullets'!E19,'3. Servic_Hospitals&Clinics'!D37,IF(D5='Basic Bullets'!E20,'3. Service_ Others '!D37,0)))))))))))))))))))) -> 1.0405522 | E21: =IF(D5='Basic Bullets'!E1,'1. RMG'!E37,IF(D5='Basic Bullets'!E2,'2. Textile '!E37,IF(D5='Basic Bullets'!E3,'3. Food and Allied'!E37,IF(D5='Basic Bullets'!E4,'4. Pharmaceutical'!E37,IF(D5='Basic Bullets'!E5,'5. Chemical'!E37,IF(D5='Basic Bullets'!E6,'6. Fertilizer'!E37,IF(D5='Basic Bullets'!E7,'7.Cement'!E37,IF(D5='Basic Bullets'!E8,'8. Ceramic'!E37,IF(D5='Basic Bullets'!E9,'9. Ship Building'!E37,IF(D5='Basic Bullets'!E10,'10. Ship Breaking'!E37,IF(D5='Basic Bullets'!E11,'11. Jute Mills'!E37,IF(D5='Basic Bullets'!E12,'12. Steel Engineering '!E37,IF(D5='Basic Bullets'!E13,'13.Power and gas'!E37,IF(D5='Basic Bullets'!E14,'14. Industry_Others'!E37,IF(D5='Basic Bullets'!E15,'B. Trade and commerce'!E37,IF(D5='Basic Bullets'!E16,'C. Agro'!E37,IF(D5='Basic Bullets'!E17,'1. Service_Housing&Cnst'!E37,IF(D5='Basic Bullets'!E18,'2. Service_Telecom'!E37,IF(D5='Basic Bullets'!E19,'3. Servic_Hospitals&Clinics'!E37,IF(D5='Basic Bullets'!E20,'3. Service_ Others '!E37,0)))))))))))))))))))) -> 5 | F21: 7 | G21: =E21/F21 -> 0.71428571 | H21: =IF(G21>=80%,"Excellent",IF(G21>=70%,"Good",IF(G21>=60%,"Marginal",IF(G21<60%,"Unacceptable",0)))) -> Good
B22: B.2 | C22: ='9. Inputs-Analysis'!C10 -> 2. Cash Ratio (Cash) | D22: =IF(D5='Basic Bullets'!E1,'1. RMG'!D45,IF(D5='Basic Bullets'!E2,'2. Textile '!D45,IF(D5='Basic Bullets'!E3,'3. Food and Allied'!D45,IF(D5='Basic Bullets'!E4,'4. Pharmaceutical'!D45,IF(D5='Basic Bullets'!E5,'5. Chemical'!D45,IF(D5='Basic Bullets'!E6,'6. Fertilizer'!D45,IF(D5='Basic Bullets'!E7,'7.Cement'!D45,IF(D5='Basic Bullets'!E8,'8. Ceramic'!D45,IF(D5='Basic Bullets'!E9,'9. Ship Building'!D45,IF(D5='Basic Bullets'!E10,'10. Ship Breaking'!D45,IF(D5='Basic Bullets'!E11,'11. Jute Mills'!D45,IF(D5='Basic Bullets'!E12,'12. Steel Engineering '!D45,IF(D5='Basic Bullets'!E13,'13.Power and gas'!D45,IF(D5='Basic Bullets'!E14,'14. Industry_Others'!D45,IF(D5='Basic Bullets'!E15,'B. Trade and commerce'!D45,IF(D5='Basic Bullets'!E16,'C. Agro'!D45,IF(D5='Basic Bullets'!E17,'1. Service_Housing&Cnst'!D45,IF(D5='Basic Bullets'!E18,'2. Service_Telecom'!D45,IF(D5='Basic Bullets'!E19,'3. Servic_Hospitals&Clinics'!D45,IF(D5='Basic Bullets'!E20,'3. Service_ Others '!D45,0)))))))))))))))))))) -> 0.0061472341 | E22: =IF(D5='Basic Bullets'!E1,'1. RMG'!E45,IF(D5='Basic Bullets'!E2,'2. Textile '!E45,IF(D5='Basic Bullets'!E3,'3. Food and Allied'!E45,IF(D5='Basic Bullets'!E4,'4. Pharmaceutical'!E45,IF(D5='Basic Bullets'!E5,'5. Chemical'!E45,IF(D5='Basic Bullets'!E6,'6. Fertilizer'!E45,IF(D5='Basic Bullets'!E7,'7.Cement'!E45,IF(D5='Basic Bullets'!E8,'8. Ceramic'!E45,IF(D5='Basic Bullets'!E9,'9. Ship Building'!E45,IF(D5='Basic Bullets'!E10,'10. Ship Breaking'!E45,IF(D5='Basic Bullets'!E11,'11. Jute Mills'!E45,IF(D5='Basic Bullets'!E12,'12. Steel Engineering '!E45,IF(D5='Basic Bullets'!E13,'13.Power and gas'!E45,IF(D5='Basic Bullets'!E14,'14. Industry_Others'!E45,IF(D5='Basic Bullets'!E15,'B. Trade and commerce'!E45,IF(D5='Basic Bullets'!E16,'C. Agro'!E45,IF(D5='Basic Bullets'!E17,'1. Service_Housing&Cnst'!E45,IF(D5='Basic Bullets'!E18,'2. Service_Telecom'!E45,IF(D5='Basic Bullets'!E19,'3. Servic_Hospitals&Clinics'!E45,IF(D5='Basic Bullets'!E20,'3. Service_ Others '!E45,0)))))))))))))))))))) -> 0 | F22: 3 | G22: =E22/F22 -> 0 | H22: =IF(G22>=80%,"Excellent",IF(G22>=70%,"Good",IF(G22>=60%,"Marginal",IF(G22<60%,"Unacceptable",0)))) -> Unacceptable
B23: C | C23: Profitability | E23: =SUM(E24:E26) -> 5 | F23: =SUM(F24:F26) -> 10 | G23: =E23/F23 -> 0.5 | H23: =IF(G23>=80%,"Excellent",IF(G23>=70%,"Good",IF(G23>=60%,"Marginal",IF(G23<60%,"Unacceptable",0)))) -> Unacceptable
B24: C.1 | C24: ='9. Inputs-Analysis'!C15 -> 1. Net Profit Margin (NPM) | D24: =IF(D5='Basic Bullets'!E1,'1. RMG'!D53,IF(D5='Basic Bullets'!E2,'2. Textile '!D53,IF(D5='Basic Bullets'!E3,'3. Food and Allied'!D53,IF(D5='Basic Bullets'!E4,'4. Pharmaceutical'!D53,IF(D5='Basic Bullets'!E5,'5. Chemical'!D53,IF(D5='Basic Bullets'!E6,'6. Fertilizer'!D53,IF(D5='Basic Bullets'!E7,'7.Cement'!D53,IF(D5='Basic Bullets'!E8,'8. Ceramic'!D53,IF(D5='Basic Bullets'!E9,'9. Ship Building'!D53,IF(D5='Basic Bullets'!E10,'10. Ship Breaking'!D53,IF(D5='Basic Bullets'!E11,'11. Jute Mills'!D53,IF(D5='Basic Bullets'!E12,'12. Steel Engineering '!D53,IF(D5='Basic Bullets'!E13,'13.Power and gas'!D53,IF(D5='Basic Bullets'!E14,'14. Industry_Others'!D53,IF(D5='Basic Bullets'!E15,'B. Trade and commerce'!D53,IF(D5='Basic Bullets'!E16,'C. Agro'!D53,IF(D5='Basic Bullets'!E17,'1. Service_Housing&Cnst'!D53,IF(D5='Basic Bullets'!E18,'2. Service_Telecom'!D53,IF(D5='Basic Bullets'!E19,'3. Servic_Hospitals&Clinics'!D53,IF(D5='Basic Bullets'!E20,'3. Service_ Others '!D53,0)))))))))))))))))))) -> 0.054896988 | E24: =IF(D5='Basic Bullets'!E1,'1. RMG'!E53,IF(D5='Basic Bullets'!E2,'2. Textile '!E53,IF(D5='Basic Bullets'!E3,'3. Food and Allied'!E53,IF(D5='Basic Bullets'!E4,'4. Pharmaceutical'!E53,IF(D5='Basic Bullets'!E5,'5. Chemical'!E53,IF(D5='Basic Bullets'!E6,'6. Fertilizer'!E53,IF(D5='Basic Bullets'!E7,'7.Cement'!E53,IF(D5='Basic Bullets'!E8,'8. Ceramic'!E53,IF(D5='Basic Bullets'!E9,'9. Ship Building'!E53,IF(D5='Basic Bullets'!E10,'10. Ship Breaking'!E53,IF(D5='Basic Bullets'!E11,'11. Jute Mills'!E53,IF(D5='Basic Bullets'!E12,'12. Steel Engineering '!E53,IF(D5='Basic Bullets'!E13,'13.Power and gas'!E53,IF(D5='Basic Bullets'!E14,'14. Industry_Others'!E53,IF(D5='Basic Bullets'!E15,'B. Trade and commerce'!E53,IF(D5='Basic Bullets'!E16,'C. Agro'!E53,IF(D5='Basic Bullets'!E17,'1. Service_Housing&Cnst'!E53,IF(D5='Basic Bullets'!E18,'2. Service_Telecom'!E53,IF(D5='Basic Bullets'!E19,'3. Servic_Hospitals&Clinics'!E53,IF(D5='Basic Bullets'!E20,'3. Service_ Others '!E53,0)))))))))))))))))))) -> 3 | F24: 5 | G24: =E24/F24 -> 0.6 | H24: =IF(G24>=80%,"Excellent",IF(G24>=70%,"Good",IF(G24>=60%,"Marginal",IF(G24<60%,"Unacceptable",0)))) -> Marginal
B25: C.2 | C25: ='9. Inputs-Analysis'!C18 -> 2. Return on Assets (ROA) | D25: =IF(D5='Basic Bullets'!E1,'1. RMG'!D62,IF(D5='Basic Bullets'!E2,'2. Textile '!D62,IF(D5='Basic Bullets'!E3,'3. Food and Allied'!D62,IF(D5='Basic Bullets'!E4,'4. Pharmaceutical'!D62,IF(D5='Basic Bullets'!E5,'5. Chemical'!D62,IF(D5='Basic Bullets'!E6,'6. Fertilizer'!D62,IF(D5='Basic Bullets'!E7,'7.Cement'!D62,IF(D5='Basic Bullets'!E8,'8. Ceramic'!D62,IF(D5='Basic Bullets'!E9,'9. Ship Building'!D62,IF(D5='Basic Bullets'!E10,'10. Ship Breaking'!D62,IF(D5='Basic Bullets'!E11,'11. Jute Mills'!D62,IF(D5='Basic Bullets'!E12,'12. Steel Engineering '!D62,IF(D5='Basic Bullets'!E13,'13.Power and gas'!D62,IF(D5='Basic Bullets'!E14,'14. Industry_Others'!D62,IF(D5='Basic Bullets'!E15,'B. Trade and commerce'!D62,IF(D5='Basic Bullets'!E16,'C. Agro'!D62,IF(D5='Basic Bullets'!E17,'1. Service_Housing&Cnst'!D62,IF(D5='Basic Bullets'!E18,'2. Service_Telecom'!D62,IF(D5='Basic Bullets'!E19,'3. Servic_Hospitals&Clinics'!D62,IF(D5='Basic Bullets'!E20,'3. Service_ Others '!D62,0)))))))))))))))))))) -> 0.019426111 | E25: =IF(D5='Basic Bullets'!E1,'1. RMG'!E62,IF(D5='Basic Bullets'!E2,'2. Textile '!E62,IF(D5='Basic Bullets'!E3,'3. Food and Allied'!E62,IF(D5='Basic Bullets'!E4,'4. Pharmaceutical'!E62,IF(D5='Basic Bullets'!E5,'5. Chemical'!E62,IF(D5='Basic Bullets'!E6,'6. Fertilizer'!E62,IF(D5='Basic Bullets'!E7,'7.Cement'!E62,IF(D5='Basic Bullets'!E8,'8. Ceramic'!E62,IF(D5='Basic Bullets'!E9,'9. Ship Building'!E62,IF(D5='Basic Bullets'!E10,'10. Ship Breaking'!E62,IF(D5='Basic Bullets'!E11,'11. Jute Mills'!E62,IF(D5='Basic Bullets'!E12,'12. Steel Engineering '!E62,IF(D5='Basic Bullets'!E13,'13.Power and gas'!E62,IF(D5='Basic Bullets'!E14,'14. Industry_Others'!E62,IF(D5='Basic Bullets'!E15,'B. Trade and commerce'!E62,IF(D5='Basic Bullets'!E16,'C. Agro'!E62,IF(D5='Basic Bullets'!E17,'1. Service_Housing&Cnst'!E62,IF(D5='Basic Bullets'!E18,'2. Service_Telecom'!E62,IF(D5='Basic Bullets'!E19,'3. Servic_Hospitals&Clinics'!E62,IF(D5='Basic Bullets'!E20,'3. Service_ Others '!E62,0)))))))))))))))))))) -> 1 | F25: 3 | G25: =E25/F25 -> 0.33333333 | H25: =IF(G25>=80%,"Excellent",IF(G25>=70%,"Good",IF(G25>=60%,"Marginal",IF(G25<60%,"Unacceptable",0)))) -> Unacceptable
B26: C.3 | C26: ='9. Inputs-Analysis'!C21 -> 3. Operating Profit to Operating Assets (OPOA) | D26: =IF(D5='Basic Bullets'!E1,'1. RMG'!D69,IF(D5='Basic Bullets'!E2,'2. Textile '!D69,IF(D5='Basic Bullets'!E3,'3. Food and Allied'!D69,IF(D5='Basic Bullets'!E4,'4. Pharmaceutical'!D69,IF(D5='Basic Bullets'!E5,'5. Chemical'!D69,IF(D5='Basic Bullets'!E6,'6. Fertilizer'!D69,IF(D5='Basic Bullets'!E7,'7.Cement'!D69,IF(D5='Basic Bullets'!E8,'8. Ceramic'!D69,IF(D5='Basic Bullets'!E9,'9. Ship Building'!D69,IF(D5='Basic Bullets'!E10,'10. Ship Breaking'!D69,IF(D5='Basic Bullets'!E11,'11. Jute Mills'!D69,IF(D5='Basic Bullets'!E12,'12. Steel Engineering '!D69,IF(D5='Basic Bullets'!E13,'13.Power and gas'!D69,IF(D5='Basic Bullets'!E14,'14. Industry_Others'!D69,IF(D5='Basic Bullets'!E15,'B. Trade and commerce'!D69,IF(D5='Basic Bullets'!E16,'C. Agro'!D69,IF(D5='Basic Bullets'!E17,'1. Service_Housing&Cnst'!D69,IF(D5='Basic Bullets'!E18,'2. Service_Telecom'!D69,IF(D5='Basic Bullets'!E19,'3. Servic_Hospitals&Clinics'!D69,IF(D5='Basic Bullets'!E20,'3. Service_ Others '!D69,0)))))))))))))))))))) -> 0.04652054 | E26: =IF(D5='Basic Bullets'!E1,'1. RMG'!E69,IF(D5='Basic Bullets'!E2,'2. Textile '!E69,IF(D5='Basic Bullets'!E3,'3. Food and Allied'!E69,IF(D5='Basic Bullets'!E4,'4. Pharmaceutical'!E69,IF(D5='Basic Bullets'!E5,'5. Chemical'!E69,IF(D5='Basic Bullets'!E6,'6. Fertilizer'!E69,IF(D5='Basic Bullets'!E7,'7.Cement'!E69,IF(D5='Basic Bullets'!E8,'8. Ceramic'!E69,IF(D5='Basic Bullets'!E9,'9. Ship Building'!E69,IF(D5='Basic Bullets'!E10,'10. Ship Breaking'!E69,IF(D5='Basic Bullets'!E11,'11. Jute Mills'!E69,IF(D5='Basic Bullets'!E12,'12. Steel Engineering '!E69,IF(D5='Basic Bullets'!E13,'13.Power and gas'!E69,IF(D5='Basic Bullets'!E14,'14. Industry_Others'!E69,IF(D5='Basic Bullets'!E15,'B. Trade and commerce'!E69,IF(D5='Basic Bullets'!E16,'C. Agro'!E69,IF(D5='Basic Bullets'!E17,'1. Service_Housing&Cnst'!E69,IF(D5='Basic Bullets'!E18,'2. Service_Telecom'!E69,IF(D5='Basic Bullets'!E19,'3. Servic_Hospitals&Clinics'!E69,IF(D5='Basic Bullets'!E20,'3. Service_ Others '!E69,0)))))))))))))))))))) -> 1 | F26: 2 | G26: =E26/F26 -> 0.5 | H26: =IF(G26>=80%,"Excellent",IF(G26>=70%,"Good",IF(G26>=60%,"Marginal",IF(G26<60%,"Unacceptable",0)))) -> Unacceptable
B27: D | C27: Coverage | E27: =SUM(E28:E31) -> 6 | F27: =SUM(F28:F31) -> 15 | G27: =E27/F27 -> 0.4 | H27: =IF(G27>=80%,"Excellent",IF(G27>=70%,"Good",IF(G27>=60%,"Marginal",IF(G27<60%,"Unacceptable",0)))) -> Unacceptable
B28: D.1 | C28: ='9. Inputs-Analysis'!C24 -> 1. Interest Coverage (IC) | D28: =IF(D5='Basic Bullets'!E1,'1. RMG'!D76,IF(D5='Basic Bullets'!E2,'2. Textile '!D76,IF(D5='Basic Bullets'!E3,'3. Food and Allied'!D76,IF(D5='Basic Bullets'!E4,'4. Pharmaceutical'!D76,IF(D5='Basic Bullets'!E5,'5. Chemical'!D76,IF(D5='Basic Bullets'!E6,'6. Fertilizer'!D76,IF(D5='Basic Bullets'!E7,'7.Cement'!D76,IF(D5='Basic Bullets'!E8,'8. Ceramic'!D76,IF(D5='Basic Bullets'!E9,'9. Ship Building'!D76,IF(D5='Basic Bullets'!E10,'10. Ship Breaking'!D76,IF(D5='Basic Bullets'!E11,'11. Jute Mills'!D76,IF(D5='Basic Bullets'!E12,'12. Steel Engineering '!D76,IF(D5='Basic Bullets'!E13,'13.Power and gas'!D76,IF(D5='Basic Bullets'!E14,'14. Industry_Others'!D76,IF(D5='Basic Bullets'!E15,'B. Trade and commerce'!D76,IF(D5='Basic Bullets'!E16,'C. Agro'!D76,IF(D5='Basic Bullets'!E17,'1. Service_Housing&Cnst'!D76,IF(D5='Basic Bullets'!E18,'2. Service_Telecom'!D76,IF(D5='Basic Bullets'!E19,'3. Servic_Hospitals&Clinics'!D76,IF(D5='Basic Bullets'!E20,'3. Service_ Others '!D76,0)))))))))))))))))))) -> 2.1640484 | E28: =IF(D5='Basic Bullets'!E1,'1. RMG'!E76,IF(D5='Basic Bullets'!E2,'2. Textile '!E76,IF(D5='Basic Bullets'!E3,'3. Food and Allied'!E76,IF(D5='Basic Bullets'!E4,'4. Pharmaceutical'!E76,IF(D5='Basic Bullets'!E5,'5. Chemical'!E76,IF(D5='Basic Bullets'!E6,'6. Fertilizer'!E76,IF(D5='Basic Bullets'!E7,'7.Cement'!E76,IF(D5='Basic Bullets'!E8,'8. Ceramic'!E76,IF(D5='Basic Bullets'!E9,'9. Ship Building'!E76,IF(D5='Basic Bullets'!E10,'10. Ship Breaking'!E76,IF(D5='Basic Bullets'!E11,'11. Jute Mills'!E76,IF(D5='Basic Bullets'!E12,'12. Steel Engineering '!E76,IF(D5='Basic Bullets'!E13,'13.Power and gas'!E76,IF(D5='Basic Bullets'!E14,'14. Industry_Others'!E76,IF(D5='Basic Bullets'!E15,'B. Trade and commerce'!E76,IF(D5='Basic Bullets'!E16,'C. Agro'!E76,IF(D5='Basic Bullets'!E17,'1. Service_Housing&Cnst'!E76,IF(D5='Basic Bullets'!E18,'2. Service_Telecom'!E76,IF(D5='Basic Bullets'!E19,'3. Servic_Hospitals&Clinics'!E76,IF(D5='Basic Bullets'!E20,'3. Service_ Others '!E76,0)))))))))))))))))))) -> 1 | F28: 3 | G28: =E28/F28 -> 0.33333333 | H28: =IF(G28>=80%,"Excellent",IF(G28>=70%,"Good",IF(G28>=60%,"Marginal",IF(G28<60%,"Unacceptable",0)))) -> Unacceptable
B29: D.2 | C29: ='9. Inputs-Analysis'!C27 -> 2. Debt Service Coverage Ratio (DSCR) | D29: =IF(D5='Basic Bullets'!E1,'1. RMG'!D83,IF(D5='Basic Bullets'!E2,'2. Textile '!D83,IF(D5='Basic Bullets'!E3,'3. Food and Allied'!D83,IF(D5='Basic Bullets'!E4,'4. Pharmaceutical'!D83,IF(D5='Basic Bullets'!E5,'5. Chemical'!D83,IF(D5='Basic Bullets'!E6,'6. Fertilizer'!D83,IF(D5='Basic Bullets'!E7,'7.Cement'!D83,IF(D5='Basic Bullets'!E8,'8. Ceramic'!D83,IF(D5='Basic Bullets'!E9,'9. Ship Building'!D83,IF(D5='Basic Bullets'!E10,'10. Ship Breaking'!D83,IF(D5='Basic Bullets'!E11,'11. Jute Mills'!D83,IF(D5='Basic Bullets'!E12,'12. Steel Engineering '!D83,IF(D5='Basic Bullets'!E13,'13.Power and gas'!D83,IF(D5='Basic Bullets'!E14,'14. Industry_Others'!D83,IF(D5='Basic Bullets'!E15,'B. Trade and commerce'!D83,IF(D5='Basic Bullets'!E16,'C. Agro'!D83,IF(D5='Basic Bullets'!E17,'1. Service_Housing&Cnst'!D83,IF(D5='Basic Bullets'!E18,'2. Service_Telecom'!D83,IF(D5='Basic Bullets'!E19,'3. Servic_Hospitals&Clinics'!D83,IF(D5='Basic Bullets'!E20,'3. Service_ Others '!D83,0)))))))))))))))))))) -> 1.4160266 | E29: =IF(D5='Basic Bullets'!E1,'1. RMG'!E83,IF(D5='Basic Bullets'!E2,'2. Textile '!E83,IF(D5='Basic Bullets'!E3,'3. Food and Allied'!E83,IF(D5='Basic Bullets'!E4,'4. Pharmaceutical'!E83,IF(D5='Basic Bullets'!E5,'5. Chemical'!E83,IF(D5='Basic Bullets'!E6,'6. Fertilizer'!E83,IF(D5='Basic Bullets'!E7,'7.Cement'!E83,IF(D5='Basic Bullets'!E8,'8. Ceramic'!E83,IF(D5='Basic Bullets'!E9,'9. Ship Building'!E83,IF(D5='Basic Bullets'!E10,'10. Ship Breaking'!E83,IF(D5='Basic Bullets'!E11,'11. Jute Mills'!E83,IF(D5='Basic Bullets'!E12,'12. Steel Engineering '!E83,IF(D5='Basic Bullets'!E13,'13.Power and gas'!E83,IF(D5='Basic Bullets'!E14,'14. Industry_Others'!E83,IF(D5='Basic Bullets'!E15,'B. Trade and commerce'!E83,IF(D5='Basic Bullets'!E16,'C. Agro'!E83,IF(D5='Basic Bullets'!E17,'1. Service_Housing&Cnst'!E83,IF(D5='Basic Bullets'!E18,'2. Service_Telecom'!E83,IF(D5='Basic Bullets'!E19,'3. Servic_Hospitals&Clinics'!E83,IF(D5='Basic Bullets'!E20,'3. Service_ Others '!E83,0)))))))))))))))))))) -> 2 | F29: 5 | G29: =E29/F29 -> 0.4 | H29: =IF(G29>=80%,"Excellent",IF(G29>=70%,"Good",IF(G29>=60%,"Marginal",IF(G29<60%,"Unacceptable",0)))) -> Unacceptable
B30: D.3 | C30: ='9. Inputs-Analysis'!C30 -> 3. Operating Cashflow to Debt Ratio (CDR) | D30: =IF(D5='Basic Bullets'!E1,'1. RMG'!D93,IF(D5='Basic Bullets'!E2,'2. Textile '!D93,IF(D5='Basic Bullets'!E3,'3. Food and Allied'!D93,IF(D5='Basic Bullets'!E4,'4. Pharmaceutical'!D93,IF(D5='Basic Bullets'!E5,'5. Chemical'!D93,IF(D5='Basic Bullets'!E6,'6. Fertilizer'!D93,IF(D5='Basic Bullets'!E7,'7.Cement'!D93,IF(D5='Basic Bullets'!E8,'8. Ceramic'!D93,IF(D5='Basic Bullets'!E9,'9. Ship Building'!D93,IF(D5='Basic Bullets'!E10,'10. Ship Breaking'!D93,IF(D5='Basic Bullets'!E11,'11. Jute Mills'!D93,IF(D5='Basic Bullets'!E12,'12. Steel Engineering '!D93,IF(D5='Basic Bullets'!E13,'13.Power and gas'!D93,IF(D5='Basic Bullets'!E14,'14. Industry_Others'!D93,IF(D5='Basic Bullets'!E15,'B. Trade and commerce'!D93,IF(D5='Basic Bullets'!E16,'C. Agro'!D93,IF(D5='Basic Bullets'!E17,'1. Service_Housing&Cnst'!D93,IF(D5='Basic Bullets'!E18,'2. Service_Telecom'!D93,IF(D5='Basic Bullets'!E19,'3. Servic_Hospitals&Clinics'!D93,IF(D5='Basic Bullets'!E20,'3. Service_ Others '!D93,0)))))))))))))))))))) -> 0.033545581 | E30: =IF(D5='Basic Bullets'!E1,'1. RMG'!E93,IF(D5='Basic Bullets'!E2,'2. Textile '!E93,IF(D5='Basic Bullets'!E3,'3. Food and Allied'!E93,IF(D5='Basic Bullets'!E4,'4. Pharmaceutical'!E93,IF(D5='Basic Bullets'!E5,'5. Chemical'!E93,IF(D5='Basic Bullets'!E6,'6. Fertilizer'!E93,IF(D5='Basic Bullets'!E7,'7.Cement'!E93,IF(D5='Basic Bullets'!E8,'8. Ceramic'!E93,IF(D5='Basic Bullets'!E9,'9. Ship Building'!E93,IF(D5='Basic Bullets'!E10,'10. Ship Breaking'!E93,IF(D5='Basic Bullets'!E11,'11. Jute Mills'!E93,IF(D5='Basic Bullets'!E12,'12. Steel Engineering '!E93,IF(D5='Basic Bullets'!E13,'13.Power and gas'!E93,IF(D5='Basic Bullets'!E14,'14. Industry_Others'!E93,IF(D5='Basic Bullets'!E15,'B. Trade and commerce'!E93,IF(D5='Basic Bullets'!E16,'C. Agro'!E93,IF(D5='Basic Bullets'!E17,'1. Service_Housing&Cnst'!E93,IF(D5='Basic Bullets'!E18,'2. Service_Telecom'!E93,IF(D5='Basic Bullets'!E19,'3. Servic_Hospitals&Clinics'!E93,IF(D5='Basic Bullets'!E20,'3. Service_ Others '!E93,0)))))))))))))))))))) -> 1 | F30: 4 | G30: =E30/F30 -> 0.25 | H30: =IF(G30>=80%,"Excellent",IF(G30>=70%,"Good",IF(G30>=60%,"Marginal",IF(G30<60%,"Unacceptable",0)))) -> Unacceptable
B31: D.4 | C31: ='9. Inputs-Analysis'!C33 -> 4. Cashflow Coverage Ratio (CCR) | D31: =IF(D5='Basic Bullets'!E1,'1. RMG'!D100,IF(D5='Basic Bullets'!E2,'2. Textile '!D100,IF(D5='Basic Bullets'!E3,'3. Food and Allied'!D100,IF(D5='Basic Bullets'!E4,'4. Pharmaceutical'!D100,IF(D5='Basic Bullets'!E5,'5. Chemical'!D100,IF(D5='Basic Bullets'!E6,'6. Fertilizer'!D100,IF(D5='Basic Bullets'!E7,'7.Cement'!D100,IF(D5='Basic Bullets'!E8,'8. Ceramic'!D100,IF(D5='Basic Bullets'!E9,'9. Ship Building'!D100,IF(D5='Basic Bullets'!E10,'10. Ship Breaking'!D100,IF(D5='Basic Bullets'!E11,'11. Jute Mills'!D100,IF(D5='Basic Bullets'!E12,'12. Steel Engineering '!D100,IF(D5='Basic Bullets'!E13,'13.Power and gas'!D100,IF(D5='Basic Bullets'!E14,'14. Industry_Others'!D100,IF(D5='Basic Bullets'!E15,'B. Trade and commerce'!D100,IF(D5='Basic Bullets'!E16,'C. Agro'!D100,IF(D5='Basic Bullets'!E17,'1. Service_Housing&Cnst'!D100,IF(D5='Basic Bullets'!E18,'2. Service_Telecom'!D100,IF(D5='Basic Bullets'!E19,'3. Servic_Hospitals&Clinics'!D100,IF(D5='Basic Bullets'!E20,'3. Service_ Others '!D100,0)))))))))))))))))))) -> 0.76522361 | E31: =IF(D5='Basic Bullets'!E1,'1. RMG'!E100,IF(D5='Basic Bullets'!E2,'2. Textile '!E100,IF(D5='Basic Bullets'!E3,'3. Food and Allied'!E100,IF(D5='Basic Bullets'!E4,'4. Pharmaceutical'!E100,IF(D5='Basic Bullets'!E5,'5. Chemical'!E100,IF(D5='Basic Bullets'!E6,'6. Fertilizer'!E100,IF(D5='Basic Bullets'!E7,'7.Cement'!E100,IF(D5='Basic Bullets'!E8,'8. Ceramic'!E100,IF(D5='Basic Bullets'!E9,'9. Ship Building'!E100,IF(D5='Basic Bullets'!E10,'10. Ship Breaking'!E100,IF(D5='Basic Bullets'!E11,'11. Jute Mills'!E100,IF(D5='Basic Bullets'!E12,'12. Steel Engineering '!E100,IF(D5='Basic Bullets'!E13,'13.Power and gas'!E100,IF(D5='Basic Bullets'!E14,'14. Industry_Others'!E100,IF(D5='Basic Bullets'!E15,'B. Trade and commerce'!E100,IF(D5='Basic Bullets'!E16,'C. Agro'!E100,IF(D5='Basic Bullets'!E17,'1. Service_Housing&Cnst'!E100,IF(D5='Basic Bullets'!E18,'2. Service_Telecom'!E100,IF(D5='Basic Bullets'!E19,'3. Servic_Hospitals&Clinics'!E100,IF(D5='Basic Bullets'!E20,'3. Service_ Others '!E100,0)))))))))))))))))))) -> 2 | F31: 3 | G31: =E31/F31 -> 0.66666667 | H31: =IF(G31>=80%,"Excellent",IF(G31>=70%,"Good",IF(G31>=60%,"Marginal",IF(G31<60%,"Unacceptable",0)))) -> Marginal
B32: E | C32: Operational Efficiency | E32: =SUM(E33:E35) -> 3 | F32: =SUM(F33:F35) -> 10 | G32: =E32/F32 -> 0.3 | H32: =IF(G32>=80%,"Excellent",IF(G32>=70%,"Good",IF(G32>=60%,"Marginal",IF(G32<60%,"Unacceptable",0)))) -> Unacceptable
B33: E.1 | C33: ='9. Inputs-Analysis'!C36 -> 1. Stock Turnover Days (STD) | D33: =IF(D5='Basic Bullets'!E1,'1. RMG'!D107,IF(D5='Basic Bullets'!E2,'2. Textile '!D107,IF(D5='Basic Bullets'!E3,'3. Food and Allied'!D107,IF(D5='Basic Bullets'!E4,'4. Pharmaceutical'!D107,IF(D5='Basic Bullets'!E5,'5. Chemical'!D107,IF(D5='Basic Bullets'!E6,'6. Fertilizer'!D107,IF(D5='Basic Bullets'!E7,'7.Cement'!D107,IF(D5='Basic Bullets'!E8,'8. Ceramic'!D107,IF(D5='Basic Bullets'!E9,'9. Ship Building'!D107,IF(D5='Basic Bullets'!E10,'10. Ship Breaking'!D107,IF(D5='Basic Bullets'!E11,'11. Jute Mills'!D107,IF(D5='Basic Bullets'!E12,'12. Steel Engineering '!D107,IF(D5='Basic Bullets'!E13,'13.Power and gas'!D107,IF(D5='Basic Bullets'!E14,'14. Industry_Others'!D107,IF(D5='Basic Bullets'!E15,'B. Trade and commerce'!D107,IF(D5='Basic Bullets'!E16,'C. Agro'!D107,IF(D5='Basic Bullets'!E17,'1. Service_Housing&Cnst'!D107,IF(D5='Basic Bullets'!E18,'2. Service_Telecom'!D107,IF(D5='Basic Bullets'!E19,'3. Servic_Hospitals&Clinics'!D107,IF(D5='Basic Bullets'!E20,'3. Service_ Others '!D107,0)))))))))))))))))))) -> 823.7278 | E33: =IF(D5='Basic Bullets'!E1,'1. RMG'!E107,IF(D5='Basic Bullets'!E2,'2. Textile '!E107,IF(D5='Basic Bullets'!E3,'3. Food and Allied'!E107,IF(D5='Basic Bullets'!E4,'4. Pharmaceutical'!E107,IF(D5='Basic Bullets'!E5,'5. Chemical'!E107,IF(D5='Basic Bullets'!E6,'6. Fertilizer'!E107,IF(D5='Basic Bullets'!E7,'7.Cement'!E107,IF(D5='Basic Bullets'!E8,'8. Ceramic'!E107,IF(D5='Basic Bullets'!E9,'9. Ship Building'!E107,IF(D5='Basic Bullets'!E10,'10. Ship Breaking'!E107,IF(D5='Basic Bullets'!E11,'11. Jute Mills'!E107,IF(D5='Basic Bullets'!E12,'12. Steel Engineering '!E107,IF(D5='Basic Bullets'!E13,'13.Power and gas'!E107,IF(D5='Basic Bullets'!E14,'14. Industry_Others'!E107,IF(D5='Basic Bullets'!E15,'B. Trade and commerce'!E107,IF(D5='Basic Bullets'!E16,'C. Agro'!E107,IF(D5='Basic Bullets'!E17,'1. Service_Housing&Cnst'!E107,IF(D5='Basic Bullets'!E18,'2. Service_Telecom'!E107,IF(D5='Basic Bullets'!E19,'3. Servic_Hospitals&Clinics'!E107,IF(D5='Basic Bullets'!E20,'3. Service_ Others '!E107,0)))))))))))))))))))) -> 0 | F33: =IF(D5='Basic Bullets'!E17,0,IF(D5='Basic Bullets'!E18,0,IF(D5='Basic Bullets'!E19,0,IF(D5='Basic Bullets'!E20,0,4)))) -> 4 | G33: =E33/F33 -> 0 | H33: =IF(G33>=80%,"Excellent",IF(G33>=70%,"Good",IF(G33>=60%,"Marginal",IF(G33<60%,"Unacceptable",0)))) -> Unacceptable
B34: E.2 | C34: ='9. Inputs-Analysis'!C39 -> 2. Trade Debtor Collection Days (TDCD) | D34: =IF(D5='Basic Bullets'!E1,'1. RMG'!D115,IF(D5='Basic Bullets'!E2,'2. Textile '!D115,IF(D5='Basic Bullets'!E3,'3. Food and Allied'!D115,IF(D5='Basic Bullets'!E4,'4. Pharmaceutical'!D115,IF(D5='Basic Bullets'!E5,'5. Chemical'!D115,IF(D5='Basic Bullets'!E6,'6. Fertilizer'!D115,IF(D5='Basic Bullets'!E7,'7.Cement'!D115,IF(D5='Basic Bullets'!E8,'8. Ceramic'!D115,IF(D5='Basic Bullets'!E9,'9. Ship Building'!D115,IF(D5='Basic Bullets'!E10,'10. Ship Breaking'!D115,IF(D5='Basic Bullets'!E11,'11. Jute Mills'!D115,IF(D5='Basic Bullets'!E12,'12. Steel Engineering '!D115,IF(D5='Basic Bullets'!E13,'13.Power and gas'!D115,IF(D5='Basic Bullets'!E14,'14. Industry_Others'!D115,IF(D5='Basic Bullets'!E15,'B. Trade and commerce'!D115,IF(D5='Basic Bullets'!E16,'C. Agro'!D115,IF(D5='Basic Bullets'!E17,'1. Service_Housing&Cnst'!D115,IF(D5='Basic Bullets'!E18,'2. Service_Telecom'!D115,IF(D5='Basic Bullets'!E19,'3. Servic_Hospitals&Clinics'!D115,IF(D5='Basic Bullets'!E20,'3. Service_ Others '!D115,0)))))))))))))))))))) -> 89.219452 | E34: =IF(D5='Basic Bullets'!E1,'1. RMG'!E115,IF(D5='Basic Bullets'!E2,'2. Textile '!E115,IF(D5='Basic Bullets'!E3,'3. Food and Allied'!E115,IF(D5='Basic Bullets'!E4,'4. Pharmaceutical'!E115,IF(D5='Basic Bullets'!E5,'5. Chemical'!E115,IF(D5='Basic Bullets'!E6,'6. Fertilizer'!E115,IF(D5='Basic Bullets'!E7,'7.Cement'!E115,IF(D5='Basic Bullets'!E8,'8. Ceramic'!E115,IF(D5='Basic Bullets'!E9,'9. Ship Building'!E115,IF(D5='Basic Bullets'!E10,'10. Ship Breaking'!E115,IF(D5='Basic Bullets'!E11,'11. Jute Mills'!E115,IF(D5='Basic Bullets'!E12,'12. Steel Engineering '!E115,IF(D5='Basic Bullets'!E13,'13.Power and gas'!E115,IF(D5='Basic Bullets'!E14,'14. Industry_Others'!E115,IF(D5='Basic Bullets'!E15,'B. Trade and commerce'!E115,IF(D5='Basic Bullets'!E16,'C. Agro'!E115,IF(D5='Basic Bullets'!E17,'1. Service_Housing&Cnst'!E115,IF(D5='Basic Bullets'!E18,'2. Service_Telecom'!E115,IF(D5='Basic Bullets'!E19,'3. Servic_Hospitals&Clinics'!E115,IF(D5='Basic Bullets'!E20,'3. Service_ Others '!E115,0)))))))))))))))))))) -> 2 | F34: =IF(D5='Basic Bullets'!E17,5,IF(D5='Basic Bullets'!E18,5,IF(D5='Basic Bullets'!E19,5,IF(D5='Basic Bullets'!E20,5,3)))) -> 3 | G34: =E34/F34 -> 0.66666667 | H34: =IF(G34>=80%,"Excellent",IF(G34>=70%,"Good",IF(G34>=60%,"Marginal",IF(G34<60%,"Unacceptable",0)))) -> Marginal
B35: E.3 | C35: ='9. Inputs-Analysis'!C42 -> 3. Asset Turnover (AT) | D35: =IF(D5='Basic Bullets'!E1,'1. RMG'!D122,IF(D5='Basic Bullets'!E2,'2. Textile '!D122,IF(D5='Basic Bullets'!E3,'3. Food and Allied'!D122,IF(D5='Basic Bullets'!E4,'4. Pharmaceutical'!D122,IF(D5='Basic Bullets'!E5,'5. Chemical'!D122,IF(D5='Basic Bullets'!E6,'6. Fertilizer'!D122,IF(D5='Basic Bullets'!E7,'7.Cement'!D122,IF(D5='Basic Bullets'!E8,'8. Ceramic'!D122,IF(D5='Basic Bullets'!E9,'9. Ship Building'!D122,IF(D5='Basic Bullets'!E10,'10. Ship Breaking'!D122,IF(D5='Basic Bullets'!E11,'11. Jute Mills'!D122,IF(D5='Basic Bullets'!E12,'12. Steel Engineering '!D122,IF(D5='Basic Bullets'!E13,'13.Power and gas'!D122,IF(D5='Basic Bullets'!E14,'14. Industry_Others'!D122,IF(D5='Basic Bullets'!E15,'B. Trade and commerce'!D122,IF(D5='Basic Bullets'!E16,'C. Agro'!D122,IF(D5='Basic Bullets'!E17,'1. Service_Housing&Cnst'!D122,IF(D5='Basic Bullets'!E18,'2. Service_Telecom'!D122,IF(D5='Basic Bullets'!E19,'3. Servic_Hospitals&Clinics'!D122,IF(D5='Basic Bullets'!E20,'3. Service_ Others '!D122,0)))))))))))))))))))) -> 0.35386479 | E35: =IF(D5='Basic Bullets'!E1,'1. RMG'!E122,IF(D5='Basic Bullets'!E2,'2. Textile '!E122,IF(D5='Basic Bullets'!E3,'3. Food and Allied'!E122,IF(D5='Basic Bullets'!E4,'4. Pharmaceutical'!E122,IF(D5='Basic Bullets'!E5,'5. Chemical'!E122,IF(D5='Basic Bullets'!E6,'6. Fertilizer'!E122,IF(D5='Basic Bullets'!E7,'7.Cement'!E122,IF(D5='Basic Bullets'!E8,'8. Ceramic'!E122,IF(D5='Basic Bullets'!E9,'9. Ship Building'!E122,IF(D5='Basic Bullets'!E10,'10. Ship Breaking'!E122,IF(D5='Basic Bullets'!E11,'11. Jute Mills'!E122,IF(D5='Basic Bullets'!E12,'12. Steel Engineering '!E122,IF(D5='Basic Bullets'!E13,'13.Power and gas'!E122,IF(D5='Basic Bullets'!E14,'14. Industry_Others'!E122,IF(D5='Basic Bullets'!E15,'B. Trade and commerce'!E122,IF(D5='Basic Bullets'!E16,'C. Agro'!E122,IF(D5='Basic Bullets'!E17,'1. Service_Housing&Cnst'!E122,IF(D5='Basic Bullets'!E18,'2. Service_Telecom'!E122,IF(D5='Basic Bullets'!E19,'3. Servic_Hospitals&Clinics'!E122,IF(D5='Basic Bullets'!E20,'3. Service_ Others '!E122,0)))))))))))))))))))) -> 1 | F35: =IF(D5='Basic Bullets'!E17,5,IF(D5='Basic Bullets'!E18,5,IF(D5='Basic Bullets'!E19,5,IF(D5='Basic Bullets'!E20,5,3)))) -> 3 | G35: =E35/F35 -> 0.33333333 | H35: =IF(G35>=80%,"Excellent",IF(G35>=70%,"Good",IF(G35>=60%,"Marginal",IF(G35<60%,"Unacceptable",0)))) -> Unacceptable
B36: F | C36: Earning Quality | E36: =E37+E38 -> 2 | F36: =F37+F38 -> 5 | G36: =E36/F36 -> 0.4 | H36: =IF(G36>=80%,"Excellent",IF(G36>=70%,"Good",IF(G36>=60%,"Marginal",IF(G36<60%,"Unacceptable",0)))) -> Unacceptable
B37: F.1 | C37: ='9. Inputs-Analysis'!C45 -> 1. Operating Cash Flow to Sales (CFS) | D37: =IF(D5='Basic Bullets'!E1,'1. RMG'!D130,IF(D5='Basic Bullets'!E2,'2. Textile '!D130,IF(D5='Basic Bullets'!E3,'3. Food and Allied'!D130,IF(D5='Basic Bullets'!E4,'4. Pharmaceutical'!D130,IF(D5='Basic Bullets'!E5,'5. Chemical'!D130,IF(D5='Basic Bullets'!E6,'6. Fertilizer'!D130,IF(D5='Basic Bullets'!E7,'7.Cement'!D130,IF(D5='Basic Bullets'!E8,'8. Ceramic'!D130,IF(D5='Basic Bullets'!E9,'9. Ship Building'!D130,IF(D5='Basic Bullets'!E10,'10. Ship Breaking'!D130,IF(D5='Basic Bullets'!E11,'11. Jute Mills'!D130,IF(D5='Basic Bullets'!E12,'12. Steel Engineering '!D130,IF(D5='Basic Bullets'!E13,'13.Power and gas'!D130,IF(D5='Basic Bullets'!E14,'14. Industry_Others'!D130,IF(D5='Basic Bullets'!E15,'B. Trade and commerce'!D130,IF(D5='Basic Bullets'!E16,'C. Agro'!D130,IF(D5='Basic Bullets'!E17,'1. Service_Housing&Cnst'!D130,IF(D5='Basic Bullets'!E18,'2. Service_Telecom'!D130,IF(D5='Basic Bullets'!E19,'3. Servic_Hospitals&Clinics'!D130,IF(D5='Basic Bullets'!E20,'3. Service_ Others '!D130,0)))))))))))))))))))) -> 0.074443631 | E37: =IF(D5='Basic Bullets'!E1,'1. RMG'!E130,IF(D5='Basic Bullets'!E2,'2. Textile '!E130,IF(D5='Basic Bullets'!E3,'3. Food and Allied'!E130,IF(D5='Basic Bullets'!E4,'4. Pharmaceutical'!E130,IF(D5='Basic Bullets'!E5,'5. Chemical'!E130,IF(D5='Basic Bullets'!E6,'6. Fertilizer'!E130,IF(D5='Basic Bullets'!E7,'7.Cement'!E130,IF(D5='Basic Bullets'!E8,'8. Ceramic'!E130,IF(D5='Basic Bullets'!E9,'9. Ship Building'!E130,IF(D5='Basic Bullets'!E10,'10. Ship Breaking'!E130,IF(D5='Basic Bullets'!E11,'11. Jute Mills'!E130,IF(D5='Basic Bullets'!E12,'12. Steel Engineering '!E130,IF(D5='Basic Bullets'!E13,'13.Power and gas'!E130,IF(D5='Basic Bullets'!E14,'14. Industry_Others'!E130,IF(D5='Basic Bullets'!E15,'B. Trade and commerce'!E130,IF(D5='Basic Bullets'!E16,'C. Agro'!E130,IF(D5='Basic Bullets'!E17,'1. Service_Housing&Cnst'!E130,IF(D5='Basic Bullets'!E18,'2. Service_Telecom'!E130,IF(D5='Basic Bullets'!E19,'3. Servic_Hospitals&Clinics'!E130,IF(D5='Basic Bullets'!E20,'3. Service_ Others '!E130,0)))))))))))))))))))) -> 2 | F37: 3 | G37: =E37/F37 -> 0.66666667 | H37: =IF(G37>=80%,"Excellent",IF(G37>=70%,"Good",IF(G37>=60%,"Marginal",IF(G37<60%,"Unacceptable",0)))) -> Marginal
B38: F.2 | C38: ='9. Inputs-Analysis'!C48 -> 2. Cashflow based accrual ratio (CAR) | D38: =IF(D5='Basic Bullets'!E1,'1. RMG'!D137,IF(D5='Basic Bullets'!E2,'2. Textile '!D137,IF(D5='Basic Bullets'!E3,'3. Food and Allied'!D137,IF(D5='Basic Bullets'!E4,'4. Pharmaceutical'!D137,IF(D5='Basic Bullets'!E5,'5. Chemical'!D137,IF(D5='Basic Bullets'!E6,'6. Fertilizer'!D137,IF(D5='Basic Bullets'!E7,'7.Cement'!D137,IF(D5='Basic Bullets'!E8,'8. Ceramic'!D137,IF(D5='Basic Bullets'!E9,'9. Ship Building'!D137,IF(D5='Basic Bullets'!E10,'10. Ship Breaking'!D137,IF(D5='Basic Bullets'!E11,'11. Jute Mills'!D137,IF(D5='Basic Bullets'!E12,'12. Steel Engineering '!D137,IF(D5='Basic Bullets'!E13,'13.Power and gas'!D137,IF(D5='Basic Bullets'!E14,'14. Industry_Others'!D137,IF(D5='Basic Bullets'!E15,'B. Trade and commerce'!D137,IF(D5='Basic Bullets'!E16,'C. Agro'!D137,IF(D5='Basic Bullets'!E17,'1. Service_Housing&Cnst'!D137,IF(D5='Basic Bullets'!E18,'2. Service_Telecom'!D137,IF(D5='Basic Bullets'!E19,'3. Servic_Hospitals&Clinics'!D137,IF(D5='Basic Bullets'!E20,'3. Service_ Others '!D137,0)))))))))))))))))))) -> 0.0077292885 | E38: =IF(D5='Basic Bullets'!E1,'1. RMG'!E137,IF(D5='Basic Bullets'!E2,'2. Textile '!E137,IF(D5='Basic Bullets'!E3,'3. Food and Allied'!E137,IF(D5='Basic Bullets'!E4,'4. Pharmaceutical'!E137,IF(D5='Basic Bullets'!E5,'5. Chemical'!E137,IF(D5='Basic Bullets'!E6,'6. Fertilizer'!E137,IF(D5='Basic Bullets'!E7,'7.Cement'!E137,IF(D5='Basic Bullets'!E8,'8. Ceramic'!E137,IF(D5='Basic Bullets'!E9,'9. Ship Building'!E137,IF(D5='Basic Bullets'!E10,'10. Ship Breaking'!E137,IF(D5='Basic Bullets'!E11,'11. Jute Mills'!E137,IF(D5='Basic Bullets'!E12,'12. Steel Engineering '!E137,IF(D5='Basic Bullets'!E13,'13.Power and gas'!E137,IF(D5='Basic Bullets'!E14,'14. Industry_Others'!E137,IF(D5='Basic Bullets'!E15,'B. Trade and commerce'!E137,IF(D5='Basic Bullets'!E16,'C. Agro'!E137,IF(D5='Basic Bullets'!E17,'1. Service_Housing&Cnst'!E137,IF(D5='Basic Bullets'!E18,'2. Service_Telecom'!E137,IF(D5='Basic Bullets'!E19,'3. Servic_Hospitals&Clinics'!E137,IF(D5='Basic Bullets'!E20,'3. Service_ Others '!E137,0)))))))))))))))))))) -> 0 | F38: 2 | G38: =E38/F38 -> 0 | H38: =IF(G38>=80%,"Excellent",IF(G38>=70%,"Good",IF(G38>=60%,"Marginal",IF(G38<60%,"Unacceptable",0)))) -> Unacceptable
B39: Qualitative Assessments | E39: =E40+E44+E49+E54+E59+E61 -> 28.5 | F39: =F40+F44+F49+F54+F59+F61 -> 40 | G39: =E39/F39 -> 0.7125 | H39: =IF(G39>=80%,"Excellent",IF(G39>=70%,"Good",IF(G39>=60%,"Marginal",IF(G39<60%,"Unacceptable",0)))) -> Good
B40: G | C40: Performance Behavior | E40: =SUM(E41:E43) -> 10 | F40: =SUM(F41:F43) -> 10 | G40: =E40/F40 -> 1 | H40: =IF(G40>=80%,"Excellent",IF(G40>=70%,"Good",IF(G40>=60%,"Marginal",IF(G40<60%,"Unacceptable",0)))) -> Excellent
B41: G.1.1 | C41: ='10. Qualitative Analysis'!C19 -> How many times the borrower was adversely classified in last 3 years | D41: ='10. Qualitative Analysis'!F19 -> O time | E41: ='10. Qualitative Analysis'!G19 -> 5 | F41: ='10. Qualitative Analysis'!E20 -> 5 | G41: =E41/F41 -> 1 | H41: =IF(G41>=80%,"Excellent",IF(G41>=70%,"Good",IF(G41>=60%,"Marginal",IF(G41<60%,"Unacceptable",0)))) -> Excellent
B42: G.1.2 | C42: ='10. Qualitative Analysis'!C25 -> How many times the borrower's loans was rescheduled/ restructured in last 3 years | D42: ='10. Qualitative Analysis'!F25 -> 0 time | E42: ='10. Qualitative Analysis'!G25 -> 4 | F42: ='10. Qualitative Analysis'!E26 -> 4 | G42: =E42/F42 -> 1 | H42: =IF(G42>=80%,"Excellent",IF(G42>=70%,"Good",IF(G42>=60%,"Marginal",IF(G42<60%,"Unacceptable",0)))) -> Excellent
B43: G.2 | C43: ='10. Qualitative Analysis'!C32 -> Did The Borrower Pay Its Suppliers/ Creditors Regularly In Last 1 Year | D43: ='10. Qualitative Analysis'!F31 -> Yes | E43: ='10. Qualitative Analysis'!G31 -> 1 | F43: ='10. Qualitative Analysis'!E32 -> 1 | G43: =E43/F43 -> 1 | H43: =IF(G43>=80%,"Excellent",IF(G43>=70%,"Good",IF(G43>=60%,"Marginal",IF(G43<60%,"Unacceptable",0)))) -> Excellent
B44: H | C44: Business and Industry Risk | E44: =SUM(E45:E48) -> 6 | F44: =SUM(F45:F48) -> 7 | G44: =E44/F44 -> 0.85714286 | H44: =IF(G44>=80%,"Excellent",IF(G44>=70%,"Good",IF(G44>=60%,"Marginal",IF(G44<60%,"Unacceptable",0)))) -> Excellent
B45: H.1 | C45: ='10. Qualitative Analysis'!C35 -> Sales Growth | D45: ='10. Qualitative Analysis'!F35 -> >10% | E45: ='10. Qualitative Analysis'!G35 -> 2 | F45: 2 | G45: =E45/F45 -> 1 | H45: =IF(G45>=80%,"Excellent",IF(G45>=70%,"Good",IF(G45>=60%,"Marginal",IF(G45<60%,"Unacceptable",0)))) -> Excellent
B46: H.2 | C46: Age of Business | D46: ='10. Qualitative Analysis'!F41 -> >10 years | E46: ='10. Qualitative Analysis'!G41 -> 2 | F46: 2 | G46: =E46/F46 -> 1 | H46: =IF(G46>=80%,"Excellent",IF(G46>=70%,"Good",IF(G46>=60%,"Marginal",IF(G46<60%,"Unacceptable",0)))) -> Excellent
B47: H.3 | C47: Industry Prospects | D47: ='10. Qualitative Analysis'!F47 -> Growing but High Volatility | E47: ='10. Qualitative Analysis'!G47 -> 0.5 | F47: 1 | G47: =E47/F47 -> 0.5 | H47: =IF(G47>=85%,"Excellent",IF(G47>=70%,"Good",IF(G47>=55%,"Marginal",IF(G47<55%,"Unacceptable",0)))) -> Unacceptable
B48: H.4 | C48: ='10. Qualitative Analysis'!C52 -> Long-Term External Credit Rating of the Borrower | D48: ='10. Qualitative Analysis'!F52 -> 2&3 | E48: ='10. Qualitative Analysis'!G52 -> 1.5 | F48: 2 | G48: =E48/F48 -> 0.75 | H48: =IF(G48>=80%,"Excellent",IF(G48>=70%,"Good",IF(G48>=60%,"Marginal",IF(G48<60%,"Unacceptable",0)))) -> Good
B49: I | C49: Management Risk | E49: =SUM(E50:E53) -> 5 | F49: =SUM(F50:F53) -> 7 | G49: =E49/F49 -> 0.71428571 | H49: =IF(G49>=80%,"Excellent",IF(G49>=70%,"Good",IF(G49>=60%,"Marginal",IF(G49<60%,"Unacceptable",0)))) -> Good
B50: I.1 | C50: Experience of the Management | D50: ='10. Qualitative Analysis'!F58 -> More than 10 years in the related line of business | E50: ='10. Qualitative Analysis'!G58 -> 2 | F50: 2 | G50: =E50/F50 -> 1 | H50: =IF(G50>=80%,"Excellent",IF(G50>=70%,"Good",IF(G50>=60%,"Marginal",IF(G50<60%,"Unacceptable",0)))) -> Excellent
B51: I.2 | C51: Existence of Succession Plan | D51: ='10. Qualitative Analysis'!F63 -> Yes, with good capability of successor | E51: ='10. Qualitative Analysis'!G63 -> 2 | F51: 2 | G51: =E51/F51 -> 1 | H51: =IF(G51>=80%,"Excellent",IF(G51>=70%,"Good",IF(G51>=60%,"Marginal",IF(G51<60%,"Unacceptable",0)))) -> Excellent
B52: I.3 | C52: Auditing Firms | D52: ='10. Qualitative Analysis'!F68 -> Other Auditors | E52: ='10. Qualitative Analysis'!G68 -> 1 | F52: 2 | G52: =E52/F52 -> 0.5 | H52: =IF(G52>=80%,"Excellent",IF(G52>=70%,"Good",IF(G52>=60%,"Marginal",IF(G52<60%,"Unacceptable",0)))) -> Unacceptable
B53: I.4 | C53: Change in Auditors in last 3 years | D53: ='10. Qualitative Analysis'!F72 -> No | E53: ='10. Qualitative Analysis'!G72 -> 0 | F53: 1 | G53: =E53/F53 -> 0 | H53: =IF(G53>=80%,"Excellent",IF(G53>=70%,"Good",IF(G53>=60%,"Marginal",IF(G53<60%,"Unacceptable",0)))) -> Unacceptable
B54: J | C54: Security Risk | E54: =SUM(E55:E58) -> 2.5 | F54: =SUM(F55:F58) -> 11 | G54: =E54/F54 -> 0.22727273 | H54: =IF(G54>=80%,"Excellent",IF(G54>=70%,"Good",IF(G54>=60%,"Marginal",IF(G54<60%,"Unacceptable",0)))) -> Unacceptable
B55: J.1 | C55: Primary Security | D55: ='10. Qualitative Analysis'!F76 -> Registered Hypothecation (1st Charge/1st Pari Passu Charge) | E55: ='10. Qualitative Analysis'!G76 -> 1.5 | F55: 2 | G55: =E55/F55 -> 0.75 | H55: =IF(G55>=80%,"Excellent",IF(G55>=70%,"Good",IF(G55>=60%,"Marginal",IF(G55<60%,"Unacceptable",0)))) -> Good
B56: J.2 | C56: Collateral | D56: ='10. Qualitative Analysis'!F81 -> No Collateral | E56: ='10. Qualitative Analysis'!G81 -> 0 | F56: 2 | G56: =E56/F56 -> 0 | H56: =IF(G56>=80%,"Excellent",IF(G56>=70%,"Good",IF(G56>=60%,"Marginal",IF(G56<60%,"Unacceptable",0)))) -> Unacceptable
B57: J.3 | C57: Collataral Coverage | D57: ='10. Qualitative Analysis'!F86 -> <50% | E57: ='10. Qualitative Analysis'!G86 -> 0 | F57: 5 | G57: =E57/F57 -> 0 | H57: =IF(G57>=80%,"Excellent",IF(G57>=70%,"Good",IF(G57>=60%,"Marginal",IF(G57<60%,"Unacceptable",0)))) -> Unacceptable
B58: J.4 | C58: Guarantee | D58: ='10. Qualitative Analysis'!F92 -> Personal Guarantees or Corporate Guarantee without Strong Financial Strength | E58: ='10. Qualitative Analysis'!G92 -> 1 | F58: 2 | G58: =E58/F58 -> 0.5 | H58: =IF(G58>=80%,"Excellent",IF(G58>=70%,"Good",IF(G58>=60%,"Marginal",IF(G58<60%,"Unacceptable",0)))) -> Unacceptable
B59: K | C59: Guarantee | E59: =E60 -> 3 | F59: =F60 -> 3 | G59: =E59/F59 -> 1 | H59: =IF(G59>=80%,"Excellent",IF(G59>=70%,"Good",IF(G59>=60%,"Marginal",IF(G59<60%,"Unacceptable",0)))) -> Excellent
B60: K.1 | C60: Account Conduct | D60: ='10. Qualitative Analysis'!F99 -> More than 3 years Accounts with Faultless Record | E60: ='10. Qualitative Analysis'!G99 -> 3 | F60: 3 | G60: =E60/F60 -> 1 | H60: =IF(G60>=80%,"Excellent",IF(G60>=70%,"Good",IF(G60>=60%,"Marginal",IF(G60<60%,"Unacceptable",0)))) -> Excellent
B61: L | C61: Compliance Risk | E61: =SUM(E62:E63) -> 2 | F61: =SUM(F62:F63) -> 2 | G61: =E61/F61 -> 1 | H61: =IF(G61>=80%,"Excellent",IF(G61>=70%,"Good",IF(G61>=60%,"Marginal",IF(G61<60%,"Unacceptable",0)))) -> Excellent
B62: L.1 | C62: Compliance with environmental rules, regulations and covenants | D62: ='10. Qualitative Analysis'!F105 -> Yes | E62: ='10. Qualitative Analysis'!G105 -> 1 | F62: 1 | G62: =E62/F62 -> 1 | H62: =IF(G62>=80%,"Excellent",IF(G62>=70%,"Good",IF(G62>=60%,"Marginal",IF(G62<60%,"Unacceptable",0)))) -> Excellent
B63: L.2 | C63: Corporate Governance and CSR activities | D63: ='10. Qualitative Analysis'!F108 -> Good Corporate Governance | E63: ='10. Qualitative Analysis'!G108 -> 1 | F63: 1 | G63: =E63/F63 -> 1 | H63: =IF(G63>=80%,"Excellent",IF(G63>=70%,"Good",IF(G63>=60%,"Marginal",IF(G63<60%,"Unacceptable",0)))) -> Excellent
B64: * DCRR = Dynamic Credit Risk Rating
B65: Note: 1. For any Risk Area, if the riskrating falls under yellow or redzone, whatever the aggregate score is, The relationship manager should justyfy how those risks are mitigated if the loan is sanctioned and in final proposal, the approval authority should review that thoroghly and make necessary comments on how the bank will manage the risk and the details of that official discussions should be retained in the loan file.
B66: 2. Loans can be sanctioned only if the ICRS is 70% or more (excellent and good category). But if the ICRS category is 60% to 69% level, management should take cautionary measures and may sanction the loan based on perofrmance behavior, relationship, collateral and maangement quality of the borrower.
B68: 3. No loan can be sanctioned for borroer whose DCRR is less than 60% except the loan is 100% cash covered or Government Guaranteed or Bank Guaranteed of for stateowned organization or projects
B69: 4. Whatever score a borrower get in qualitative analysis, if the score in quantative part is less than 50/60%, the borrower's ICRM cant be more than Fair.

Sheet 12. Executive Summary
B2: ='11. Detail Managment Report'!B2:C2 -> File / Reference No: | D2: ='11. Detail Managment Report'!D2 -> Outpace Spinning Mills Ltd
B3: ='11. Detail Managment Report'!B3:C3 -> Borrower Name | D3: Audited | E3: Total Score
B4: ='11. Detail Managment Report'!B4:C4 -> Group Name (if any) | D4: ='11. Detail Managment Report'!D4 -> Outright Group | I4: Score obtained | J4: not obtained
B5: ='11. Detail Managment Report'!B5:C5 -> Industry Name | D5: ='11. Detail Managment Report'!D5 -> 2. Textile | H5: Total | I5: =F31 -> 0.505 | J5: =1-I5 -> 0.495
B6: ='11. Detail Managment Report'!B6:C6 -> Latest CIB Status | D6: ='11. Detail Managment Report'!D6 -> Standard | E6: Quantitative Score | H6: Quantitative | I6: =F17 -> 0.36666667 | J6: =1-I6 -> 0.63333333
B7: ='11. Detail Managment Report'!B7:C7 -> Audit Status | D7: ='11. Detail Managment Report'!D7 -> Unaudited | H7: Qualitative | I7: =F24 -> 0.7125 | J7: =1-I7 -> 0.2875
B8: ='11. Detail Managment Report'!B8:C8 -> Auditor Name | D8: ='11. Detail Managment Report'!D8 -> Dewan Nazrul Islam & Co.
B9: ='11. Detail Managment Report'!B9:C9 -> Analyst Name, Designations | D9: ='11. Detail Managment Report'!D9 -> Md. Matiur Rahman, SRM
B10: ='11. Detail Managment Report'!B10:C10 -> Verifier Name, Designation | D10: ='11. Detail Managment Report'!D10 -> Farhana Afrin, SM
B11: ='11. Detail Managment Report'!B12:C12 -> Date of Analysis | D11: ='11. Detail Managment Report'!D12 -> 45652 | E11: Qualitative Score
B12: ='11. Detail Managment Report'!B13:C13 -> Date of Financials | D12: ='11. Detail Managment Report'!D13 -> 45473
B13: Assessment Criteria: Greater than or equal to 80%= Excellent; 70%-80% = Good; 60% to 70% = Marginal; Less than 60% = Unacceptable
D16: Score Obtained | E16: Scale | F16: Percentage | G16: ICRR | O16: s
B17: Quantitative Assessments | D17: =SUM(D18:D23) -> 22 | E17: =SUM(E18:E23) -> 60 | F17: =D17/E17 -> 0.36666667 | G17: =IF(F17>=80%,"Excellent",IF(F17>=70%,"Good",IF(F17>=50%,"Marginal",IF(F17<50%,"Unacceptable",0)))) -> Unacceptable
B18: A | C18: Leverage | D18: ='11. Detail Managment Report'!E17 -> 1 | E18: ='11. Detail Managment Report'!F17 -> 10 | F18: =D18/E18 -> 0.1 | G18: =IF(F18>=80%,"Excellent",IF(F18>=70%,"Good",IF(F18>=60%,"Marginal",IF(F18<60%,"Unacceptable",0)))) -> Unacceptable
B19: B | C19: Liquidity | D19: ='11. Detail Managment Report'!E20 -> 5 | E19: ='11. Detail Managment Report'!F20 -> 10 | F19: =D19/E19 -> 0.5 | G19: =IF(F19>=80%,"Excellent",IF(F19>=70%,"Good",IF(F19>=60%,"Marginal",IF(F19<60%,"Unacceptable",0)))) -> Unacceptable
B20: C | C20: Profitability | D20: ='11. Detail Managment Report'!E23 -> 5 | E20: ='11. Detail Managment Report'!F23 -> 10 | F20: =D20/E20 -> 0.5 | G20: =IF(F20>=80%,"Excellent",IF(F20>=70%,"Good",IF(F20>=60%,"Marginal",IF(F20<60%,"Unacceptable",0)))) -> Unacceptable
B21: D | C21: Coverage | D21: ='11. Detail Managment Report'!E27 -> 6 | E21: ='11. Detail Managment Report'!F27 -> 15 | F21: =D21/E21 -> 0.4 | G21: =IF(F21>=80%,"Excellent",IF(F21>=70%,"Good",IF(F21>=60%,"Marginal",IF(F21<60%,"Unacceptable",0)))) -> Unacceptable
B22: E | C22: Operational Efficiency | D22: ='11. Detail Managment Report'!E32 -> 3 | E22: ='11. Detail Managment Report'!F32 -> 10 | F22: =D22/E22 -> 0.3 | G22: =IF(F22>=80%,"Excellent",IF(F22>=70%,"Good",IF(F22>=60%,"Marginal",IF(F22<60%,"Unacceptable",0)))) -> Unacceptable
B23: F | C23: Earning Quality | D23: ='11. Detail Managment Report'!E36 -> 2 | E23: ='11. Detail Managment Report'!F36 -> 5 | F23: =D23/E23 -> 0.4 | G23: =IF(F23>=80%,"Excellent",IF(F23>=70%,"Good",IF(F23>=60%,"Marginal",IF(F23<60%,"Unacceptable",0)))) -> Unacceptable
B24: Qualitative Assessments | D24: =SUM(D25:D30) -> 28.5 | E24: =SUM(E25:E30) -> 40 | F24: =D24/E24 -> 0.7125 | G24: =IF(F24>=80%,"Excellent",IF(F24>=70%,"Good",IF(F24>=60%,"Marginal",IF(F24<60%,"Unacceptable",0)))) -> Good
B25: G | C25: Performance behavior | D25: ='11. Detail Managment Report'!E40 -> 10 | E25: ='11. Detail Managment Report'!F40 -> 10 | F25: =D25/E25 -> 1 | G25: =IF(F25>=80%,"Excellent",IF(F25>=70%,"Good",IF(F25>=60%,"Marginal",IF(F25<60%,"Unacceptable",0)))) -> Excellent
B26: H | C26: Business and Industry Risk | D26: ='11. Detail Managment Report'!E44 -> 6 | E26: ='11. Detail Managment Report'!F44 -> 7 | F26: =D26/E26 -> 0.85714286 | G26: =IF(F26>=80%,"Excellent",IF(F26>=70%,"Good",IF(F26>=60%,"Marginal",IF(F26<60%,"Unacceptable",0)))) -> Excellent
B27: I | C27: Management Risk | D27: ='11. Detail Managment Report'!E49 -> 5 | E27: ='11. Detail Managment Report'!F49 -> 7 | F27: =D27/E27 -> 0.71428571 | G27: =IF(F27>=80%,"Excellent",IF(F27>=70%,"Good",IF(F27>=60%,"Marginal",IF(F27<60%,"Unacceptable",0)))) -> Good
B28: J | C28: Security Risk | D28: ='11. Detail Managment Report'!E54 -> 2.5 | E28: ='11. Detail Managment Report'!F54 -> 11 | F28: =D28/E28 -> 0.22727273 | G28: =IF(F28>=80%,"Excellent",IF(F28>=70%,"Good",IF(F28>=60%,"Marginal",IF(F28<60%,"Unacceptable",0)))) -> Unacceptable
B29: K | C29: Relationship Risk | D29: ='11. Detail Managment Report'!E59 -> 3 | E29: ='11. Detail Managment Report'!F59 -> 3 | F29: =D29/E29 -> 1 | G29: =IF(F29>=80%,"Excellent",IF(F29>=70%,"Good",IF(F29>=60%,"Marginal",IF(F29<60%,"Unacceptable",0)))) -> Excellent
B30: L | C30: Compliance Risk | D30: ='11. Detail Managment Report'!E61 -> 2 | E30: ='11. Detail Managment Report'!F61 -> 2 | F30: =D30/E30 -> 1 | G30: =IF(F30>=80%,"Excellent",IF(F30>=70%,"Good",IF(F30>=60%,"Marginal",IF(F30<60%,"Unacceptable",0)))) -> Excellent
B31: Aggregate | D31: =D17+D24 -> 50.5 | E31: =E17+E24 -> 100 | F31: =D31/E31 -> 0.505 | G31: =IF(F17<50%,"Unacceptable",IF(F31>=80%,"Excellent",IF(F31>=70%,"Good",IF(F31>=60%,"Marginal",IF(F31<60%,"Unacceptable",0))))) -> Unacceptable
C36: Note: For any Risk Area, if the risk mapping falls under yellow or redzone, whatever the aggregate score is, The relationship manager should justyfy how those risks are mitigated and in final proposal is, the approval authority should review that thoroghly and make necessary comments on how the bank will manage the risk and the details of that official discussions should be retained in the loan file
C37: 2. Loans can be sanctioned only if the ICRS is 70% or more (excellent and good category). But if the ICRS category is 60% to 69% level, management should take cautionary measures and may sanction the loan based on perofrmance behavior, relationship, collateral and maangement quality of the borrower.
C39: 3. No loan can be sanctioned for borroer whose ICRS is less than 60% except the loan is 100% cash covered or Government Guaranteed or Bank Guaranteed.
C40: 4. Whatever score a borrower get in qualitative analysis, if the score in quantative part is less than 55%, then the loan cant be sanctioned.
C41: 5. If there is unprecedented movement in graph, the analyst should verify he root causes of such aberrant movement; in this regard the analyst should be sketical regarding such movement
B45: * if the score of quantitiave analysis is less than 50%, whatever the aggregate score is, the overall ICRR will be "Unacceptable"

Sheet Annex Eligible Collateral
G4: Eligible Collateral
G6: -100% of deposit under lien against the loan
G7: -100% of the value of government bond/savings certificate under lien
G8: -100% of the value of guarantee given by Government or Bangladesh Bank
G9: -100% of the market value of gold or gold ornaments pledged with the bank.
G10: - 50% of the market value of easily marketable commodities kept under control of the bank
G11: - Maximum 50% of the market value of land and building mortgaged with the bank
G12: - 50% of the average market value for last 06 months or 50% of the face value,
G13: whichever is less, of the shares traded in stock exchange.

Sheet Annex rating maping
E7: Rating Mapping
E9: BB Rating Grade | F9: Equivalent Rating of S&P and Fitch | G9: Equivalent Rating of Moody | H9: Equivalent Rating of CRISL | I9: Equivalent Rating of CRAB | J9: Equivalent Rating of NCRL | K9: Equivalent Rating of ECRL | L9: Equivalent Rating of ACRSL | M9: Equivalent Rating of ACRL | N9: Equivalent Rating of WASO
E10: 1 | F10: AAA to AA | G10: Aaa to Aa | H10: AAA, | I10: AAA, | J10: AAA, | K10: AAA, | L10: AAA, | M10: AAA, | N10: AAA
H11: AA+, AA, AA- | I11: AA1, AA2, AA3 | J11: AA+, AA, AA- | K11: AA+, AA, AA- | L11: AA+, AA, AA- | M11: AA+, AA, AA- | N11: AA1, AA2, AA3
E12: 2 | F12: A | G12: A | H12: A+, A, A- | I12: A1, A2, A3 | J12: A+, A, A- | K12: A+, A, A- | L12: A+, A, A- | M12: A+, A, A- | N12: A1, A2, A3
E13: 3 | F13: BBB | G13: Baa | H13: BBB+, BBB, BBB- | I13: BBB1, BBB2, BBB3 | J13: BBB+, BBB, BBB- | K13: BBB+, BBB, BBB- | L13: BBB+, BBB, BBB- | M13: BBB+, BBB, BBB- | N13: BBB1, BBB2, BBB3
E14: 4 | F14: BB to B | G14: Ba to B | H14: BB+, BB, BB- | I14: BB1, BB2, BB3 | J14: BB+, BB, BB- | K14: BB+, BB, BB- | L14: BB+, BB, BB- | M14: BB+, BB, BB- | N14: BB1, BB2, BB3
E15: 5 | F15: Below B | G15: Below B | H15: B+, B, B-, | I15: B1, B2, B3, | J15: B+, B, B- | K15: B+, B, B- | L15: B+, B, B-, | M15: B+, B, B-, | N15: B1, B2, B3, CCC
H16: CCC+, CCC, CCC-, | I16: CCC1, CCC2, CCC3, | L16: CC+,CC,CC- | M16: CCC
H17: CC+, CC, CC- | I17: CC
E18: 6 | H18: C+, C, C-, D | I18: C, D | J18: C+, C, C-, D | K18: D | L18: C+, C, C-, D | M18: CC+,CC,CC-, | N18: CC1, CC2, CC3, C+, C, C-, D
M19: C+, C, C-, D
E20: Short-Term Rating Category Mapping
E21: S1 | F21: F1+ | G21: P1 | H21: ST-1 | I21: ST-1 | J21: N1 | K21: ECRL-1 | L21: ST-1 | M21: AR-1 | N21: P-1
E22: S2 | F22: F1 | G22: P2 | H22: ST-2 | I22: ST-2 | J22: N2 | K22: ECRL-2 | L22: ST-2 | M22: AR-2 | N22: P-2
E23: S3 | F23: F2 | G23: P3 | H23: ST-3 | I23: ST-3 | J23: N3 | K23: ECRL-3 | L23: ST-3 | M23: AR-3 | N23: P-3
E24: S4 | F24: F3 | H24: ST-4 | I24: ST-4 | J24: N4 | K24: ECRL-4 | L24: ST-4 | M24: AR-4 | N24: P-4
E25: S5,S6 | F25: B,C, D | G25: NP | H25: ST-5, ST-6 | I25: ST-5, ST-6 | J25: N5 | K25: D | L25: ST-5, ST-6 | M25: AR-5, AR-6 | N25: P-5, P-6

Sheet Drop DOwn
E1: Sector Classificaions | F1: Code | I1: Ownership | K1: CIB Status
E2: A. Industry: | F2: Error: Please Select Sub Group | I2: Sole Proprietorship | K2: Standard
E3: 1. RMG | F3: 101 | I3: Partnership | K3: SMA
E4: 2. Textile | F4: 102 | I4: Private Ltd | K4: Doubtful
E5: 3. Food and Allied | F5: 103 | I5: Public Ltd | K5: Substandard
E6: 4. Pharmaceutical | F6: 104 | K6: Bad&Loss
E7: 5. Chemical | F7: 105
E8: 6. Fertilizer | F8: 106
E9: 7.Cement | F9: 107
E10: 8. Ceramic | F10: 108
E11: 9. Ship Building | F11: 109
E12: 10 Ship Breaking | F12: 110
E13: 11. Jute Mills | F13: 111 | I13: Audit Status
E14: 12. Steel Engineering | F14: 112 | I14: Audited
E15: 13.Power and gas | F15: 113 | I15: Unaudited
E16: 14. Others | F16: 114
E17: B. Trade and commerce | F17: 200
E18: C. Agro based and Agro Processing | F18: 300
E19: D. Service: | F19: Error: Please Select Sub Group
E20: 1. Housing and Construction | F20: 401
E21: 2. Telecommunication | F21: 402
E22: 3. Hospitals and Clinics | F22: 403
E23: 4. Others | F23: 404

Sheet 1. RMG
A1: Internal Credit Risk Score Sheet
A2: Quantitative Analysis (RMG)
A3: File / Reference No: | B3: ='11. Detail Managment Report'!D2 -> Outpace Spinning Mills Ltd
A4: Borrowe Name | B4: ='11. Detail Managment Report'!D3 -> Outpace Spinning Mills Ltd
A5: Group Name (if any) | B5: ='11. Detail Managment Report'!D4 -> Outright Group
A6: Industry Name | B6: ='11. Detail Managment Report'!D5 -> 2. Textile | S6: Score | T6: =C142 -> 0.3 | U6: =1-T6 -> 0.7
A7: Latest CIB Status | B7: ='11. Detail Managment Report'!D6 -> Standard
A8: Audit Status | B8: ='11. Detail Managment Report'!D7 -> Unaudited
A9: Auditor Name | B9: ='11. Detail Managment Report'!D8 -> Dewan Nazrul Islam & Co.
A10: Analyst Name, Designations | B10: ='11. Detail Managment Report'!D9 -> Md. Matiur Rahman, SRM
A11: Verifier Name, Designation | B11: ='11. Detail Managment Report'!D10 -> Farhana Afrin, SM
A13: Date of Analysis | B13: ='11. Detail Managment Report'!D12 -> 45652
A14: Date of Financials | B14: ='11. Detail Managment Report'!D13 -> 45473
A16: Quantitative Indicators (60)
A17: Criteria | B17: Parameter | C17: Score | D17: Actual Parameter | E17: Score Obtained
A18: A. Leverage | C18: 10 | E18: =E19+E29 -> 1
A19: ='11. Detail Managment Report'!C18 -> 1. Financial Debt to Tangible Net Worth (DTN) | B19: Less than 0.75× | C19: 7 | D19: ='9. Inputs-Analysis'!D4 -> 3.9252586 | E19: =IF(D19<=0,0,IF(D19<0.75,7,IF(D19<1,6,IF(D19<1.25,5,IF(D19<1.5,4,IF(D19<2.5,3,IF(D19<3.5,2,0))))))) -> 0
B20: 0.75x to 1.00x | C20: 6
B21: 1.01× to 1.25x | C21: 5
B22: 1.26 × to 1.50x | C22: 4
B23: 1.51× to 2.00x | C23: 3
B24: 2.01× to 3.00 x | C24: 2
B25: More than or equal to 3.01× | C25: 0
A29: ='11. Detail Managment Report'!C19 -> 2. Financial Debt to Total Assets (DTA) | B29: Less than 0.35x | C29: 3 | D29: ='9. Inputs-Analysis'!D7 -> 0.78528911 | E29: =IF(D29<0,0,IF(D29<0.35,3,IF(D29<0.74,2,IF(D29<0.99,1,0)))) -> 1
B30: 0.35x to 0.74x | C30: 2
B31: 0.74x to 0.99x | C31: 1
B32: Greater than 1.00× | C32: 0
A36: B. Liquidity | C36: 10 | E36: =E37+E45 -> 5
A37: ='11. Detail Managment Report'!C21 -> 1. Current Ratio (CR) | B37: Greater than 2.00× | C37: 7 | D37: ='9. Inputs-Analysis'!D11 -> 1.0405522 | E37: =IF(D37>2,7,IF(D37>=1.51,6,IF(D37>=1.01,5,IF(D37>=0.51,2,0)))) -> 5
B38: 1.51× to 2.00x | C38: 6
B39: 1.01× to 1.50 x | C39: 5
B40: 0.51× to 1.00x | C40: 2
B41: Less than or equal 0.50 | C41: 0
A45: ='11. Detail Managment Report'!C22 -> 2. Cash Ratio (Cash) | B45: Greater than or equal to 0. 20x | C45: 3 | D45: ='9. Inputs-Analysis'!D10 -> 0.0061472341 | E45: =IF(D45>0.2,3,IF(D45>=0.11,2,IF(D45>=0.06,1,0))) -> 0
B46: 0.11x to 0. 20 x | C46: 2
B47: 0.06x to 0. 10x | C47: 1
B48: Less than 0.06x | C48: 0
A52: C. Profitability | C52: 10 | E52: =E53+E62+E69 -> 4
A53: ='11. Detail Managment Report'!C24 -> 1. Net Profit Margin (NPM) | B53: Greater than or equal to 8% | C53: 5 | D53: ='9. Inputs-Analysis'!D15 -> 0.054896988 | E53: =IF(D53>8%,5,IF(D53>=7%,4,IF(D53>=5%,3,IF(D53>=3%,2,IF(D53>=1%,1,0))))) -> 3
B54: .00% to 8.00% | C54: 4
B55: 5.00% to 7.00% | C55: 3
B56: 3.00% to5.00% | C56: 2
B57: 1.00% to3.00% | C57: 1
B58: Less than or equal to 1% | C58: 0
A62: ='11. Detail Managment Report'!C25 -> 2. Return on Assets (ROA) | B62: Greater than or equal to 5% | C62: 3 | D62: ='9. Inputs-Analysis'!D18 -> 0.019426111 | E62: =IF(D62>5%,3,IF(D62>=3.01%,2,IF(D62>=2.01%,1,0))) -> 0
B63: 3.01% to 5.00% | C63: 2
B64: 2.01% to 3.00% | C64: 1
B65: Less than 2% | C65: 0
A69: ='11. Detail Managment Report'!C26 -> 3. Operating Profit to Operating Assets (OPOA) | B69: Greater than or equal to 6% | C69: 2 | D69: ='9. Inputs-Analysis'!D21 -> 0.04652054 | E69: =IF(D69>6%,2,IF(D69>=4.01%,1,0)) -> 1
B70: 4.01% to 6.00% | C70: 1
B71: Less than or equal to 4% | C71: 0
A75: D. Coverage | C75: 15 | E75: =E76+E83+E93+E100 -> 5
A76: ='11. Detail Managment Report'!C28 -> 1. Interest Coverage (IC) | B76: Greater than or equal to 5x | C76: 3 | D76: ='9. Inputs-Analysis'!D24 -> 2.1640484 | E76: =IF(D76>5,3,IF(D76>=3.01,2,IF(D76>=1.01,1,0))) -> 1
B77: 3.01x to 5.00x | C77: 2
B78: 1.01x-3.00x | C78: 1
B79: Less than or equal to 1x | C79: 0
A83: ='11. Detail Managment Report'!C29 -> 2. Debt Service Coverage Ratio (DSCR) | D83: ='9. Inputs-Analysis'!D27 -> 1.4160266 | E83: =IF(D83>4,5,IF(D83>=3,4,IF(D83>=2,3,IF(D83>=1.51,2,IF(D83>=1.01,1,0))))) -> 1
B84: Greater than or equal to 4.00x | C84: 5
B85: 3.00x to 4.00x | C85: 4
B86: 2.00x to 3.00x | C86: 3
B87: 1.51x to 2.00 x | C87: 2
B88: 1.01x to 1.50x | C88: 1
B89: Less than 1x | C89: 0
A93: ='11. Detail Managment Report'!C30 -> 3. Operating Cashflow to Debt Ratio (CDR) | B93: More than 0.55x | C93: 4 | D93: ='9. Inputs-Analysis'!D30 -> 0.033545581 | E93: =IF(D93>0.55,4,IF(D93>=0.35,3,IF(D93>=0.25,2,IF(D93>=-0.1,1,0)))) -> 1
B94: 0.35x to 0.55x | C94: 3
B95: 0.25x to 0.35x | C95: 2
B96: 0.15x to 0.24x | C96: 1
B97: Less than 0.15x | C97: 0
A100: ='11. Detail Managment Report'!C31 -> 4. Cashflow Coverage Ratio (CCR) | B100: Greater than 1 times | C100: 3 | D100: ='9. Inputs-Analysis'!D33 -> 0.76522361 | E100: =IF(D100>1,3,IF(D100>=0.5,2,IF(D100>=-0.1,1,0))) -> 2
B101: 0.50 time to 1 times | C101: 2
B102: 0.25 time to 0.50 times | C102: 1
B103: Less than 0.25 times | C103: 0
A106: E. Operational Efficiency | C106: 10 | E106: =E107+E115+E122 -> 1
A107: ='11. Detail Managment Report'!C33 -> 1. Stock Turnover Days (STD) | B107: Less than 100 days | C107: 4 | D107: ='9. Inputs-Analysis'!D36 -> 823.7278 | E107: =IF(D107<100,4,IF(D107<120,3,IF(D107<150,2,IF(D107<180,1,0)))) -> 0
B108: 100 to 120 days | C108: 3
B109: 121 to 150 days | C109: 2
B110: 151 days to 180 days | C110: 1
B111: More than or equal to 180 days | C111: 0
A115: ='11. Detail Managment Report'!C34 -> 2. Trade Debtor Collection Days (TDCD) | B115: Less than 45 days | C115: 3 | D115: ='9. Inputs-Analysis'!D39 -> 89.219452 | E115: =IF(D115<45,3,IF(D115<60,2,IF(D115<90,1,0))) -> 1
B116: 45 days to 60 days | C116: 2
B117: 60 days to 90 days | C117: 1
B118: More than or equal to 90 days | C118: 0
A122: ='11. Detail Managment Report'!C35 -> 3. Asset Turnover (AT) | B122: Greater than or equal to 125% | C122: 3 | D122: ='9. Inputs-Analysis'!D42 -> 0.35386479 | E122: =IF(D122>=125%,3,IF(D122>=75%,2,IF(D122>=50%,1,0))) -> 0
B123: 75% to 124% | C123: 2
B124: 50% to 75% | C124: 1
B125: Less than 50% | C125: 0
A129: F. Earning Quality | C129: 5 | E129: =E130+E137 -> 2
A130: ='11. Detail Managment Report'!C37 -> 1. Operating Cash Flow to Sales (CFS) | B130: Greater than 8% | C130: 3 | D130: ='9. Inputs-Analysis'!D45 -> 0.074443631 | E130: =IF(D130>8%,3,IF(D130>=4.01%,2,IF(D130>=2.01%,1,0))) -> 2
B131: 4.01% to 8% | C131: 2
B132: 2.01% to 4% | C132: 1
B133: Less than or equal to 2% | C133: 0
A137: ='11. Detail Managment Report'!C38 -> 2. Cashflow based accrual ratio (CAR) | B137: Negative = 2 | C137: 2 | D137: ='9. Inputs-Analysis'!D48 -> 0.0077292885 | E137: =IF(D137<0,2,IF(D137>0,0,IF(D137=0,1,0))) -> 0
B138: Positive =0 | C138: 0
B139: Zero = 1
A141: Total | C141: =C129+C106+C75+C52+C36+C18 -> 60 | E141: =E129+E106+E75+E52+E36+E18 -> 18
A142: Percentage | C142: =E141/C141 -> 0.3

Sheet 2.  Textile 
A1: Internal Credit Risk Score Sheet
A2: Quantitative Analysis (Service-Hospital&Clinic)
A3: File / Reference No: | B3: ='11. Detail Managment Report'!D2 -> Outpace Spinning Mills Ltd
A4: Borrowe Name | B4: ='11. Detail Managment Report'!D3 -> Outpace Spinning Mills Ltd
A5: Group Name (if any) | B5: ='11. Detail Managment Report'!D4 -> Outright Group
A6: Industry Name | B6: ='11. Detail Managment Report'!D5 -> 2. Textile | S6: Score | T6: =C142 -> 0.36666667 | U6: =1-T6 -> 0.63333333
A7: Latest CIB Status | B7: ='11. Detail Managment Report'!D6 -> Standard
A8: Audit Status | B8: ='11. Detail Managment Report'!D7 -> Unaudited
A9: Auditor Name | B9: ='11. Detail Managment Report'!D8 -> Dewan Nazrul Islam & Co.
A10: Analyst Name, Designations | B10: ='11. Detail Managment Report'!D9 -> Md. Matiur Rahman, SRM
A11: Verifier Name, Designation | B11: ='11. Detail Managment Report'!D10 -> Farhana Afrin, SM
A13: Date of Analysis | B13: ='11. Detail Managment Report'!D12 -> 45652
A14: Date of Financials | B14: ='11. Detail Managment Report'!D13 -> 45473
A16: Quantitative Indicators (60)
A17: Criteria | B17: Parameter | C17: Score | D17: Actual Parameter | E17: Score Obtained
A18: A. Leverage | C18: 10 | E18: =E19+E29 -> 1
A19: ='11. Detail Managment Report'!C18 -> 1. Financial Debt to Tangible Net Worth (DTN) | B19: Less than 0.7× | C19: 7 | D19: ='9. Inputs-Analysis'!D4 -> 3.9252586 | E19: =IF(D19<0,0,IF(D19<0.7,7,IF(D19<1,6,IF(D19<1.5,5,IF(D19<2,4,IF(D19<3,3,IF(D19<3.5,2,0))))))) -> 0
B20: 0.70x to 1.00x | C20: 6
B21: 1.00× to 1.25x | C21: 5
B22: 1.25 × to 1.50x | C22: 4
B23: 1.51× to 2.00x | C23: 3
B24: 2.01× to 2.99 x | C24: 2
B25: More than or equal to 3.00× | C25: 0
A29: ='11. Detail Managment Report'!C19 -> 2. Financial Debt to Total Assets (DTA) | B29: Less than 0.35x | C29: 3 | D29: ='9. Inputs-Analysis'!D7 -> 0.78528911 | E29: =IF(D29<0,0,IF(D29<0.35,3,IF(D29<0.74,2,IF(D29<0.99,1,0)))) -> 1
B30: 0.25x to 0.74x | C30: 2
B31: 0.75x to 0.99x | C31: 1
B32: Greater than or equal to 1.00× | C32: 0
A36: B. Liquidity | C36: 10 | E36: =E37+E45 -> 5
A37: ='11. Detail Managment Report'!C21 -> 1. Current Ratio (CR) | B37: Greater than 2.00× | C37: 7 | D37: ='9. Inputs-Analysis'!D11 -> 1.0405522 | E37: =IF(D37>2,7,IF(D37>=1.51,6,IF(D37>=1.01,5,IF(D37>=0.75,2,IF(D37>=0.51,1,0))))) -> 5
B38: 1.51× to 2.00x | C38: 6
B39: 1.01× to 1.50 x | C39: 5
B40: 0.75× to 1.00x | C40: 2
B41: 0.51x to 1.00x | C41: 1
B42: Less than or equal 0.50 | C42: 0
A45: ='11. Detail Managment Report'!C22 -> 2. Cash Ratio (Cash) | B45: Greater than 0. 10x | C45: 3 | D45: ='9. Inputs-Analysis'!D10 -> 0.0061472341 | E45: =IF(D45>0.1,3,IF(D45>=0.05,2,IF(D45>=0.03,1,0))) -> 0
B46: 0.05x to 0. 10 x | C46: 2
B47: 0.03x to 0. 05x | C47: 1
B48: Less than 0.03x | C48: 0
A52: C. Profitability | C52: 10 | E52: =E53+E62+E69 -> 5
A53: ='11. Detail Managment Report'!C24 -> 1. Net Profit Margin (NPM) | B53: Greater than 8% | C53: 5 | D53: ='9. Inputs-Analysis'!D15 -> 0.054896988 | E53: =IF(D53>8%,5,IF(D53>=7%,4,IF(D53>=5%,3,IF(D53>=3%,2,IF(D53>=1%,1,0))))) -> 3
B54: 7.00% to 8.00% | C54: 4
B55: 5.00% to 7.00% | C55: 3
B56: 3.00% to5.00% | C56: 2
B57: 1.00% to 3.00% | C57: 1
B58: Less than or equal to 1% | C58: 0
A62: ='11. Detail Managment Report'!C25 -> 2. Return on Assets (ROA) | B62: Greater than 4.5% | C62: 3 | D62: ='9. Inputs-Analysis'!D18 -> 0.019426111 | E62: =IF(D62>4.5%,3,IF(D62>=2.5%,2,IF(D62>=1.5%,1,0))) -> 1
B63: 2.50% to 4.50% | C63: 2
B64: 1.50% to 2.49% | C64: 1
B65: Less than 1.50% | C65: 0
A69: ='11. Detail Managment Report'!C26 -> 3. Operating Profit to Operating Assets (OPOA) | B69: Greater than 8% | C69: 2 | D69: ='9. Inputs-Analysis'!D21 -> 0.04652054 | E69: =IF(D69>6%,2,IF(D69>=2%,1,0)) -> 1
B70: 3.50% to 8.00% | C70: 1
B71: Less than or equal to 3.5% | C71: 0
A75: D. Coverage | C75: 15 | E75: =E76+E83+E93+E100 -> 6
A76: ='11. Detail Managment Report'!C28 -> 1. Interest Coverage (IC) | B76: Greater than 3x | C76: 3 | D76: ='9. Inputs-Analysis'!D24 -> 2.1640484 | E76: =IF(D76>3,3,IF(D76>=2.5,2,IF(D76>=1.01,1,0))) -> 1
B77: 2.50x to 3.00x | C77: 2
B78: 1.01x to 2.49x | C78: 1
B79: Less than or equal to 1x | C79: 0
A83: ='11. Detail Managment Report'!C29 -> 2. Debt Service Coverage Ratio (DSCR) | D83: ='9. Inputs-Analysis'!D27 -> 1.4160266 | E83: =IF(D83>2.5,5,IF(D83>=2,4,IF(D83>=1.5,3,IF(D83>=1,2,IF(D83>=0.5,1,0))))) -> 2
B84: Greater than 2.50x | C84: 5
B85: 2.00x to 2.50x | C85: 4
B86: 1.50x to 2.00x | C86: 3
B87: 1.25x to 1.49 x | C87: 2
B88: 1.01x to 1.24x | C88: 1
B89: Less than or equal to 1x | C89: 0
A93: ='11. Detail Managment Report'!C30 -> 3. Operating Cashflow to Debt Ratio (CDR) | B93: More than 0.5x | C93: 4 | D93: ='9. Inputs-Analysis'!D30 -> 0.033545581 | E93: =IF(D93>0.5,4,IF(D93>=0.35,3,IF(D93>=0.25,2,IF(D93>=-0.1,1,0)))) -> 1
B94: 0.35x to 0.50x | C94: 3
B95: 0.25x to 0.35x | C95: 2
B96: 0.15x to 0.10x | C96: 1
B97: less than or equal to 0.15x | C97: 0
A100: ='11. Detail Managment Report'!C31 -> 4. Cashflow Coverage Ratio (CCR) | B100: Greater than 1x | C100: 3 | D100: ='9. Inputs-Analysis'!D33 -> 0.76522361 | E100: =IF(D100>1,3,IF(D100>=0.5,2,IF(D100>=-0.1,1,0))) -> 2
B101: 0.50 x to 1x | C101: 2
B102: 0.25x to 0.50 | C102: 1
B103: Less than 0.5 times | C103: 0
A106: E. Operational Efficiency | C106: 10 | E106: =E107+E115+E122 -> 3
A107: ='11. Detail Managment Report'!C33 -> 1. Stock Turnover Days (STD) | B107: Less than 120 days | C107: 4 | D107: ='9. Inputs-Analysis'!D36 -> 823.7278 | E107: =IF(D107<120,4,IF(D107<150,3,IF(D107<180,2,IF(D107<219,1,0)))) -> 0
B108: 121 days to 150 days | C108: 3
B109: 151 days to 180 days | C109: 2
B110: 180 days to 219 days | C110: 1
B111: More than or equal to 220 days | C111: 0
A115: ='11. Detail Managment Report'!C34 -> 2. Trade Debtor Collection Days (TDCD) | B115: Less than 80 days | C115: 3 | D115: ='9. Inputs-Analysis'!D39 -> 89.219452 | E115: =IF(D115<80,3,IF(D115<120,2,IF(D115<150,1,0))) -> 2
B116: 80 days to 120 days | C116: 2
B117: 121 days to 150 days | C117: 1
B118: More than 150 days | C118: 0
A122: ='11. Detail Managment Report'!C35 -> 3. Asset Turnover (AT) | B122: Greater than 70% | C122: 3 | D122: ='9. Inputs-Analysis'!D42 -> 0.35386479 | E122: =IF(D122>70%,3,IF(D122>=51%,2,IF(D122>=25%,1,0))) -> 1
B123: 51% to 70% | C123: 2
B124: 25% to 50% | C124: 1
B125: Less than 24% | C125: 0
A129: F. Earning Quality | C129: 5 | E129: =E130+E137 -> 2
A130: ='11. Detail Managment Report'!C37 -> 1. Operating Cash Flow to Sales (CFS) | B130: Greater than 8% | C130: 3 | D130: ='9. Inputs-Analysis'!D45 -> 0.074443631 | E130: =IF(D130>8%,3,IF(D130>=4.01%,2,IF(D130>=2.01%,1,0))) -> 2
B131: 4.01% to 8.00% | C131: 2
B132: 2.01% to 4.00% | C132: 1
B133: Less than or equal to 2% | C133: 0
A137: ='11. Detail Managment Report'!C38 -> 2. Cashflow based accrual ratio (CAR) | B137: Negative = 2 | C137: 2 | D137: ='9. Inputs-Analysis'!D48 -> 0.0077292885 | E137: =IF(D137<0,2,IF(D137>0,0,IF(D137=0,1,0))) -> 0
B138: Positive =0 | C138: 0
B139: Zero = 1
A141: Total | C141: =C129+C106+C75+C52+C36+C18 -> 60 | E141: =E129+E106+E75+E52+E36+E18 -> 22
A142: Percentage | C142: =E141/C141 -> 0.36666667

Sheet 3. Food and Allied
A1: Internal Credit Risk Score Sheet
A2: Quantitative Analysis (Service-Hospital&Clinic)
A3: File / Reference No: | B3: ='11. Detail Managment Report'!D2 -> Outpace Spinning Mills Ltd
A4: Borrowe Name | B4: ='11. Detail Managment Report'!D3 -> Outpace Spinning Mills Ltd
A5: Group Name (if any) | B5: ='11. Detail Managment Report'!D4 -> Outright Group
A6: Industry Name | B6: ='11. Detail Managment Report'!D5 -> 2. Textile | S6: Score | T6: =C142 -> 0.36666667 | U6: =1-T6 -> 0.63333333
A7: Latest CIB Status | B7: ='11. Detail Managment Report'!D6 -> Standard
A8: Audit Status | B8: ='11. Detail Managment Report'!D7 -> Unaudited
A9: Auditor Name | B9: ='11. Detail Managment Report'!D8 -> Dewan Nazrul Islam & Co.
A10: Analyst Name, Designations | B10: ='11. Detail Managment Report'!D9 -> Md. Matiur Rahman, SRM
A11: Verifier Name, Designation | B11: ='11. Detail Managment Report'!D10 -> Farhana Afrin, SM
A13: Date of Analysis | B13: ='11. Detail Managment Report'!D12 -> 45652
A14: Date of Financials | B14: ='11. Detail Managment Report'!D13 -> 45473
A16: Quantitative Indicators (60)
A17: Criteria | B17: Parameter | C17: Score | D17: Actual Parameter | E17: Score Obtained
A18: A. Leverage | C18: 10 | E18: =E19+E29 -> 1
A19: ='11. Detail Managment Report'!C18 -> 1. Financial Debt to Tangible Net Worth (DTN) | B19: Less than 0.7× | C19: 7 | D19: ='9. Inputs-Analysis'!D4 -> 3.9252586 | E19: =IF(D19<0,0,IF(D19<0.7,7,IF(D19<1,6,IF(D19<1.5,5,IF(D19<2,4,IF(D19<3,3,IF(D19<3.5,2,0))))))) -> 0
B20: 0.70x to 1.00x | C20: 6
B21: 1.00× to 1.25x | C21: 5
B22: 1.25 × to 1.50x | C22: 4
B23: 1.51× to 2.00x | C23: 3
B24: 2.01× to 2.99 x | C24: 2
B25: More than or equal to 3.00× | C25: 0
A29: ='11. Detail Managment Report'!C19 -> 2. Financial Debt to Total Assets (DTA) | B29: Less than 0.45x | C29: 3 | D29: ='9. Inputs-Analysis'!D7 -> 0.78528911 | E29: =IF(D29<0,0,IF(D29<0.45,3,IF(D29<0.74,2,IF(D29<0.99,1,0)))) -> 1
B30: 0.45x to 0.74x | C30: 2
B31: 0.74x to 0.99x | C31: 1
B32: Greater than 1.00× | C32: 0
A36: B. Liquidity | C36: 10 | E36: =E37+E45 -> 5
A37: ='11. Detail Managment Report'!C21 -> 1. Current Ratio (CR) | B37: Greater than 2.00× | C37: 7 | D37: ='9. Inputs-Analysis'!D11 -> 1.0405522 | E37: =IF(D37>2,7,IF(D37>1.51,6,IF(D37>1.01,5,IF(D37>0.51,2,IF(D37>0.25,1,0))))) -> 5
B38: 1.51× to 2.00x | C38: 6
B39: 1.01× to 1.50 x | C39: 5
B40: 0.51× to 1.00x | C40: 2
B41: 0.25x to 0.50 | C41: 1
B42: Less than or equal to 0.50 | C42: 0
A45: ='11. Detail Managment Report'!C22 -> 2. Cash Ratio (Cash) | B45: Greater than 0. 10x | C45: 3 | D45: ='9. Inputs-Analysis'!D10 -> 0.0061472341 | E45: =IF(D45>0.1,3,IF(D45>0.05,2,IF(D45>0.03,1,0))) -> 0
B46: 0.05x to 0. 10 x | C46: 2
B47: 0.03x to 0. 05x | C47: 1
B48: Less than 0.03x | C48: 0
A52: C. Profitability | C52: 10 | E52: =E53+E62+E69 -> 3
A53: ='11. Detail Managment Report'!C24 -> 1. Net Profit Margin (NPM) | B53: Greater than or equal to 7.00% | C53: 5 | D53: ='9. Inputs-Analysis'!D15 -> 0.054896988 | E53: =IF(D53>=7%,5,IF(D53>=6%,4,IF(D53>=5%,3,IF(D53>=3%,2,IF(D53>=1%,1,0))))) -> 3
B54: 6.00% to 7.00% | C54: 4
B55: 5.00% to 6.00% | C55: 3
B56: 3.00% to5.00% | C56: 2
B57: 1.00% to3.00% | C57: 1
B58: Less than or equal to 1% | C58: 0
A62: ='11. Detail Managment Report'!C25 -> 2. Return on Assets (ROA) | B62: Greater than 6.00% | C62: 3 | D62: ='9. Inputs-Analysis'!D18 -> 0.019426111 | E62: =IF(D62>6%,3,IF(D62>=3.01%,2,IF(D62>=2.01%,1,0))) -> 0
B63: 3.01% to 6.00% | C63: 2
B64: 2.01% to 3.00% | C64: 1
B65: Less than 2% | C65: 0
A69: ='11. Detail Managment Report'!C26 -> 3. Operating Profit to Operating Assets (OPOA) | B69: Greater than 10% | C69: 2 | D69: ='9. Inputs-Analysis'!D21 -> 0.04652054 | E69: =IF(D69>10%,2,IF(D69>=5.01%,1,0)) -> 0
B70: 5.01% to 10.00% | C70: 1
B71: Less than or equal to 5% | C71: 0
A75: D. Coverage | C75: 15 | E75: =E76+E83+E93+E100 -> 6
A76: ='11. Detail Managment Report'!C28 -> 1. Interest Coverage (IC) | B76: Greater than 5x | C76: 3 | D76: ='9. Inputs-Analysis'!D24 -> 2.1640484 | E76: =IF(D76>5,3,IF(D76>=3.01,2,IF(D76>=1.01,1,0))) -> 1
B77: 3.01x to 5.00x | C77: 2
B78: 1.01x to 3.00x | C78: 1
B79: Less than or equal to 1x | C79: 0
A83: ='11. Detail Managment Report'!C29 -> 2. Debt Service Coverage Ratio (DSCR) | D83: ='9. Inputs-Analysis'!D27 -> 1.4160266 | E83: =IF(D83>4,5,IF(D83>=3.01,4,IF(D83>=2.01,3,IF(D83>=1,2,IF(D83>=0.5,1,0))))) -> 2
B84: Greater than 4.00x | C84: 5
B85: 3.01x to 4.00x | C85: 4
B86: 2.01x to 3.00x | C86: 3
B87: 1.51x to 2.00x | C87: 2
B88: 1.01x to 1.51x | C88: 1
B89: Less than or equal to 1x | C89: 0
A93: ='11. Detail Managment Report'!C30 -> 3. Operating Cashflow to Debt Ratio (CDR) | B93: More than 0.50x | C93: 4 | D93: ='9. Inputs-Analysis'!D30 -> 0.033545581 | E93: =IF(D93>0.5,4,IF(D93>0.35,3,IF(D93>0.25,2,IF(D93>-0.1,1,0)))) -> 1
B94: 0.35x to 0.50x | C94: 3
B95: 0.25x to 0.35x | C95: 2
B96: 0.15x to 0.10x | C96: 1
B97: Less than 0.15x | C97: 0
A100: ='11. Detail Managment Report'!C31 -> 4. Cashflow Coverage Ratio (CCR) | B100: Greater than 1x | C100: 3 | D100: ='9. Inputs-Analysis'!D33 -> 0.76522361 | E100: =IF(D100>1,3,IF(D100>=0.5,2,IF(D100>=-0.1,1,0))) -> 2
B101: 0.50x to 1.00x | C101: 2
B102: 0.25x to 0.50x | C102: 1
B103: Less than 0.25x | C103: 0
A106: E. Operational Efficiency | C106: 10 | E106: =E107+E115+E122 -> 4
A107: ='11. Detail Managment Report'!C33 -> 1. Stock Turnover Days (STD) | B107: Less than 100 days | C107: 4 | D107: ='9. Inputs-Analysis'!D36 -> 823.7278 | E107: =IF(D107<100,4,IF(D107<120,3,IF(D107<149,2,IF(D107<180,1,0)))) -> 0
B108: 100 to 120 days | C108: 3
B109: 121 to 149 days | C109: 2
B110: 150 days to 180 days | C110: 1
B111: More than or equal to 180 days | C111: 0
A115: ='11. Detail Managment Report'!C34 -> 2. Trade Debtor Collection Days (TDCD) | B115: Less than 45 days | C115: 3 | D115: ='9. Inputs-Analysis'!D39 -> 89.219452 | E115: =IF(D115<90,3,IF(D115<120,2,IF(D115<180,1,0))) -> 3
B116: 45 days to 60 days | C116: 2
B117: 60 days to 90 days | C117: 1
B118: More than or equal to 90 days | C118: 0
A122: ='11. Detail Managment Report'!C35 -> 3. Asset Turnover (AT) | B122: Greater than 100% | C122: 3 | D122: ='9. Inputs-Analysis'!D42 -> 0.35386479 | E122: =IF(D122>100%,3,IF(D122>=51%,2,IF(D122>=31%,1,0))) -> 1
B123: 51% to 100% | C123: 2
B124: 31% to 50% | C124: 1
B125: Less than or equal to 30% | C125: 0
A129: F. Earning Quality | C129: 5 | E129: =E130+E137 -> 3
A130: ='11. Detail Managment Report'!C37 -> 1. Operating Cash Flow to Sales (CFS) | B130: Greater than 5% | C130: 3 | D130: ='9. Inputs-Analysis'!D45 -> 0.074443631 | E130: =IF(D130>5%,3,IF(D130>=3.01%,2,IF(D130>=2%,1,0))) -> 3
B131: 3.01% to 5.00% | C131: 2
B132: 2.00% to 3.00% | C132: 1
B133: Less than 2% | C133: 0
A137: ='11. Detail Managment Report'!C38 -> 2. Cashflow based accrual ratio (CAR) | B137: Negative = 2 | C137: 2 | D137: ='9. Inputs-Analysis'!D48 -> 0.0077292885 | E137: =IF(D137<0,2,IF(D137>0,0,IF(D137=0,1,0))) -> 0
B138: Positive =0 | C138: 0
B139: Zero = 1
A141: Total | C141: =C129+C106+C75+C52+C36+C18 -> 60 | E141: =E129+E106+E75+E52+E36+E18 -> 22
A142: Percentage | C142: =E141/C141 -> 0.36666667

Sheet 4. Pharmaceutical
A1: Internal Credit Risk Score Sheet
A2: Quantitative Analysis (Service-Hospital&Clinic)
A3: File / Reference No: | B3: ='11. Detail Managment Report'!D2 -> Outpace Spinning Mills Ltd
A4: Borrowe Name | B4: ='11. Detail Managment Report'!D3 -> Outpace Spinning Mills Ltd
A5: Group Name (if any) | B5: ='11. Detail Managment Report'!D4 -> Outright Group
A6: Industry Name | B6: ='11. Detail Managment Report'!D5 -> 2. Textile | S6: Score | T6: =C142 -> 0.36666667 | U6: =1-T6 -> 0.63333333
A7: Latest CIB Status | B7: ='11. Detail Managment Report'!D6 -> Standard
A8: Audit Status | B8: ='11. Detail Managment Report'!D7 -> Unaudited
A9: Auditor Name | B9: ='11. Detail Managment Report'!D8 -> Dewan Nazrul Islam & Co.
A10: Analyst Name, Designations | B10: ='11. Detail Managment Report'!D9 -> Md. Matiur Rahman, SRM
A11: Verifier Name, Designation | B11: ='11. Detail Managment Report'!D10 -> Farhana Afrin, SM
A13: Date of Analysis | B13: ='11. Detail Managment Report'!D12 -> 45652
A14: Date of Financials | B14: ='11. Detail Managment Report'!D13 -> 45473
A16: Quantitative Indicators (60)
A17: Criteria | B17: Parameter | C17: Score | D17: Actual Parameter | E17: Score Obtained
A18: A. Leverage | C18: 10 | E18: =E19+E29 -> 4
A19: ='11. Detail Managment Report'!C18 -> 1. Financial Debt to Tangible Net Worth (DTN) | B19: Less than 0.75× | C19: 7 | D19: ='9. Inputs-Analysis'!D4 -> 3.9252586 | E19: =IF(D19<0,0,IF(D19<0.75,7,IF(D19<1,6,IF(D19<1.25,5,IF(D19<1.5,4,IF(D19<2,3,IF(D19<4,2,0))))))) -> 2
B20: 0.75x to 1.00x | C20: 6
B21: 1.01× to 1.25x | C21: 5
B22: 1.26 × to 1.50x | C22: 4
B23: 1.51× to 2.00x | C23: 3
B24: 2.01× to 3.00 x | C24: 2
B25: More than or equal to 3.01× | C25: 0
A29: ='11. Detail Managment Report'!C19 -> 2. Financial Debt to Total Assets (DTA) | B29: Less than 0.45x | C29: 3 | D29: ='9. Inputs-Analysis'!D7 -> 0.78528911 | E29: =IF(D29<0,0,IF(D29<0.45,3,IF(D29<0.8,2,IF(D29<0.99,1,0)))) -> 2
B30: 0.45x to 0.74x | C30: 2
B31: 0.74x to 0.99x | C31: 1
B32: Greater than 1.00× | C32: 0
A36: B. Liquidity | C36: 10 | E36: =E37+E45 -> 6
A37: ='11. Detail Managment Report'!C21 -> 1. Current Ratio (CR) | B37: Greater than 1.50× | C37: 7 | D37: ='9. Inputs-Analysis'!D11 -> 1.0405522 | E37: =IF(D37>1.5,7,IF(D37>=1.01,6,IF(D37>=0.75,5,IF(D37>=0.51,3,IF(D37>=0.35,2,0))))) -> 6
B38: 1.01× to 1.50x | C38: 6
B39: 0.75× to 1x | C39: 5
B40: 0.51× to 0.75x | C40: 3
B41: 0.35x to 0.50x | C41: 2
B42: less than or equal to 0.35 | C42: 0
A45: ='11. Detail Managment Report'!C22 -> 2. Cash Ratio (Cash) | B45: Greater than 0. 10x | C45: 3 | D45: ='9. Inputs-Analysis'!D10 -> 0.0061472341 | E45: =IF(D45>0.1,3,IF(D45>=0.05,2,IF(D45>=0.03,1,0))) -> 0
B46: 0.05x to 0. 01 x | C46: 2
B47: 0.03x to 0. 05x | C47: 1
B48: Less than 0.03x | C48: 0
A52: C. Profitability | C52: 10 | E52: =E53+E62+E69 -> 3
A53: ='11. Detail Managment Report'!C24 -> 1. Net Profit Margin (NPM) | B53: Greater than 8.00% | C53: 5 | D53: ='9. Inputs-Analysis'!D15 -> 0.054896988 | E53: =IF(D53>7%,5,IF(D53>=7%,4,IF(D53>=5%,3,IF(D53>=3%,2,IF(D53>=1%,1,0))))) -> 3
B54: 7.00% to 8.00% | C54: 4
B55: 5.00% to 7.00% | C55: 3
B56: 3.00% to 5.00% | C56: 2
B57: 1.00% to3.00% | C57: 1
B58: Less than or equal to 1% | C58: 0
A62: ='11. Detail Managment Report'!C25 -> 2. Return on Assets (ROA) | B62: Greater than 4.5% | C62: 3 | D62: ='9. Inputs-Analysis'!D18 -> 0.019426111 | E62: =IF(D62>4.5%,3,IF(D62>=3.01%,2,IF(D62>=2.01%,1,0))) -> 0
B63: 3.01% to 4.50% | C63: 2
B64: 2.01% to 3.00% | C64: 1
B65: Less than 2% | C65: 0
A69: ='11. Detail Managment Report'!C26 -> 3. Operating Profit to Operating Assets (OPOA) | B69: Greater than 10% | C69: 2 | D69: ='9. Inputs-Analysis'!D21 -> 0.04652054 | E69: =IF(D69>10%,2,IF(D69>=5.01%,1,0)) -> 0
B70: 5.01% to 9.00% | C70: 1
B71: Less than or equal to 5% | C71: 0
A75: D. Coverage | C75: 15 | E75: =E76+E83+E93+E100 -> 6
A76: ='11. Detail Managment Report'!C28 -> 1. Interest Coverage (IC) | B76: Greater than 4x | C76: 3 | D76: ='9. Inputs-Analysis'!D24 -> 2.1640484 | E76: =IF(D76>4,3,IF(D76>=3.01,2,IF(D76>=1.01,1,0))) -> 1
B77: 3.0x to 4.00x | C77: 2
B78: 1.01x to 3.00x | C78: 1
B79: Less than or equal to 1x | C79: 0
A83: ='11. Detail Managment Report'!C29 -> 2. Debt Service Coverage Ratio (DSCR) | D83: ='9. Inputs-Analysis'!D27 -> 1.4160266 | E83: =IF(D83>2.5,5,IF(D83>=2,4,IF(D83>=1.5,3,IF(D83>=1,2,IF(D83>=0.5,1,0))))) -> 2
B84: Greater than 2.50x | C84: 5
B85: 2.00x to 2.50x | C85: 4
B86: 1.50x to 2.00x | C86: 3
B87: 1.25x to 1.49 x | C87: 2
B88: 1.01x to 1.24x | C88: 1
B89: Less than or equal to 1x | C89: 0
A93: ='11. Detail Managment Report'!C30 -> 3. Operating Cashflow to Debt Ratio (CDR) | B93: More than 0.25x | C93: 4 | D93: ='9. Inputs-Analysis'!D30 -> 0.033545581 | E93: =IF(D93>0.25,4,IF(D93>0.15,3,IF(D93>0.1,2,IF(D93>-0.05,1,0)))) -> 1
B94: 0.15x to 0.25x | C94: 3
B95: 0.10x to 0.15x | C95: 2
B96: 0.05x to 0.10x | C96: 1
B97: Less than 0.05x | C97: 0
A100: ='11. Detail Managment Report'!C31 -> 4. Cashflow Coverage Ratio (CCR) | B100: More than 1.5x | C100: 3 | D100: ='9. Inputs-Analysis'!D33 -> 0.76522361 | E100: =IF(D100>1.5,3,IF(D100>=0.25,2,0)) -> 2
B101: 0.51x to 1.50x | C101: 2
B102: Less than or equal to 0.5x | C102: 0
A106: E. Operational Efficiency | C106: 10 | E106: =E107+E115+E122 -> 2
A107: ='11. Detail Managment Report'!C33 -> 1. Stock Turnover Days (STD) | B107: Less than 120 days | C107: 4 | D107: ='9. Inputs-Analysis'!D36 -> 823.7278 | E107: =IF(D107<120,4,IF(D107<150,3,IF(D107<180,1,0))) -> 0
B108: 120 to 150 days | C108: 3
B109: 150 to 180 days | C109: 1
B110: More than 180 days | C110: 0
A115: ='11. Detail Managment Report'!C34 -> 2. Trade Debtor Collection Days (TDCD) | B115: Less than 45 days | C115: 3 | D115: ='9. Inputs-Analysis'!D39 -> 89.219452 | E115: =IF(D115<45,3,IF(D115<60,2,IF(D115<90,1,0))) -> 1
B116: 45 days to 60 days | C116: 2
B117: 60 days to 90 days | C117: 1
B118: More than or equal to 90 days | C118: 0
A122: ='11. Detail Managment Report'!C35 -> 3. Asset Turnover (AT) | B122: Greater than 80% | C122: 3 | D122: ='9. Inputs-Analysis'!D42 -> 0.35386479 | E122: =IF(D122>80%,3,IF(D122>=51%,2,IF(D122>=31%,1,0))) -> 1
B123: 51% to 80% | C123: 2
B124: 31% to 50% | C124: 1
B125: Less than or equal to 30% | C125: 0
A129: F. Earning Quality | C129: 5 | E129: =E130+E137 -> 1
A130: ='11. Detail Managment Report'!C37 -> 1. Operating Cash Flow to Sales (CFS) | B130: Greater than 10% | C130: 3 | D130: ='9. Inputs-Analysis'!D45 -> 0.074443631 | E130: =IF(D130>10%,3,IF(D130>=9%,2,IF(D130>=5%,1,0))) -> 1
B131: 9.00% to 10.00% | C131: 2
B132: 5.00% to 9.00% | C132: 1
B133: Less than 5% | C133: 0
A137: ='11. Detail Managment Report'!C38 -> 2. Cashflow based accrual ratio (CAR) | B137: Negative = 2 | C137: 2 | D137: ='9. Inputs-Analysis'!D48 -> 0.0077292885 | E137: =IF(D137<0,2,IF(D137>0,0,IF(D137=0,1,0))) -> 0
B138: Positive =2 | C138: 0
B139: Zero = 1
A141: Total | C141: =C129+C106+C75+C52+C36+C18 -> 60 | E141: =E129+E106+E75+E52+E36+E18 -> 22
A142: Percentage | C142: =E141/C141 -> 0.36666667

Sheet 5. Chemical
A1: Internal Credit Risk Score Sheet
A2: Quantitative Analysis (Service-Hospital&Clinic)
A3: File / Reference No: | B3: ='11. Detail Managment Report'!D2 -> Outpace Spinning Mills Ltd
A4: Borrowe Name | B4: ='11. Detail Managment Report'!D3 -> Outpace Spinning Mills Ltd
A5: Group Name (if any) | B5: ='11. Detail Managment Report'!D4 -> Outright Group
A6: Industry Name | B6: ='11. Detail Managment Report'!D5 -> 2. Textile | S6: Score | T6: =C142 -> 0.38333333 | U6: =1-T6 -> 0.61666667
A7: Latest CIB Status | B7: ='11. Detail Managment Report'!D6 -> Standard
A8: Audit Status | B8: ='11. Detail Managment Report'!D7 -> Unaudited
A9: Auditor Name | B9: ='11. Detail Managment Report'!D8 -> Dewan Nazrul Islam & Co.
A10: Analyst Name, Designations | B10: ='11. Detail Managment Report'!D9 -> Md. Matiur Rahman, SRM
A11: Verifier Name, Designation | B11: ='11. Detail Managment Report'!D10 -> Farhana Afrin, SM
A13: Date of Analysis | B13: ='11. Detail Managment Report'!D12 -> 45652
A14: Date of Financials | B14: ='11. Detail Managment Report'!D13 -> 45473
A16: Quantitative Indicators (60)
A17: Criteria | B17: Parameter | C17: Score | D17: Actual Parameter | E17: Score Obtained
A18: A. Leverage | C18: 10 | E18: =E19+E29 -> 1
A19: ='11. Detail Managment Report'!C18 -> 1. Financial Debt to Tangible Net Worth (DTN) | B19: Less than 0.55× | C19: 7 | D19: ='9. Inputs-Analysis'!D4 -> 3.9252586 | E19: =IF(D19<0,0,IF(D19<0.55,7,IF(D19<=1,6,IF(D19<=1.25,5,IF(D19<=1.5,4,IF(D19<=2,3,IF(D19<=3.5,2,0))))))) -> 0
B20: 0.55x to 1.0x | C20: 6
B21: 1.01× to 1.25x | C21: 5
B22: 1.26x × to 1.50x | C22: 4
B23: 1.51× to 2.0x | C23: 3
B24: 2.01× to 3.00 x | C24: 2
B25: More than or equal to 3.01× | C25: 0
A29: ='11. Detail Managment Report'!C19 -> 2. Financial Debt to Total Assets (DTA) | B29: Less than 0.25x | C29: 3 | D29: ='9. Inputs-Analysis'!D7 -> 0.78528911 | E29: =IF(D29<0,0,IF(D29<0.25,3,IF(D29<0.74,2,IF(D29<0.99,1,0)))) -> 1
B30: 0.25x to 0.74x | C30: 2
B31: 0.74x to 0.99x | C31: 1
B32: More than 1.00× | C32: 0
A36: B. Liquidity | C36: 10 | E36: =E37+E45 -> 6
A37: ='11. Detail Managment Report'!C21 -> 1. Current Ratio (CR) | B37: Greater than 1.50× | C37: 7 | D37: ='9. Inputs-Analysis'!D11 -> 1.0405522 | E37: =IF(D37>1.5,7,IF(D37>=1.01,6,IF(D37>=0.75,5,IF(D37>=0.51,3,IF(D37>=0.35,2,0))))) -> 6
B38: 1.01× to 1.50 x | C38: 6
B39: .75x to 1x | C39: 5
B40: .51× to .75x | C40: 3
B41: 0.35x to 0.50x | C41: 2
B42: Less than or equal .35 | C42: 0
A45: ='11. Detail Managment Report'!C22 -> 2. Cash Ratio (Cash) | B45: Greater than 0.07x | C45: 3 | D45: ='9. Inputs-Analysis'!D10 -> 0.0061472341 | E45: =IF(D45>0.07,3,IF(D45>=0.04,2,IF(D45>=0.02,1,0))) -> 0
B46: 0.04 to 0. 07 x | C46: 2
B47: 0.02x to 0. 04x | C47: 1
B48: Less than 0.02x | C48: 0
A52: C. Profitability | C52: 10 | E52: =E53+E62+E69 -> 4
A53: ='11. Detail Managment Report'!C24 -> 1. Net Profit Margin (NPM) | B53: Greater than 6.00% | C53: 5 | D53: ='9. Inputs-Analysis'!D15 -> 0.054896988 | E53: =IF(D53>6%,5,IF(D53>=5%,4,IF(D53>=4%,3,IF(D53>=3%,2,IF(D53>=1%,1,0))))) -> 4
B54: 5% to 6.00% | C54: 4
B55: 4% to 5% | C55: 3
B56: 3% to4% | C56: 2
B57: 1% to3% | C57: 1
B58: Less than or equal to 1% | C58: 0
A62: ='11. Detail Managment Report'!C25 -> 2. Return on Assets (ROA) | B62: Greater than 4% | C62: 3 | D62: ='9. Inputs-Analysis'!D18 -> 0.019426111 | E62: =IF(D62>4%,3,IF(D62>=3.01%,2,IF(D62>=2.01%,1,0))) -> 0
B63: 3.01% to 4.00% | C63: 2
B64: 2.01% to 3.00% | C64: 1
B65: Less than 2% | C65: 0
A69: ='11. Detail Managment Report'!C26 -> 3. Operating Profit to Operating Assets (OPOA) | B69: Greater than 8% | C69: 2 | D69: ='9. Inputs-Analysis'!D21 -> 0.04652054 | E69: =IF(D69>8%,2,IF(D69>=5.01%,1,0)) -> 0
B70: 5.01% to 8% | C70: 1
B71: Less than of equal to 5% | C71: 0
A75: D. Coverage | C75: 15 | E75: =E76+E83+E93+E100 -> 7
A76: ='11. Detail Managment Report'!C28 -> 1. Interest Coverage (IC) | B76: More than 3x | C76: 3 | D76: ='9. Inputs-Analysis'!D24 -> 2.1640484 | E76: =IF(D76>3,3,IF(D76>=2.01,2,IF(D76>=1.01,1,0))) -> 2
B77: 2.01x- 3x | C77: 2
B78: 1.01x-2.00x | C78: 1
B79: Less than or equal to 1x | C79: 0
A83: ='11. Detail Managment Report'!C29 -> 2. Debt Service Coverage Ratio (DSCR) | D83: ='9. Inputs-Analysis'!D27 -> 1.4160266 | E83: =IF(D83>2.5,5,IF(D83>=2,4,IF(D83>=1.5,3,IF(D83>=1,2,IF(D83>=0.5,1,0))))) -> 2
B84: Greater than 2.50x | C84: 5
B85: 2.x to 2.5x | C85: 4
B86: 1.5x to 2x | C86: 3
B87: 1.25x to 1.49 x | C87: 2
B88: 1.01x to 1.24x | C88: 1
B89: Less than or equal to 1x | C89: 0
A93: ='11. Detail Managment Report'!C30 -> 3. Operating Cashflow to Debt Ratio (CDR) | B93: More than .25x | C93: 4 | D93: ='9. Inputs-Analysis'!D30 -> 0.033545581 | E93: =IF(D93>0.25,4,IF(D93>=0.15,3,IF(D93>=0.1,2,IF(D93>=-0.05,1,0)))) -> 1
B94: .15x to .25x | C94: 3
B95: .1x to .15x | C95: 2
B96: .05x to .10x | C96: 1
B97: less than .05x | C97: 0
A100: ='11. Detail Managment Report'!C31 -> 4. Cashflow Coverage Ratio (CCR) | B100: More than 1 times | C100: 3 | D100: ='9. Inputs-Analysis'!D33 -> 0.76522361 | E100: =IF(D100>1,3,IF(D100>=0.5,2,IF(D100>=-0.1,1,0))) -> 2
B101: 0.50 time to 1. times | C101: 2
B102: 0..25 ime to .50imes | C102: 1
B103: less than .25 | C103: 0
A106: E. Operational Efficiency | C106: 10 | E106: =E107+E115+E122 -> 2
A107: ='11. Detail Managment Report'!C33 -> 1. Stock Turnover Days (STD) | B107: Less than 90 days | C107: 4 | D107: ='9. Inputs-Analysis'!D36 -> 823.7278 | E107: =IF(D107<90,4,IF(D107<=100,3,IF(D107<=120,2,IF(D107<=180,1,0)))) -> 0
B108: 90 to100 days | C108: 3
B109: 100 to 120 days | C109: 2
B110: 120 days to 180 days | C110: 1
B111: More than or equal to 180 days | C111: 0
A115: ='11. Detail Managment Report'!C34 -> 2. Trade Debtor Collection Days (TDCD) | B115: Less than 45 days | C115: 3 | D115: ='9. Inputs-Analysis'!D39 -> 89.219452 | E115: =IF(D115<45,3,IF(D115<60,2,IF(D115<90,1,0))) -> 1
B116: 45 days to 60 days | C116: 2
B117: 60 days to 90 days | C117: 1
B118: More than or equal to 90 days | C118: 0
A122: ='11. Detail Managment Report'!C35 -> 3. Asset Turnover (AT) | B122: More than 100% | C122: 3 | D122: ='9. Inputs-Analysis'!D42 -> 0.35386479 | E122: =IF(D122>100%,3,IF(D122>=51%,2,IF(D122>=31%,1,0))) -> 1
B123: 51% to 100% | C123: 2
B124: 31% to 50% | C124: 1
B125: Less than or equal to 30% | C125: 0
A129: F. Earning Quality | C129: 5 | E129: =E130+E137 -> 3
A130: ='11. Detail Managment Report'!C37 -> 1. Operating Cash Flow to Sales (CFS) | B130: More than 5% | C130: 3 | D130: ='9. Inputs-Analysis'!D45 -> 0.074443631 | E130: =IF(D130>5%,3,IF(D130>=3.01%,2,IF(D130>=2%,1,0))) -> 3
B131: 3.01% to 5% | C131: 2
B132: 2% to 3% | C132: 1
B133: Less than or equal to 2% | C133: 0
A137: ='11. Detail Managment Report'!C38 -> 2. Cashflow based accrual ratio (CAR) | B137: Negative = 2 | C137: 2 | D137: ='9. Inputs-Analysis'!D48 -> 0.0077292885 | E137: =IF(D137<0,2,IF(D137>0,0,IF(D137=0,1,0))) -> 0
B138: Positive =0 | C138: 0
B139: Zero = 1
A141: Total | C141: =C129+C106+C75+C52+C36+C18 -> 60 | E141: =E129+E106+E75+E52+E36+E18 -> 23
A142: Percentage | C142: =E141/C141 -> 0.38333333

Sheet 6. Fertilizer
A1: Internal Credit Risk Score Sheet
A2: Quantitative Analysis (Service-Hospital&Clinic)
A3: File / Reference No: | B3: ='11. Detail Managment Report'!D2 -> Outpace Spinning Mills Ltd
A4: Borrowe Name | B4: ='11. Detail Managment Report'!D3 -> Outpace Spinning Mills Ltd
A5: Group Name (if any) | B5: ='11. Detail Managment Report'!D4 -> Outright Group
A6: Industry Name | B6: ='11. Detail Managment Report'!D5 -> 2. Textile | S6: Score | T6: =C142 -> 0.36666667 | U6: =1-T6 -> 0.63333333
A7: Latest CIB Status | B7: ='11. Detail Managment Report'!D6 -> Standard
A8: Audit Status | B8: ='11. Detail Managment Report'!D7 -> Unaudited
A9: Auditor Name | B9: ='11. Detail Managment Report'!D8 -> Dewan Nazrul Islam & Co.
A10: Analyst Name, Designations | B10: ='11. Detail Managment Report'!D9 -> Md. Matiur Rahman, SRM
A11: Verifier Name, Designation | B11: ='11. Detail Managment Report'!D10 -> Farhana Afrin, SM
A13: Date of Analysis | B13: ='11. Detail Managment Report'!D12 -> 45652
A14: Date of Financials | B14: ='11. Detail Managment Report'!D13 -> 45473
A16: Quantitative Indicators (60)
A17: Criteria | B17: Parameter | C17: Score | D17: Actual Parameter | E17: Score Obtained
A18: A. Leverage | C18: 10 | E18: =E19+E29 -> 3
A19: ='11. Detail Managment Report'!C18 -> 1. Financial Debt to Tangible Net Worth (DTN) | B19: Less than 1.0× | C19: 7 | D19: ='9. Inputs-Analysis'!D4 -> 3.9252586 | E19: =IF(D19<0,0,IF(D19<1,7,IF(D19<=1.49,6,IF(D19<=1.99,5,IF(D19<=2.49,4,IF(D19<=3,3,IF(D19<=4.5,2,0))))))) -> 2
B20: 1.00x to 1.49x | C20: 6
B21: 1.50× to 1.99x | C21: 5
B22: 2.00 × to 2.49x | C22: 4
B23: 2.50× to 2.99x | C23: 3
B24: 3.00× to 3.49 x | C24: 2
B25: More than or equal to 3.50× | C25: 0
A29: ='11. Detail Managment Report'!C19 -> 2. Financial Debt to Total Assets (DTA) | B29: Less than 0.25x | C29: 3 | D29: ='9. Inputs-Analysis'!D7 -> 0.78528911 | E29: =IF(D29<0,0,IF(D29<0.25,3,IF(D29<=0.74,2,IF(D29<=0.99,1,0)))) -> 1
B30: 0.25x to 0.74x | C30: 2
B31: 0.74x to 0.99x | C31: 1
B32: More than 1.00× | C32: 0
A36: B. Liquidity | C36: 10 | E36: =E37+E45 -> 5
A37: ='11. Detail Managment Report'!C21 -> 1. Current Ratio (CR) | B37: Greater than 2.00× | C37: 7 | D37: ='9. Inputs-Analysis'!D11 -> 1.0405522 | E37: =IF(D37>2,7,IF(D37>=1.51,6,IF(D37>=1.01,5,IF(D37>=0.51,2,0)))) -> 5
B38: 1.51× to 2.00x | C38: 6
B39: 1.01× to 1.50 x | C39: 5
B40: .51× to 1.00x | C40: 2
B41: Less than or equal .50 | C41: 0
A45: ='11. Detail Managment Report'!C22 -> 2. Cash Ratio (Cash) | B45: Greater than 0. 20x | C45: 3 | D45: ='9. Inputs-Analysis'!D10 -> 0.0061472341 | E45: =IF(D45>0.2,3,IF(D45>=0.11,2,IF(D45>=0.06,1,0))) -> 0
B46: 0.11x to 0. 20 x | C46: 2
B47: 0.06x to 0. 10x | C47: 1
B48: Less than 0.06x | C48: 0
A52: C. Profitability | C52: 10 | E52: =E53+E62+E69 -> 3
A53: ='11. Detail Managment Report'!C24 -> 1. Net Profit Margin (NPM) | B53: Greater than 8% | C53: 5 | D53: ='9. Inputs-Analysis'!D15 -> 0.054896988 | E53: =IF(D53>8%,5,IF(D53>=6.01%,4,IF(D53>=4.01%,3,IF(D53>=2.01%,2,IF(D53>=1.01%,1,0))))) -> 3
B54: 6.01% to 8.00% | C54: 4
B55: 4.01% to 6.00% | C55: 3
B56: 2.01% to 4.00% | C56: 2
B57: 1.01% to 2.00% | C57: 1
B58: Less than or equal to 1% | C58: 0
A62: ='11. Detail Managment Report'!C25 -> 2. Return on Assets (ROA) | B62: Greater than 4.5% | C62: 3 | D62: ='9. Inputs-Analysis'!D18 -> 0.019426111 | E62: =IF(D62>4.5%,3,IF(D62>=3.01%,2,IF(D62>=2.01%,1,0))) -> 0
B63: 3.01% to 4.50% | C63: 2
B64: 2.01% to 3.00% | C64: 1
B65: Less than 2% | C65: 0
A69: ='11. Detail Managment Report'!C26 -> 3. Operating Profit to Operating Assets (OPOA) | B69: Greater than 8% | C69: 2 | D69: ='9. Inputs-Analysis'!D21 -> 0.04652054 | E69: =IF(D69>8%,2,IF(D69>=5.01%,1,0)) -> 0
B70: 5.01% to 8% | C70: 1
B71: Less than of equal to 5% | C71: 0
A75: D. Coverage | C75: 15 | E75: =E76+E83+E93+E100 -> 6
A76: ='11. Detail Managment Report'!C28 -> 1. Interest Coverage (IC) | B76: More than 4x | C76: 3 | D76: ='9. Inputs-Analysis'!D24 -> 2.1640484 | E76: =IF(D76>4,3,IF(D76>=3.01,2,IF(D76>=1.01,1,0))) -> 1
B77: 3.01x- 4x | C77: 2
B78: 1.01x-3.00x | C78: 1
B79: Less than or equal to 1x | C79: 0
A83: ='11. Detail Managment Report'!C29 -> 2. Debt Service Coverage Ratio (DSCR) | D83: ='9. Inputs-Analysis'!D27 -> 1.4160266 | E83: =IF(D83>4,5,IF(D83>=3.01,4,IF(D83>=2.01,3,IF(D83>=1,2,IF(D83>=0.5,1,0))))) -> 2
B84: Greater than 4.00x | C84: 5
B85: 3.01x to 4.00x | C85: 4
B86: 2.01x to 3.00x | C86: 3
B87: 1.51x to 2.0 x | C87: 2
B88: 1.01x to 1.51x | C88: 1
B89: Less than or equal to 1x | C89: 0
A93: ='11. Detail Managment Report'!C30 -> 3. Operating Cashflow to Debt Ratio (CDR) | B93: More than .5x | C93: 4 | D93: ='9. Inputs-Analysis'!D30 -> 0.033545581 | E93: =IF(D93>0.5,4,IF(D93>=0.3,3,IF(D93>=0.2,2,IF(D93>=-0.15,1,0)))) -> 1
B94: .35x to .5x | C94: 3
B95: .25x to .35x | C95: 2
B96: .15x to .10x | C96: 1
B97: less than .15x | C97: 0
A100: ='11. Detail Managment Report'!C31 -> 4. Cashflow Coverage Ratio (CCR) | B100: More than 1.5 times | C100: 3 | D100: ='9. Inputs-Analysis'!D33 -> 0.76522361 | E100: =IF(D100>1.5,3,IF(D100>=0.351,2,IF(D100>-0.2,1,0))) -> 2
B101: 0.51 time to 1.5 times | C101: 2
B102: Less than or equla to 0.5 time | C102: 0
A106: E. Operational Efficiency | C106: 10 | E106: =E107+E115+E122 -> 3
A107: ='11. Detail Managment Report'!C33 -> 1. Stock Turnover Days (STD) | B107: Less than 30 days | C107: 4 | D107: ='9. Inputs-Analysis'!D36 -> 823.7278 | E107: =IF(D107<30,4,IF(D107<=59,3,IF(D107<=74,2,IF(D107<=89,1,0)))) -> 0
B108: 30 to 59 days | C108: 3
B109: 60 to 74 days | C109: 2
B110: 75 days to 89 days | C110: 1
B111: More than or equal to 90 days | C111: 0
A115: ='11. Detail Managment Report'!C34 -> 2. Trade Debtor Collection Days (TDCD) | B115: Less than 60 days | C115: 3 | D115: ='9. Inputs-Analysis'!D39 -> 89.219452 | E115: =IF(D115<60,3,IF(D115<=120,2,IF(D115<=180,1,0))) -> 2
B116: 61 days to 120 days | C116: 2
B117: 121 days to 180 days | C117: 1
B118: More than or equal to 180 days | C118: 0
A122: ='11. Detail Managment Report'!C35 -> 3. Asset Turnover (AT) | B122: More than 100% | C122: 3 | D122: ='9. Inputs-Analysis'!D42 -> 0.35386479 | E122: =IF(D122>100%,3,IF(D122>=51%,2,IF(D122>=31%,1,0))) -> 1
B123: 51% to 100% | C123: 2
B124: 31% to 50% | C124: 1
B125: Less than or equal to 30% | C125: 0
A129: F. Earning Quality | C129: 5 | E129: =E130+E137 -> 2
A130: ='11. Detail Managment Report'!C37 -> 1. Operating Cash Flow to Sales (CFS) | B130: More than 10% | C130: 3 | D130: ='9. Inputs-Analysis'!D45 -> 0.074443631 | E130: =IF(D130>10%,3,IF(D130>=3.01%,2,IF(D130>=2.01%,1,0))) -> 2
B131: 3.01% to 10% | C131: 2
B132: 2.01% to 3% | C132: 1
B133: Less than or equal to 2% | C133: 0
A137: ='11. Detail Managment Report'!C38 -> 2. Cashflow based accrual ratio (CAR) | B137: Negative = 2 | C137: 2 | D137: ='9. Inputs-Analysis'!D48 -> 0.0077292885 | E137: =IF(D137<0,2,IF(D137>0,0,IF(D137=0,1,0))) -> 0
B138: Positive =0 | C138: 0
B139: Zero = 1
A141: Total | C141: =C129+C106+C75+C52+C36+C18 -> 60 | E141: =E129+E106+E75+E52+E36+E18 -> 22
A142: Percentage | C142: =E141/C141 -> 0.36666667

Sheet 7.Cement
A1: Internal Credit Risk Score Sheet
A2: Quantitative Analysis (Service-Hospital&Clinic)
A3: File / Reference No: | B3: ='11. Detail Managment Report'!D2 -> Outpace Spinning Mills Ltd
A4: Borrowe Name | B4: ='11. Detail Managment Report'!D3 -> Outpace Spinning Mills Ltd
A5: Group Name (if any) | B5: ='11. Detail Managment Report'!D4 -> Outright Group
A6: Industry Name | B6: ='11. Detail Managment Report'!D5 -> 2. Textile | S6: Score | T6: =C142 -> 0.4 | U6: =1-T6 -> 0.6
A7: Latest CIB Status | B7: ='11. Detail Managment Report'!D6 -> Standard
A8: Audit Status | B8: ='11. Detail Managment Report'!D7 -> Unaudited
A9: Auditor Name | B9: ='11. Detail Managment Report'!D8 -> Dewan Nazrul Islam & Co.
A10: Analyst Name, Designations | B10: ='11. Detail Managment Report'!D9 -> Md. Matiur Rahman, SRM
A11: Verifier Name, Designation | B11: ='11. Detail Managment Report'!D10 -> Farhana Afrin, SM
A13: Date of Analysis | B13: ='11. Detail Managment Report'!D12 -> 45652
A14: Date of Financials | B14: ='11. Detail Managment Report'!D13 -> 45473
A16: Quantitative Indicators (60)
A17: Criteria | B17: Parameter | C17: Score | D17: Actual Parameter | E17: Score Obtained
A18: A. Leverage | C18: 10 | E18: =E19+E29 -> 3
A19: ='11. Detail Managment Report'!C18 -> 1. Financial Debt to Tangible Net Worth (DTN) | B19: Less than 1.0× | C19: 7 | D19: ='9. Inputs-Analysis'!D4 -> 3.9252586 | E19: =IF(D19<=0,0,IF(D19<1,7,IF(D19<=1.49,6,IF(D19<=1.99,5,IF(D19<=2.49,4,IF(D19<=3,3,IF(D19<=4,2,0))))))) -> 2
B20: 1.00x to 1.49x | C20: 6
B21: 1.50× to 1.99x | C21: 5
B22: 2.00 × to 2.49x | C22: 4
B23: 2.50× to 2.99x | C23: 3
B24: 3.00× to 3.49 x | C24: 2
B25: More than or equal to 3.50× | C25: 0
A29: ='11. Detail Managment Report'!C19 -> 2. Financial Debt to Total Assets (DTA) | B29: Less than 0.45x | C29: 3 | D29: ='9. Inputs-Analysis'!D7 -> 0.78528911 | E29: =IF(D29<0,0,IF(D29<0.45,3,IF(D29<=0.74,2,IF(D29<=0.99,1,0)))) -> 1
B30: 0.45x to 0.74x | C30: 2
B31: 0.74x to 0.99x | C31: 1
B32: More than 1.00× | C32: 0
A36: B. Liquidity | C36: 10 | E36: =E37+E45 -> 6
A37: ='11. Detail Managment Report'!C21 -> 1. Current Ratio (CR) | B37: Greater than 1.50× | C37: 7 | D37: ='9. Inputs-Analysis'!D11 -> 1.0405522 | E37: =IF(D37>1.5,7,IF(D37>=1.01,6,IF(D37>=0.75,5,IF(D37>=0.51,3,IF(D37>=0.35,2,0))))) -> 6
B38: 1.01× to 1.50 x | C38: 6
B39: .75x to 1x | C39: 5
B40: .51× to .75x | C40: 3
B41: 0.35x to 0.50x | C41: 2
B42: Less than or equal .35 | C42: 0
A45: ='11. Detail Managment Report'!C22 -> 2. Cash Ratio (Cash) | B45: Greater than 0.06x | C45: 3 | D45: ='9. Inputs-Analysis'!D10 -> 0.0061472341 | E45: =IF(D45>0.06,3,IF(D45>=0.03,2,IF(D45>=0.01,1,0))) -> 0
B46: 0.03 to 0. 06 x | C46: 2
B47: 0.02x to 0. 03x | C47: 1
B48: Less than 0.02x | C48: 0
A52: C. Profitability | C52: 10 | E52: =E53+E62+E69 -> 4
A53: ='11. Detail Managment Report'!C24 -> 1. Net Profit Margin (NPM) | B53: Greater than 6.00% | C53: 5 | D53: ='9. Inputs-Analysis'!D15 -> 0.054896988 | E53: =IF(D53>6%,5,IF(D53>=5%,4,IF(D53>=4%,3,IF(D53>=3%,2,IF(D53>=1%,1,0))))) -> 4
B54: 5% to 6.00% | C54: 4
B55: 4% to 5% | C55: 3
B56: 3% to4% | C56: 2
B57: 1% to3% | C57: 1
B58: Less than or equal to 1% | C58: 0
A62: ='11. Detail Managment Report'!C25 -> 2. Return on Assets (ROA) | B62: Greater than 4.5% | C62: 3 | D62: ='9. Inputs-Analysis'!D18 -> 0.019426111 | E62: =IF(D62>4.5%,3,IF(D62>=3.01%,2,IF(D62>=2.01%,1,0))) -> 0
B63: 3.01% to 4.50% | C63: 2
B64: 2.01% to 3.00% | C64: 1
B65: Less than 2% | C65: 0
A69: ='11. Detail Managment Report'!C26 -> 3. Operating Profit to Operating Assets (OPOA) | B69: Greater than 8% | C69: 2 | D69: ='9. Inputs-Analysis'!D21 -> 0.04652054 | E69: =IF(D69>8%,2,IF(D69>=5.01%,1,0)) -> 0
B70: 5.01% to 8% | C70: 1
B71: Less than of equal to 5% | C71: 0
